Workbook
Name DateCalc: #REF!:INDEX(#REF!,DAY(DATE(ABREA!$B$11,MATCH(ABREA!$C$11,#REF!,0)+1,0)))
Name DateCalc: #REF!:INDEX(#REF!,DAY(DATE('Accntng Clerk Salary Sample '!$B$11,MATCH('Accntng Clerk Salary Sample '!$C$11,#REF!,0)+1,0)))
Name DateCalc: #REF!:INDEX(#REF!,DAY(DATE(ACOMPAÑADO!$B$11,MATCH(ACOMPAÑADO!$C$11,#REF!,0)+1,0)))
Name DateCalc: Data!$C$2:INDEX(Data!$C$2:$C$32,DAY(DATE(ADELANTAR!$B$11,MATCH(ADELANTAR!$C$11,Data!$B$2:$B$13,0)+1,0)))
Name DateCalc: Data!$C$2:INDEX(Data!$C$2:$C$32,DAY(DATE('ADMIN (2)'!$E$10,MATCH('ADMIN (2)'!$F$10,Data!$B$2:$B$13,0)+1,0)))
Name DateCalc: #REF!:INDEX(#REF!,DAY(DATE(ADRIANO!$B$11,MATCH(ADRIANO!$C$11,#REF!,0)+1,0)))
Name DateCalc: #REF!:INDEX(#REF!,DAY(DATE(ALEJANDRINO!$B$11,MATCH(ALEJANDRINO!$C$11,#REF!,0)+1,0)))
Name DateCalc: #REF!:INDEX(#REF!,DAY(DATE(#REF!,MATCH(#REF!,#REF!,0)+1,0)))
Name DateCalc: #REF!:INDEX(#REF!,DAY(DATE(AURELIO!$B$11,MATCH(AURELIO!$C$11,#REF!,0)+1,0)))
Name DateCalc: #REF!:INDEX(#REF!,DAY(DATE(AZMAN!$B$11,MATCH(AZMAN!$C$11,#REF!,0)+1,0)))
Name DateCalc: #REF!:INDEX(#REF!,DAY(DATE(BARORO!$B$11,MATCH(BARORO!$C$11,#REF!,0)+1,0)))
Name DateCalc: #REF!:INDEX(#REF!,DAY(DATE(BASA!$B$11,MATCH(BASA!$C$11,#REF!,0)+1,0)))
Name DateCalc: Data!$C$2:INDEX(Data!$C$2:$C$32,DAY(DATE(BATUL!$A$10,MATCH(BATUL!$B$10,Data!$B$2:$B$13,0)+1,0)))
Name DateCalc: #REF!:INDEX(#REF!,DAY(DATE(BECARO!$B$11,MATCH(BECARO!$C$11,#REF!,0)+1,0)))
Name DateCalc: Data!$C$2:INDEX(Data!$C$2:$C$32,DAY(DATE('Bi-weekly Timesheet'!$C$9,MATCH('Bi-weekly Timesheet'!$D$9,Data!$B$2:$B$13,0)+1,0)))
Name DateCalc: #REF!:INDEX(#REF!,DAY(DATE(BUNGAY!$B$11,MATCH(BUNGAY!$C$11,#REF!,0)+1,0)))
Name DateCalc: #REF!:INDEX(#REF!,DAY(DATE(CAYAPAS!$B$11,MATCH(CAYAPAS!$C$11,#REF!,0)+1,0)))
Name DateCalc: Data!$C$2:INDEX(Data!$C$2:$C$32,DAY(DATE(COMOSO!$B$11,MATCH(COMOSO!$C$11,Data!$B$2:$B$13,0)+1,0)))
Name DateCalc: #REF!:INDEX(#REF!,DAY(DATE(CONSUELO!$B$11,MATCH(CONSUELO!$C$11,#REF!,0)+1,0)))
Name DateCalc: #REF!:INDEX(#REF!,DAY(DATE(COROSO!$B$11,MATCH(COROSO!$C$11,#REF!,0)+1,0)))
Name DateCalc: Data!$C$2:INDEX(Data!$C$2:$C$32,DAY(DATE(DAGOT!$B$9,MATCH(DAGOT!$C$9,Data!$B$2:$B$13,0)+1,0)))
Name DateCalc: #REF!:INDEX(#REF!,DAY(DATE('DELA CRUZ'!$B$11,MATCH('DELA CRUZ'!$C$11,#REF!,0)+1,0)))
Name DateCalc: #REF!:INDEX(#REF!,DAY(DATE(DIOLA!$B$11,MATCH(DIOLA!$C$11,#REF!,0)+1,0)))
Name DateCalc: #REF!:INDEX(#REF!,DAY(DATE(EDON!$B$10,MATCH(EDON!$C$10,#REF!,0)+1,0)))
Name DateCalc: #REF!:INDEX(#REF!,DAY(DATE(ELEAZAR!$B$11,MATCH(ELEAZAR!$C$11,#REF!,0)+1,0)))
Name DateCalc: Data!$C$2:INDEX(Data!$C$2:$C$32,DAY(DATE(ESTARES!$B$10,MATCH(ESTARES!$C$10,Data!$B$2:$B$13,0)+1,0)))
Name DateCalc: Data!$C$2:INDEX(Data!$C$2:$C$32,DAY(DATE('Fixed Salary - Sample'!$B$10,MATCH('Fixed Salary - Sample'!$C$10,Data!$B$2:$B$13,0)+1,0)))
Name DateCalc: #REF!:INDEX(#REF!,DAY(DATE(GABO!$B$11,MATCH(GABO!$C$11,#REF!,0)+1,0)))
Name DateCalc: #REF!:INDEX(#REF!,DAY(DATE(GAID!$B$11,MATCH(GAID!$C$11,#REF!,0)+1,0)))
Name DateCalc: #REF!:INDEX(#REF!,DAY(DATE(GALLARDO!$B$11,MATCH(GALLARDO!$C$11,#REF!,0)+1,0)))
Name DateCalc: #REF!:INDEX(#REF!,DAY(DATE(GUERZO!$B$11,MATCH(GUERZO!$C$11,#REF!,0)+1,0)))
Name DateCalc: #REF!:INDEX(#REF!,DAY(DATE(HERRERA!$B$11,MATCH(HERRERA!$C$11,#REF!,0)+1,0)))
Name DateCalc: #REF!:INDEX(#REF!,DAY(DATE(LAGROSA!$B$11,MATCH(LAGROSA!$C$11,#REF!,0)+1,0)))
Name DateCalc: #REF!:INDEX(#REF!,DAY(DATE(LEAL!$B$11,MATCH(LEAL!$C$11,#REF!,0)+1,0)))
Name DateCalc: #REF!:INDEX(#REF!,DAY(DATE(MACATANGAY!$B$11,MATCH(MACATANGAY!$C$11,#REF!,0)+1,0)))
Name DateCalc: #REF!:INDEX(#REF!,DAY(DATE(MALAZARTE!$B$11,MATCH(MALAZARTE!$C$11,#REF!,0)+1,0)))
Name DateCalc: #REF!:INDEX(#REF!,DAY(DATE(MOHAMMAD!$B$11,MATCH(MOHAMMAD!$C$11,#REF!,0)+1,0)))
Name DateCalc: #REF!:INDEX(#REF!,DAY(DATE(NICOLAS!$B$11,MATCH(NICOLAS!$C$11,#REF!,0)+1,0)))
Name DateCalc: #REF!:INDEX(#REF!,DAY(DATE(ORBISO!$B$11,MATCH(ORBISO!$C$11,#REF!,0)+1,0)))
Name DateCalc: Data!$C$2:INDEX(Data!$C$2:$C$32,DAY(DATE(PAALAN!$B$11,MATCH(PAALAN!$C$11,Data!$B$2:$B$13,0)+1,0)))
Name DateCalc: #REF!:INDEX(#REF!,DAY(DATE(PAREDES!$B$11,MATCH(PAREDES!$C$11,#REF!,0)+1,0)))
Name DateCalc: Data!$C$2:INDEX(Data!$C$2:$C$32,DAY(DATE(PATRICIO!$B$11,MATCH(PATRICIO!$C$11,Data!$B$2:$B$13,0)+1,0)))
Name DateCalc: Data!$C$2:INDEX(Data!$C$2:$C$32,DAY(DATE('Weekly Timesheet'!$C$9,MATCH('Weekly Timesheet'!$D$9,Data!$B$2:$B$13,0)+1,0)))
Name DateCalc: #REF!:INDEX(#REF!,DAY(DATE(RODRIGUEZ!$B$11,MATCH(RODRIGUEZ!$C$11,#REF!,0)+1,0)))
Name DateCalc: #REF!:INDEX(#REF!,DAY(DATE(RUIZ!$B$11,MATCH(RUIZ!$C$11,#REF!,0)+1,0)))
Name DateCalc: #REF!:INDEX(#REF!,DAY(DATE(#REF!,MATCH(#REF!,#REF!,0)+1,0)))
Name DateCalc: #REF!:INDEX(#REF!,DAY(DATE(SUCIA!$B$11,MATCH(SUCIA!$C$11,#REF!,0)+1,0)))
Name DateCalc: #REF!:INDEX(#REF!,DAY(DATE(TRIPOLI!$B$11,MATCH(TRIPOLI!$C$11,#REF!,0)+1,0)))
Name DateCalc: Data!$C$2:INDEX(Data!$C$2:$C$32,DAY(DATE('Weekly Timesheet'!$C$9,MATCH('Weekly Timesheet'!$D$9,Data!$B$2:$B$13,0)+1,0)))

Sheet Weekly Timesheet
B1: Weekly TimeSheet Calculator
B2: Wayne Enterprise | J2: How to use this template
B3: Employee Name: | D3: Alfred Pennyworth
B4: Department: | D4: Housekeeping | J4: Visit TrumpExcel.com for more Excel Templates
B5: First Line Manager: | D5: Bruce Wayne
C8: Year | D8: Month | E8: Date | F8: Weekend
C9: 2021 | D9: February | E9: 1 | F9: Sat & Sun
C11: Start Time | D11: Regular Hours | E11: Regular Pay (hourly) | F11: Overtime Pay (hourly)
C12: 0.33333333 | D12: 9 | E12: =576.71/8 -> 72.08875 | F12: =(E12*25%)+E12 -> 90.110938
B15: Day | C15: Date | D15: In Time | E15: Out Time | F15: Break Hrs | G15: Regular Hrs | H15: OT Hours | I15: Total Pay
B16: =DATE($C$9,MATCH($D$9,Data!$B$2:$B$13,0),'Weekly Timesheet'!$E$9) -> 44228 | C16: =DATE($C$9,MATCH($D$9,Data!$B$2:$B$13,0),'Weekly Timesheet'!$E$9) -> 44228 | D16: 0.33333333 | E16: 0.70833333 | F16: 1 | G16: =IFERROR(IF(AND(D16<>"",E16<>""),IF(D16>$C$12+TIME($D$12,($D$12-INT($D$12))*60,0),0,IF(E16>$C$12+TIME($D$12,($D$12-INT($D$12))*60,0),MIN(TIME($D$12,($D$12-INT($D$12))*60,0),($C$12+TIME($D$12,($D$12-INT($D$12))*60,0)-D16)),MIN(IF((E16-$C$12)<0,0,(E16-$C$12)),(E16-D16))))*24,"")-F16,"") -> 8 | H16: =IF(AND(D16<>"",E16<>""),((IF(D16<$C$12,MIN($C$12-D16,E16-D16),0)+IF(E16>$C$12+TIME($D$12,($D$12-INT($D$12))*60,0),MIN((E16-$C$12-TIME($D$12,($D$12-INT($D$12))*60,0)),(E16-D16)),0))*24),"") -> 0 | I16: =IFERROR(G16*IF(AND(ISNUMBER(SEARCH(TEXT(B16,"ddd"),$F$9)),Data!$F$2),$F$12,$E$12)+H16*$F$12,"") -> 576.71
B17: =B16+1 -> 44229 | C17: =C16+1 -> 44229 | D17: 0.33333333 | E17: 0.70833333 | F17: 1 | G17: =IFERROR(IF(AND(D17<>"",E17<>""),IF(D17>$C$12+TIME($D$12,($D$12-INT($D$12))*60,0),0,IF(E17>$C$12+TIME($D$12,($D$12-INT($D$12))*60,0),MIN(TIME($D$12,($D$12-INT($D$12))*60,0),($C$12+TIME($D$12,($D$12-INT($D$12))*60,0)-D17)),MIN(IF((E17-$C$12)<0,0,(E17-$C$12)),(E17-D17))))*24,"")-F17,"") -> 8 | H17: =IF(AND(D17<>"",E17<>""),((IF(D17<$C$12,MIN($C$12-D17,E17-D17),0)+IF(E17>$C$12+TIME($D$12,($D$12-INT($D$12))*60,0),MIN((E17-$C$12-TIME($D$12,($D$12-INT($D$12))*60,0)),(E17-D17)),0))*24),"") -> 0 | I17: =IFERROR(G17*IF(AND(ISNUMBER(SEARCH(TEXT(B17,"ddd"),$F$9)),Data!$F$2),$F$12,$E$12)+H17*$F$12,"") -> 576.71
B18: =B17+1 -> 44230 | C18: =C17+1 -> 44230 | D18: 0.33333333 | E18: 0.70833333 | F18: 1 | G18: =IFERROR(IF(AND(D18<>"",E18<>""),IF(D18>$C$12+TIME($D$12,($D$12-INT($D$12))*60,0),0,IF(E18>$C$12+TIME($D$12,($D$12-INT($D$12))*60,0),MIN(TIME($D$12,($D$12-INT($D$12))*60,0),($C$12+TIME($D$12,($D$12-INT($D$12))*60,0)-D18)),MIN(IF((E18-$C$12)<0,0,(E18-$C$12)),(E18-D18))))*24,"")-F18,"") -> 8 | H18: =IF(AND(D18<>"",E18<>""),((IF(D18<$C$12,MIN($C$12-D18,E18-D18),0)+IF(E18>$C$12+TIME($D$12,($D$12-INT($D$12))*60,0),MIN((E18-$C$12-TIME($D$12,($D$12-INT($D$12))*60,0)),(E18-D18)),0))*24),"") -> 0 | I18: =IFERROR(G18*IF(AND(ISNUMBER(SEARCH(TEXT(B18,"ddd"),$F$9)),Data!$F$2),$F$12,$E$12)+H18*$F$12,"") -> 576.71
B19: =B18+1 -> 44231 | C19: =C18+1 -> 44231 | D19: 0.33333333 | E19: 0.70833333 | F19: 1 | G19: =IFERROR(IF(AND(D19<>"",E19<>""),IF(D19>$C$12+TIME($D$12,($D$12-INT($D$12))*60,0),0,IF(E19>$C$12+TIME($D$12,($D$12-INT($D$12))*60,0),MIN(TIME($D$12,($D$12-INT($D$12))*60,0),($C$12+TIME($D$12,($D$12-INT($D$12))*60,0)-D19)),MIN(IF((E19-$C$12)<0,0,(E19-$C$12)),(E19-D19))))*24,"")-F19,"") -> 8 | H19: =IF(AND(D19<>"",E19<>""),((IF(D19<$C$12,MIN($C$12-D19,E19-D19),0)+IF(E19>$C$12+TIME($D$12,($D$12-INT($D$12))*60,0),MIN((E19-$C$12-TIME($D$12,($D$12-INT($D$12))*60,0)),(E19-D19)),0))*24),"") -> 0 | I19: =IFERROR(G19*IF(AND(ISNUMBER(SEARCH(TEXT(B19,"ddd"),$F$9)),Data!$F$2),$F$12,$E$12)+H19*$F$12,"") -> 576.71
B20: =B19+1 -> 44232 | C20: =C19+1 -> 44232 | D20: 0.33333333 | E20: 0.70833333 | F20: 1 | G20: =IFERROR(IF(AND(D20<>"",E20<>""),IF(D20>$C$12+TIME($D$12,($D$12-INT($D$12))*60,0),0,IF(E20>$C$12+TIME($D$12,($D$12-INT($D$12))*60,0),MIN(TIME($D$12,($D$12-INT($D$12))*60,0),($C$12+TIME($D$12,($D$12-INT($D$12))*60,0)-D20)),MIN(IF((E20-$C$12)<0,0,(E20-$C$12)),(E20-D20))))*24,"")-F20,"") -> 8 | H20: =IF(AND(D20<>"",E20<>""),((IF(D20<$C$12,MIN($C$12-D20,E20-D20),0)+IF(E20>$C$12+TIME($D$12,($D$12-INT($D$12))*60,0),MIN((E20-$C$12-TIME($D$12,($D$12-INT($D$12))*60,0)),(E20-D20)),0))*24),"") -> 0 | I20: =IFERROR(G20*IF(AND(ISNUMBER(SEARCH(TEXT(B20,"ddd"),$F$9)),Data!$F$2),$F$12,$E$12)+H20*$F$12,"") -> 576.71
B21: =B20+1 -> 44233 | C21: =C20+1 -> 44233 | D21: 0.33333333 | E21: 0.70833333 | F21: 1 | G21: =IFERROR(IF(AND(D21<>"",E21<>""),IF(D21>$C$12+TIME($D$12,($D$12-INT($D$12))*60,0),0,IF(E21>$C$12+TIME($D$12,($D$12-INT($D$12))*60,0),MIN(TIME($D$12,($D$12-INT($D$12))*60,0),($C$12+TIME($D$12,($D$12-INT($D$12))*60,0)-D21)),MIN(IF((E21-$C$12)<0,0,(E21-$C$12)),(E21-D21))))*24,"")-F21,"") -> 8 | H21: =IF(AND(D21<>"",E21<>""),((IF(D21<$C$12,MIN($C$12-D21,E21-D21),0)+IF(E21>$C$12+TIME($D$12,($D$12-INT($D$12))*60,0),MIN((E21-$C$12-TIME($D$12,($D$12-INT($D$12))*60,0)),(E21-D21)),0))*24),"") -> 0 | I21: =IFERROR(G21*IF(AND(ISNUMBER(SEARCH(TEXT(B21,"ddd"),$F$9)),Data!$F$2),$F$12,$E$12)+H21*$F$12,"") -> 720.8875
B22: =B21+1 -> 44234 | C22: =C21+1 -> 44234 | G22: =IFERROR(IF(AND(D22<>"",E22<>""),IF(D22>$C$12+TIME($D$12,($D$12-INT($D$12))*60,0),0,IF(E22>$C$12+TIME($D$12,($D$12-INT($D$12))*60,0),MIN(TIME($D$12,($D$12-INT($D$12))*60,0),($C$12+TIME($D$12,($D$12-INT($D$12))*60,0)-D22)),MIN(IF((E22-$C$12)<0,0,(E22-$C$12)),(E22-D22))))*24,"")-F22,"") | H22: =IF(AND(D22<>"",E22<>""),((IF(D22<$C$12,MIN($C$12-D22,E22-D22),0)+IF(E22>$C$12+TIME($D$12,($D$12-INT($D$12))*60,0),MIN((E22-$C$12-TIME($D$12,($D$12-INT($D$12))*60,0)),(E22-D22)),0))*24),"") | I22: =IFERROR(G22*IF(AND(ISNUMBER(SEARCH(TEXT(B22,"ddd"),$F$9)),Data!$F$2),$F$12,$E$12)+H22*$F$12,"")
E24: Weekly Summary | F24: =SUM(F16:F22) -> 6 | G24: =SUM(G16:G22) -> 48 | H24: =SUM(H16:H22) -> 0 | I24: =SUM(I16:I22) -> 3604.4375

Sheet Bi-weekly Timesheet
B1: Weekly TimeSheet Calculator
B2: [Company Name] | J2: How to use this template
B3: Employee Name:
B4: Department: | J4: Visit TrumpExcel.com for more Excel Templates
B5: First Line Manager:
C8: Year | D8: Month | E8: Date | F8: Weekend
C9: 2022 | D9: April | E9: 10 | F9: Sat & Sun
C11: Start Time | D11: Regular Hours | E11: Regular Pay (hourly) | F11: Overtime Pay (hourly)
C12: 0.375 | D12: 6.5 | E12: 30 | F12: 50
B15: Day | C15: Date | D15: In Time | E15: Out Time | F15: Break Hrs | G15: Regular Hrs | H15: OT Hours | I15: Total Pay
B16: =DATE($C$9,MATCH($D$9,Data!$B$2:$B$13,0),'Bi-weekly Timesheet'!$E$9) -> 44661 | C16: =DATE($C$9,MATCH($D$9,Data!$B$2:$B$13,0),'Bi-weekly Timesheet'!$E$9) -> 44661 | D16: 0.375 | E16: 0.75 | F16: 1 | G16: =IFERROR(IF(AND(D16<>"",E16<>""),IF(D16>$C$12+TIME($D$12,($D$12-INT($D$12))*60,0),0,IF(E16>$C$12+TIME($D$12,($D$12-INT($D$12))*60,0),MIN(TIME($D$12,($D$12-INT($D$12))*60,0),($C$12+TIME($D$12,($D$12-INT($D$12))*60,0)-D16)),MIN(IF((E16-$C$12)<0,0,(E16-$C$12)),(E16-D16))))*24,"")-F16,"") -> 5.5 | H16: =IF(AND(D16<>"",E16<>""),((IF(D16<$C$12,MIN($C$12-D16,E16-D16),0)+IF(E16>$C$12+TIME($D$12,($D$12-INT($D$12))*60,0),MIN((E16-$C$12-TIME($D$12,($D$12-INT($D$12))*60,0)),(E16-D16)),0))*24),"") -> 2.5 | I16: =IFERROR(G16*IF(AND(ISNUMBER(SEARCH(TEXT(B16,"ddd"),$F$9)),Data!$F$2),$F$12,$E$12)+H16*$F$12,"") -> 400
B17: =B16+1 -> 44662 | C17: =C16+1 -> 44662 | G17: =IFERROR(IF(AND(D17<>"",E17<>""),IF(D17>$C$12+TIME($D$12,($D$12-INT($D$12))*60,0),0,IF(E17>$C$12+TIME($D$12,($D$12-INT($D$12))*60,0),MIN(TIME($D$12,($D$12-INT($D$12))*60,0),($C$12+TIME($D$12,($D$12-INT($D$12))*60,0)-D17)),MIN(IF((E17-$C$12)<0,0,(E17-$C$12)),(E17-D17))))*24,"")-F17,"") | H17: =IF(AND(D17<>"",E17<>""),((IF(D17<$C$12,MIN($C$12-D17,E17-D17),0)+IF(E17>$C$12+TIME($D$12,($D$12-INT($D$12))*60,0),MIN((E17-$C$12-TIME($D$12,($D$12-INT($D$12))*60,0)),(E17-D17)),0))*24),"") | I17: =IFERROR(G17*IF(AND(ISNUMBER(SEARCH(TEXT(B17,"ddd"),$F$9)),Data!$F$2),$F$12,$E$12)+H17*$F$12,"")
B18: =B17+1 -> 44663 | C18: =C17+1 -> 44663 | G18: =IFERROR(IF(AND(D18<>"",E18<>""),IF(D18>$C$12+TIME($D$12,($D$12-INT($D$12))*60,0),0,IF(E18>$C$12+TIME($D$12,($D$12-INT($D$12))*60,0),MIN(TIME($D$12,($D$12-INT($D$12))*60,0),($C$12+TIME($D$12,($D$12-INT($D$12))*60,0)-D18)),MIN(IF((E18-$C$12)<0,0,(E18-$C$12)),(E18-D18))))*24,"")-F18,"") | H18: =IF(AND(D18<>"",E18<>""),((IF(D18<$C$12,MIN($C$12-D18,E18-D18),0)+IF(E18>$C$12+TIME($D$12,($D$12-INT($D$12))*60,0),MIN((E18-$C$12-TIME($D$12,($D$12-INT($D$12))*60,0)),(E18-D18)),0))*24),"") | I18: =IFERROR(G18*IF(AND(ISNUMBER(SEARCH(TEXT(B18,"ddd"),$F$9)),Data!$F$2),$F$12,$E$12)+H18*$F$12,"")
B19: =B18+1 -> 44664 | C19: =C18+1 -> 44664 | G19: =IFERROR(IF(AND(D19<>"",E19<>""),IF(D19>$C$12+TIME($D$12,($D$12-INT($D$12))*60,0),0,IF(E19>$C$12+TIME($D$12,($D$12-INT($D$12))*60,0),MIN(TIME($D$12,($D$12-INT($D$12))*60,0),($C$12+TIME($D$12,($D$12-INT($D$12))*60,0)-D19)),MIN(IF((E19-$C$12)<0,0,(E19-$C$12)),(E19-D19))))*24,"")-F19,"") | H19: =IF(AND(D19<>"",E19<>""),((IF(D19<$C$12,MIN($C$12-D19,E19-D19),0)+IF(E19>$C$12+TIME($D$12,($D$12-INT($D$12))*60,0),MIN((E19-$C$12-TIME($D$12,($D$12-INT($D$12))*60,0)),(E19-D19)),0))*24),"") | I19: =IFERROR(G19*IF(AND(ISNUMBER(SEARCH(TEXT(B19,"ddd"),$F$9)),Data!$F$2),$F$12,$E$12)+H19*$F$12,"")
B20: =B19+1 -> 44665 | C20: =C19+1 -> 44665 | G20: =IFERROR(IF(AND(D20<>"",E20<>""),IF(D20>$C$12+TIME($D$12,($D$12-INT($D$12))*60,0),0,IF(E20>$C$12+TIME($D$12,($D$12-INT($D$12))*60,0),MIN(TIME($D$12,($D$12-INT($D$12))*60,0),($C$12+TIME($D$12,($D$12-INT($D$12))*60,0)-D20)),MIN(IF((E20-$C$12)<0,0,(E20-$C$12)),(E20-D20))))*24,"")-F20,"") | H20: =IF(AND(D20<>"",E20<>""),((IF(D20<$C$12,MIN($C$12-D20,E20-D20),0)+IF(E20>$C$12+TIME($D$12,($D$12-INT($D$12))*60,0),MIN((E20-$C$12-TIME($D$12,($D$12-INT($D$12))*60,0)),(E20-D20)),0))*24),"") | I20: =IFERROR(G20*IF(AND(ISNUMBER(SEARCH(TEXT(B20,"ddd"),$F$9)),Data!$F$2),$F$12,$E$12)+H20*$F$12,"")
B21: =B20+1 -> 44666 | C21: =C20+1 -> 44666 | G21: =IFERROR(IF(AND(D21<>"",E21<>""),IF(D21>$C$12+TIME($D$12,($D$12-INT($D$12))*60,0),0,IF(E21>$C$12+TIME($D$12,($D$12-INT($D$12))*60,0),MIN(TIME($D$12,($D$12-INT($D$12))*60,0),($C$12+TIME($D$12,($D$12-INT($D$12))*60,0)-D21)),MIN(IF((E21-$C$12)<0,0,(E21-$C$12)),(E21-D21))))*24,"")-F21,"") | H21: =IF(AND(D21<>"",E21<>""),((IF(D21<$C$12,MIN($C$12-D21,E21-D21),0)+IF(E21>$C$12+TIME($D$12,($D$12-INT($D$12))*60,0),MIN((E21-$C$12-TIME($D$12,($D$12-INT($D$12))*60,0)),(E21-D21)),0))*24),"") | I21: =IFERROR(G21*IF(AND(ISNUMBER(SEARCH(TEXT(B21,"ddd"),$F$9)),Data!$F$2),$F$12,$E$12)+H21*$F$12,"")
B22: =B21+1 -> 44667 | C22: =C21+1 -> 44667 | G22: =IFERROR(IF(AND(D22<>"",E22<>""),IF(D22>$C$12+TIME($D$12,($D$12-INT($D$12))*60,0),0,IF(E22>$C$12+TIME($D$12,($D$12-INT($D$12))*60,0),MIN(TIME($D$12,($D$12-INT($D$12))*60,0),($C$12+TIME($D$12,($D$12-INT($D$12))*60,0)-D22)),MIN(IF((E22-$C$12)<0,0,(E22-$C$12)),(E22-D22))))*24,"")-F22,"") | H22: =IF(AND(D22<>"",E22<>""),((IF(D22<$C$12,MIN($C$12-D22,E22-D22),0)+IF(E22>$C$12+TIME($D$12,($D$12-INT($D$12))*60,0),MIN((E22-$C$12-TIME($D$12,($D$12-INT($D$12))*60,0)),(E22-D22)),0))*24),"") | I22: =IFERROR(G22*IF(AND(ISNUMBER(SEARCH(TEXT(B22,"ddd"),$F$9)),Data!$F$2),$F$12,$E$12)+H22*$F$12,"")
B23: =B22+1 -> 44668 | C23: =C22+1 -> 44668 | G23: =IFERROR(IF(AND(D23<>"",E23<>""),IF(D23>$C$12+TIME($D$12,($D$12-INT($D$12))*60,0),0,IF(E23>$C$12+TIME($D$12,($D$12-INT($D$12))*60,0),MIN(TIME($D$12,($D$12-INT($D$12))*60,0),($C$12+TIME($D$12,($D$12-INT($D$12))*60,0)-D23)),MIN(IF((E23-$C$12)<0,0,(E23-$C$12)),(E23-D23))))*24,"")-F23,"") | H23: =IF(AND(D23<>"",E23<>""),((IF(D23<$C$12,MIN($C$12-D23,E23-D23),0)+IF(E23>$C$12+TIME($D$12,($D$12-INT($D$12))*60,0),MIN((E23-$C$12-TIME($D$12,($D$12-INT($D$12))*60,0)),(E23-D23)),0))*24),"") | I23: =IFERROR(G23*IF(AND(ISNUMBER(SEARCH(TEXT(B23,"ddd"),$F$9)),Data!$F$2),$F$12,$E$12)+H23*$F$12,"")
B24: =B23+1 -> 44669 | C24: =C23+1 -> 44669 | G24: =IFERROR(IF(AND(D24<>"",E24<>""),IF(D24>$C$12+TIME($D$12,($D$12-INT($D$12))*60,0),0,IF(E24>$C$12+TIME($D$12,($D$12-INT($D$12))*60,0),MIN(TIME($D$12,($D$12-INT($D$12))*60,0),($C$12+TIME($D$12,($D$12-INT($D$12))*60,0)-D24)),MIN(IF((E24-$C$12)<0,0,(E24-$C$12)),(E24-D24))))*24,"")-F24,"") | H24: =IF(AND(D24<>"",E24<>""),((IF(D24<$C$12,MIN($C$12-D24,E24-D24),0)+IF(E24>$C$12+TIME($D$12,($D$12-INT($D$12))*60,0),MIN((E24-$C$12-TIME($D$12,($D$12-INT($D$12))*60,0)),(E24-D24)),0))*24),"") | I24: =IFERROR(G24*IF(AND(ISNUMBER(SEARCH(TEXT(B24,"ddd"),$F$9)),Data!$F$2),$F$12,$E$12)+H24*$F$12,"")
B25: =B24+1 -> 44670 | C25: =C24+1 -> 44670 | G25: =IFERROR(IF(AND(D25<>"",E25<>""),IF(D25>$C$12+TIME($D$12,($D$12-INT($D$12))*60,0),0,IF(E25>$C$12+TIME($D$12,($D$12-INT($D$12))*60,0),MIN(TIME($D$12,($D$12-INT($D$12))*60,0),($C$12+TIME($D$12,($D$12-INT($D$12))*60,0)-D25)),MIN(IF((E25-$C$12)<0,0,(E25-$C$12)),(E25-D25))))*24,"")-F25,"") | H25: =IF(AND(D25<>"",E25<>""),((IF(D25<$C$12,MIN($C$12-D25,E25-D25),0)+IF(E25>$C$12+TIME($D$12,($D$12-INT($D$12))*60,0),MIN((E25-$C$12-TIME($D$12,($D$12-INT($D$12))*60,0)),(E25-D25)),0))*24),"") | I25: =IFERROR(G25*IF(AND(ISNUMBER(SEARCH(TEXT(B25,"ddd"),$F$9)),Data!$F$2),$F$12,$E$12)+H25*$F$12,"")
B26: =B25+1 -> 44671 | C26: =C25+1 -> 44671 | G26: =IFERROR(IF(AND(D26<>"",E26<>""),IF(D26>$C$12+TIME($D$12,($D$12-INT($D$12))*60,0),0,IF(E26>$C$12+TIME($D$12,($D$12-INT($D$12))*60,0),MIN(TIME($D$12,($D$12-INT($D$12))*60,0),($C$12+TIME($D$12,($D$12-INT($D$12))*60,0)-D26)),MIN(IF((E26-$C$12)<0,0,(E26-$C$12)),(E26-D26))))*24,"")-F26,"") | H26: =IF(AND(D26<>"",E26<>""),((IF(D26<$C$12,MIN($C$12-D26,E26-D26),0)+IF(E26>$C$12+TIME($D$12,($D$12-INT($D$12))*60,0),MIN((E26-$C$12-TIME($D$12,($D$12-INT($D$12))*60,0)),(E26-D26)),0))*24),"") | I26: =IFERROR(G26*IF(AND(ISNUMBER(SEARCH(TEXT(B26,"ddd"),$F$9)),Data!$F$2),$F$12,$E$12)+H26*$F$12,"")
B27: =B26+1 -> 44672 | C27: =C26+1 -> 44672 | G27: =IFERROR(IF(AND(D27<>"",E27<>""),IF(D27>$C$12+TIME($D$12,($D$12-INT($D$12))*60,0),0,IF(E27>$C$12+TIME($D$12,($D$12-INT($D$12))*60,0),MIN(TIME($D$12,($D$12-INT($D$12))*60,0),($C$12+TIME($D$12,($D$12-INT($D$12))*60,0)-D27)),MIN(IF((E27-$C$12)<0,0,(E27-$C$12)),(E27-D27))))*24,"")-F27,"") | H27: =IF(AND(D27<>"",E27<>""),((IF(D27<$C$12,MIN($C$12-D27,E27-D27),0)+IF(E27>$C$12+TIME($D$12,($D$12-INT($D$12))*60,0),MIN((E27-$C$12-TIME($D$12,($D$12-INT($D$12))*60,0)),(E27-D27)),0))*24),"") | I27: =IFERROR(G27*IF(AND(ISNUMBER(SEARCH(TEXT(B27,"ddd"),$F$9)),Data!$F$2),$F$12,$E$12)+H27*$F$12,"")
B28: =B27+1 -> 44673 | C28: =C27+1 -> 44673 | G28: =IFERROR(IF(AND(D28<>"",E28<>""),IF(D28>$C$12+TIME($D$12,($D$12-INT($D$12))*60,0),0,IF(E28>$C$12+TIME($D$12,($D$12-INT($D$12))*60,0),MIN(TIME($D$12,($D$12-INT($D$12))*60,0),($C$12+TIME($D$12,($D$12-INT($D$12))*60,0)-D28)),MIN(IF((E28-$C$12)<0,0,(E28-$C$12)),(E28-D28))))*24,"")-F28,"") | H28: =IF(AND(D28<>"",E28<>""),((IF(D28<$C$12,MIN($C$12-D28,E28-D28),0)+IF(E28>$C$12+TIME($D$12,($D$12-INT($D$12))*60,0),MIN((E28-$C$12-TIME($D$12,($D$12-INT($D$12))*60,0)),(E28-D28)),0))*24),"") | I28: =IFERROR(G28*IF(AND(ISNUMBER(SEARCH(TEXT(B28,"ddd"),$F$9)),Data!$F$2),$F$12,$E$12)+H28*$F$12,"")
B29: =B28+1 -> 44674 | C29: =C28+1 -> 44674 | G29: =IFERROR(IF(AND(D29<>"",E29<>""),IF(D29>$C$12+TIME($D$12,($D$12-INT($D$12))*60,0),0,IF(E29>$C$12+TIME($D$12,($D$12-INT($D$12))*60,0),MIN(TIME($D$12,($D$12-INT($D$12))*60,0),($C$12+TIME($D$12,($D$12-INT($D$12))*60,0)-D29)),MIN(IF((E29-$C$12)<0,0,(E29-$C$12)),(E29-D29))))*24,"")-F29,"") | H29: =IF(AND(D29<>"",E29<>""),((IF(D29<$C$12,MIN($C$12-D29,E29-D29),0)+IF(E29>$C$12+TIME($D$12,($D$12-INT($D$12))*60,0),MIN((E29-$C$12-TIME($D$12,($D$12-INT($D$12))*60,0)),(E29-D29)),0))*24),"") | I29: =IFERROR(G29*IF(AND(ISNUMBER(SEARCH(TEXT(B29,"ddd"),$F$9)),Data!$F$2),$F$12,$E$12)+H29*$F$12,"")
E31: Bi-weekly Summary | F31: =SUM(F16:F29) -> 1 | G31: =SUM(G16:G29) -> 5.5 | H31: =SUM(H16:H29) -> 2.5 | I31: =SUM(I16:I29) -> 400

Sheet 15
B3: BACS CONSTRUCTION SERVICES AND ENGINEERING CONSULTANCY
B4: PAYROLL SUMMARY
B5: COVERED DATE : | C5: AUG. 11-25, 2022
B6: PERIOD : | C6: 44804
B8: NAME | C8: DESIGNATION | D8: Hours/Days | E8: Basic Pay | F8: Less: Absent, Late and Undertime | G8: Total Basic Pay | H8: Overtime | I8: Holiday & Premium Pay | J8: GROSS WAGE | K8: De Minimis | O8: DEDUCTIONS | U8: TOTAL DEDUCTION | V8: NET PAY
L10: PHIC | M10: HDMF | N10: INSURANCE | O10: Income Tax | P10: COMM. ALLOWANCE | Q10: Other Deduction | R10: SSS Loan | S10: CASH ADVANCE/LOAN | T10: FOR RETRO
N11: BPI
B13: Bacosa , Cesario Jr | C13: CEO/ PRESIDENT | E13: 15000 | K13: 2500 | N13: 147.17 | P13: 899.75 | Q13: 5000 | U13: =SUM(L13:S13) -> 6046.92 | V13: =(E13+K13)-U13 -> 11453.08
B14: Villegas, Gabby G. | C14: Project Manager | E14: 13250 | K14: 4250 | L14: 397.5 | M14: 300 | N14: 147.17 | O14: =1133.33/2 -> 566.665 | P14: =500/2 -> 250 | Q14: 187.5 | S14: 1791.67 | U14: =SUM(L14:S14) -> 3640.505 | V14: =(E14+K14)-U14 -> 13859.495
B15: Germina, Mark Jayson H | C15: Operation Manager | E15: 11250 | K15: 4250 | L15: 337.5 | M15: 300 | N15: 147.17 | O15: =533.4/2 -> 266.7 | P15: =500/2 -> 250 | Q15: 187.5 | S15: 1770.83 | U15: =SUM(L15:S15) -> 3259.7 | V15: =(E15+K15)-U15 -> 12240.3
B16: Beltran, Lyn M. | C16: Admin Manager | E16: 12750 | K16: 4250 | L16: 382.5 | M16: 500 | N16: 147.17 | O16: =1133.33/2 -> 566.665 | P16: 250 | S16: 3480 | U16: =SUM(L16:S16) -> 5326.335 | V16: =(E16+K16)-U16 -> 11673.665
B17: Bacosa, Katherine J. | C17: Finance Manager | E17: 11000 | K17: 3500 | N17: 147.17 | P17: 837.25 | Q17: 5000 | S17: 1500 | U17: =SUM(L17:S17) -> 7484.42 | V17: =(E17+K17)-U17 -> 7015.58
B18: PROJECT MANAGEMENT | V18: =(E18+K18)-U18 -> 0
B19: Bocala, Kevin O. | C19: Technical Head | E19: 9000 | F19: =#REF! -> #REF! | G19: =E19-F19 -> #REF! | J19: =G19+H19+I19 -> #REF! | L19: 225 | M19: 100 | N19: 109.23 | U19: =SUM(L19:S19) -> 434.23 | V19: =(J19+K19)-U19 -> #REF!
B20: Comoso, Mayca | C20: Office Staff | E20: =COMOSO!N34 -> 7045.3846 | F20: =COMOSO!N35 -> 327.69231 | G20: =E20-F20 -> 6717.6923 | H20: =COMOSO!N37 -> 0 | I20: =COMOSO!N38 -> 1474.6154 | J20: =G20+H20+I20 -> 8192.3077 | L20: 225.64 | M20: 100 | N20: 71.29 | U20: =SUM(L20:S20) -> 396.93 | V20: =(J20+K20)-U20 -> 7795.3777
B21: Dagot, Gie Boy | C21: Technical Staff | E21: =DAGOT!N37 -> 11087.238 | F21: =DAGOT!N38 -> 596.79456 | G21: =E21-F21 -> 10490.444 | I21: =DAGOT!N41 -> 0 | J21: =G21+H21+I21 -> 10490.444 | L21: 225.64 | M21: 100 | N21: 71.29 | U21: =SUM(L21:S21) -> 396.93 | V21: =(J21+K21)-U21 -> 10093.514
B22: Sucia, Van Lloyd | C22: Technical Staff | E22: =#REF! -> #REF! | F22: =#REF! -> #REF! | G22: =E22-F22 -> #REF! | I22: =#REF! -> #REF! | J22: =G22+H22+I22 -> #REF! | L22: 225.64 | M22: 100 | N22: 71.29 | U22: =SUM(L22:S22) -> 396.93 | V22: =(J22+K22)-U22 -> #REF!
B23: Malazarte, Jan Kayle Mari | C23: Technical Staff | E23: =#REF! -> #REF! | F23: =#REF! -> #REF! | G23: =E23-F23 -> #REF! | I23: =#REF! -> #REF! | J23: =G23+H23+I23 -> #REF! | L23: 225.64 | M23: 100 | N23: 71.29 | U23: =SUM(L23:S23) -> 396.93 | V23: =(J23+K23)-U23 -> #REF!
B24: Soledad, Princess Joy | C24: Project Survey Head | E24: 10250 | G24: =E24-F24 -> 10250 | J24: =G24+H24+I24 -> 10250 | L24: 307.5 | M24: 100 | N24: 109.23 | U24: =SUM(L24:S24) -> 516.73 | V24: =(J24+K24)-U24 -> 9733.27
B25: Batul, Shajanli Grace | C25: Procurement Officer | E25: =BATUL!M32 -> 10020 | F25: =BATUL!M33 -> 0 | G25: =E25-F25 -> 10020 | H25: =BATUL!M35 -> 0 | I25: =BATUL!M36 -> 0 | J25: =G25+H25+I25 -> 10020 | L25: 180 | M25: 100 | N25: 142.58 | U25: =SUM(L25:S25) -> 422.58 | V25: =(J25+K25)-U25 -> 9597.42
B26: Juanich, Paul Jerome | C26: Draftsman | E26: =#REF! -> #REF! | F26: =#REF! -> #REF! | G26: =E26-F26 -> #REF! | I26: =#REF! -> #REF! | J26: =G26+H26+I26 -> #REF! | N26: 285.16 | U26: =SUM(L26:S26) -> 285.16 | V26: =(J26+K26)-U26 -> #REF!
B27: Manaeg, Harold | C27: Technical Staff | E27: =ADELANTAR!N34 -> 4305 | F27: =ADELANTAR!N35 -> 312.28333 | G27: =E27-F27 -> 3992.7167 | H27: =ADELANTAR!N37 -> 153.75 | I27: =ADELANTAR!N38 -> 0 | J27: =G27+H27+I27 -> 4146.4667 | L27: 180 | M27: 100 | N27: 285.16 | U27: =SUM(L27:S27) -> 565.16 | V27: =(J27+K27)-U27 -> 3581.3067
B28: Alejandrino, Rey Mark | C28: Laboratory Operator | E28: =#REF! -> #REF! | F28: =#REF! -> #REF! | G28: =E28-F28 -> #REF! | H28: =#REF! -> #REF! | I28: =#REF! -> #REF! | J28: =G28+H28+I28 -> #REF! | L28: 180 | M28: 100 | N28: 171.1 | U28: =SUM(L28:S28) -> 451.1 | V28: =(J28+K28)-U28 -> #REF!
B29: Paredes, Matthew | C29: Part Time Draftsman | E29: =#REF! -> #REF! | F29: =#REF! -> #REF! | G29: =E29-F29 -> #REF! | H29: =#REF! -> #REF! | I29: =#REF! -> #REF! | J29: =G29+H29+I29 -> #REF!
B30: ADMIN | G30: =E30-F30 -> 0 | J30: =G30+H30+I30 -> 0 | V30: =(J30+K30)-U30 -> 0
B31: Gaid, Dorabel Y. | C31: Admin Assistant | E31: =#REF! -> #REF! | F31: =#REF! -> #REF! | G31: =E31-F31 -> #REF! | H31: =#REF! -> #REF! | I31: =#REF! -> #REF! | J31: =G31+H31+I31 -> #REF! | L31: 240 | M31: 500 | N31: 147.17 | R31: 1015.19 | S31: 1000 | U31: =SUM(L31:S31) -> 2902.36 | V31: =(J31+K31)-U31 -> #REF!
B32: Guerzo, Jovelyn H. | C32: EHS Head | E32: 9250 | G32: =E32-F32 -> 9250 | J32: =G32+H32+I32 -> 9250 | L32: 277.5 | M32: 100 | N32: 109.23 | U32: =SUM(L32:S32) -> 486.73 | V32: =(J32+K32)-U32 -> 8763.27
B33: Jamelo, Elfren | C33: Amansinaya In-charge | E33: 7500 | G33: =E33-F33 -> 7500 | J33: =G33+H33+I33 -> 7500 | K33: 2000 | L33: 225 | N33: 109.23 | U33: =SUM(L33:S33) -> 334.23 | V33: =(J33+K33)-U33 -> 9165.77
B34: Macatangay, Michael | C34: Company Driver | E34: 7500 | G34: =E34-F34 -> 7500 | J34: =G34+H34+I34 -> 7500 | K34: 1000 | L34: 225 | M34: 100 | N34: 142.58 | U34: =SUM(L34:S34) -> 467.58 | V34: =(J34+K34)-U34 -> 8032.42
B35: Galedo, Joshua | C35: General Services Staff | E35: 7500 | F35: =#REF! -> #REF! | G35: =E35-F35 -> #REF! | J35: =G35+H35+I35 -> #REF! | L35: 225 | M35: 100 | N35: 71.29 | U35: =SUM(L35:S35) -> 396.29 | V35: =(J35+K35)-U35 -> #REF!
B36: Aurelio, Roderic | C36: Utility | E36: =#REF! -> #REF! | F36: =#REF! -> #REF! | G36: =E36-F36 -> #REF! | I36: =#REF! -> #REF! | J36: =G36+H36+I36 -> #REF! | L36: 150 | M36: 100 | U36: =SUM(L36:S36) -> 250 | V36: =(J36+K36)-U36 -> #REF!
B37: FINANCE | G37: =E37-F37 -> 0 | J37: =G37+H37+I37 -> 0 | V37: =(J37+K37)-U37 -> 0
B38: Acompañado, Nancy | C38: A/R Officer | E38: =#REF! -> #REF! | F38: =#REF! -> #REF! | G38: =E38-F38 -> #REF! | H38: =#REF! -> #REF! | I38: =#REF! -> #REF! | J38: =G38+H38+I38 -> #REF! | L38: 240 | M38: 100 | N38: 71.29 | Q38: 292 | U38: =SUM(L38:S38) -> 703.29 | V38: =(J38+K38)-U38 -> #REF!
B39: Consuelo, Regine | C39: Finance Assistant | E39: 8500 | F39: =#REF! -> #REF! | G39: =E39-F39 -> #REF! | J39: =G39+H39+I39 -> #REF! | L39: 255 | M39: 100 | N39: 71.29 | Q39: 292 | U39: =SUM(L39:S39) -> 718.29 | V39: =(J39+K39)-U39 -> #REF!
B40: Dobleros, Reden | C40: Accounting Clerk | E40: =#REF! -> #REF! | F40: =#REF! -> #REF! | G40: =E40-F40 -> #REF! | H40: =#REF! -> #REF! | I40: =#REF! -> #REF! | J40: =G40+H40+I40 -> #REF! | L40: 180 | M40: 100 | N40: 142.58 | U40: =SUM(L40:S40) -> 422.58 | V40: =(J40+K40)-U40 -> #REF!
B41: OPERATION | G41: =E41-F41 -> 0 | J41: =G41+H41+I41 -> 0 | V41: =(J41+K41)-U41 -> 0
B42: Cayapas, Reymond I | C42: Project Team Leader | D42: =#REF! -> #REF! | E42: =#REF! -> #REF! | F42: =#REF! -> #REF! | G42: =E42-F42 -> #REF! | J42: =G42+H42+I42 -> #REF! | L42: 180 | M42: 100 | U42: =SUM(L42:S42) -> 280 | V42: =(J42+K42)-U42 -> #REF!
B43: Morados, Moses | C43: Laborer | D43: =#REF! -> #REF! | E43: =#REF! -> #REF! | F43: =#REF! -> #REF! | G43: =E43-F43 -> #REF! | I43: =#REF! -> #REF! | J43: =G43+H43+I43 -> #REF! | L43: 180 | U43: =SUM(L43:S43) -> 180 | V43: =(J43+K43)-U43 -> #REF!
B44: Suprecencia, Melvin | C44: Project Supervisor | D44: 12D | E44: 8500 | G44: =E44-F44 -> 8500 | K44: 2500 | L44: 255 | M44: 100 | N44: 218.46 | U44: =SUM(L44:S44) -> 573.46 | V44: =(J44+K44)-U44 -> 1926.54
B45: Mitchell, Rey John | C45: Project Supervisor | D45: 12D | E45: 8500 | G45: =E45-F45 -> 8500 | K45: 2500 | L45: 255 | M45: 100 | N45: 142.58 | U45: =SUM(L45:S45) -> 497.58 | V45: =(J45+K45)-U45 -> 2002.42
B46: Samog-oy, Christian Paul | C46: Project Team Leader | D46: 12D | E46: 6500 | G46: =E46-F46 -> 6500 | K46: 2500 | L46: 210 | M46: 100 | N46: 218.46 | T46: 1798.71 | U46: =SUM(L46:S46) -> 528.46 | V46: =(G46+K46+T46)-U46 -> 10270.25
B47: Apgao, Edel John | C47: Project Team Leader | D47: 12D | E47: 6000 | G47: =E47-F47 -> 6000 | K47: 2500 | L47: 195 | M47: 100 | N47: 142.58 | U47: =SUM(L47:S47) -> 437.58 | V47: =(J47+K47)-U47 -> 2062.42
B48: Delos Santos, Gemar | C48: Project Team Leader | D48: 12D | E48: 6000 | G48: =E48-F48 -> 6000 | K48: 2500 | L48: 180 | M48: 100 | N48: 142.58 | U48: =SUM(L48:S48) -> 422.58 | V48: =(J48+K48)-U48 -> 2077.42
B49: Basig, Froilan | C49: Project Team Leader | D49: 12D | E49: 6000 | G49: =E49-F49 -> 6000 | K49: 2500 | L49: 180 | M49: 100 | N49: 218.46 | U49: =SUM(L49:S49) -> 498.46 | V49: =(J49+K49)-U49 -> 2001.54
B50: Abis, Oscar | C50: Laborer | D50: 12D | E50: 5000 | G50: =E50-F50 -> 5000 | K50: 2500 | L50: 150 | U50: =SUM(L50:S50) -> 150 | V50: =(J50+K50)-U50 -> 2350
B51: Hilado, Jonathan | C51: Laborer | D51: 12D | E51: 5000 | G51: =E51-F51 -> 5000 | K51: 2500 | U51: =SUM(L51:S51) -> 0 | V51: =(J51+K51)-U51 -> 2500
B52: Lagrosa, Noibo | C52: Laborer | D52: 12D | E52: 5000 | G52: =E52-F52 -> 5000 | K52: 2500 | L52: 150 | M52: 100 | U52: =SUM(L52:S52) -> 250 | V52: =(J52+K52)-U52 -> 2250
B53: Badang, Jayson | C53: Laborer | D53: 12D | E53: 5000 | G53: =E53-F53 -> 5000 | K53: 2500 | L53: 150 | M53: 100 | U53: =SUM(L53:S53) -> 250 | V53: =(J53+K53)-U53 -> 2250
B54: Becaro, Ronald | C54: Laborer | D54: 12D | E54: 5000 | G54: =E54-F54 -> 5000 | K54: 2500 | L54: 150 | U54: =SUM(L54:S54) -> 150 | V54: =(J54+K54)-U54 -> 2350
B55: Gallo, Aldrin | C55: Laborer | D55: 12D | E55: 5000 | G55: =E55-F55 -> 5000 | K55: 2500 | U55: =SUM(L55:S55) -> 0 | V55: =(J55+K55)-U55 -> 2500
B56: Bungay, Dennis | C56: Laborer | D56: 12D | E56: 5000 | G56: =E56-F56 -> 5000 | K56: 2500 | L56: 150 | M56: 100 | U56: =SUM(L56:S56) -> 250 | V56: =(J56+K56)-U56 -> 2250
B57: Padilla, Benigno | C57: Laborer | D57: 12D | E57: 5000 | G57: =E57-F57 -> 5000 | K57: 2500 | L57: 150 | U57: =SUM(L57:S57) -> 150 | V57: =(J57+K57)-U57 -> 2350
B58: Elevera, Dondon | C58: Laborer | D58: 12D | E58: 5000 | G58: =E58-F58 -> 5000 | K58: 2500 | L58: 150 | U58: =SUM(L58:S58) -> 150 | V58: =(J58+K58)-U58 -> 2350
B59: Andales, Joel | C59: Laborer | D59: 12D | E59: 5000 | G59: =E59-F59 -> 5000 | K59: 2500 | L59: 150 | M59: 100 | U59: =SUM(L59:S59) -> 250 | V59: =(J59+K59)-U59 -> 2250
B60: Tesado, Christopher | C60: Laborer | D60: 12D | E60: 5000 | G60: =E60-F60 -> 5000 | K60: 2500 | L60: 150 | M60: 100 | U60: =SUM(L60:S60) -> 250 | V60: =(J60+K60)-U60 -> 2250
B61: Diamad, Donald | C61: Laborer | D61: 12D | E61: 5000 | G61: =E61-F61 -> 5000 | K61: 2500 | L61: 150 | U61: =SUM(L61:S61) -> 150 | V61: =(J61+K61)-U61 -> 2350
B62: Isaak Jardin | C62: Laborer | D62: 12D | E62: 5000 | G62: =E62-F62 -> 5000 | K62: 2500 | L62: 150 | M62: 100
B64: Total Payroll | E64: =SUM(E13:E62) -> #REF! | F64: =SUM(F13:F62) -> #REF! | G64: =E64-F64 -> #REF! | H64: =SUM(H13:H62) -> #REF! | I64: =SUM(I13:I62) -> #REF! | K64: =SUM(K13:K62) -> 69250 | N64: =SUM(N13:N62) -> 4071.25 | O64: =SUM(O13:O62) -> 1400.03 | P64: =SUM(P13:P62) -> 2487 | Q64: =SUM(Q13:Q62) -> 10959 | R64: =SUM(R13:R62) -> 1015.19 | S64: =SUM(S12:S62) -> 9542.5 | T64: =SUM(T12:T62) -> 1798.71 | U64: =SUM(U13:U62) -> 42120.03 | V64: =SUM(V13:V62) -> #REF!
B66: Prepared By: | G66: Checked By: | O66: Approved By: | T66: Noted by:
B68: DORABEL Y. GAID | G68: LYN M. BELTRAN | O68: KATHERINE J. BACOSA | T68: CESARIO A. BACOSA JR.
B69: Admin Assistant | G69: Admn Manager | O69: Finance Manager | T69: CEO/President

Sheet Sheet2

Sheet 30
B3: BACS CONSTRUCTION SERVICES AND ENGINEERING CONSULTANCY
B4: PAYROLL SUMMARY
B5: COVERED DATE : | C5: JUNE 11-25, 2022
B6: PERIOD : | C6: 44742
B8: NAME | C8: DESIGNATION | D8: Hours/Days | E8: Basic Pay | F8: Less: Absent, Late and Undertime | G8: Total Basic Pay | H8: Overtime | I8: Holiday & Premium Pay | J8: GROSS WAGE | K8: De Minimis | N8: DEDUCTIONS | T8: TOTAL DEDUCTION | U8: NET PAY
L10: SSS | M10: INSURANCE | N10: Income Tax | O10: COMM. ALLOWANCE | P10: Other Deduction | Q10: SSS Loan | R10: TRAVEL | S10: LOAN
M11: BPI
B13: Bacosa , Cesario Jr | C13: CEO/ PRESIDENT | E13: 15000 | K13: 2500 | M13: 147.17 | O13: 899.75 | P13: 5000 | R13: 500 | T13: =SUM(L13:R13) -> 6546.92 | U13: =(E13+K13)-T13 -> 10953.08
B14: Villegas, Gabby G. | C14: Project Manager | E14: 13250 | K14: 4250 | L14: 1125 | M14: 147.17 | N14: =1133.33/2 -> 566.665 | O14: =500/2 -> 250 | P14: 187.5 | R14: 1000 | S14: 2691.67 | T14: =SUM(L14:R14) -> 3276.335 | U14: =(E14+K14)-T14 -> 14223.665
B15: Germina, Mark Jayson H | C15: Operation Manager | E15: 11250 | K15: 4250 | L15: 1012.5 | M15: 147.17 | N15: =533.4/2 -> 266.7 | O15: =500/2 -> 250 | P15: 187.5 | R15: 500 | S15: 2250 | T15: =SUM(L15:R15) -> 2363.87 | U15: =(E15+K15)-T15 -> 13136.13
B16: Beltran, Lyn M. | C16: Admin Manager | E16: 12750 | K16: 4250 | L16: 1125 | M16: 147.17 | N16: =1133.33/2 -> 566.665 | O16: 250 | R16: 1700 | T16: =SUM(L16:R16) -> 3788.835 | U16: =(E16+K16)-T16 -> 13211.165
B17: Bacosa, Katherine J. | C17: Finance Manager | E17: 11000 | K17: 3500 | M17: 147.17 | O17: 837.25 | P17: 5000 | R17: 500 | T17: =SUM(L17:R17) -> 6484.42 | U17: =(E17+K17)-T17 -> 8015.58
B18: PROJECT MANAGEMENT | U18: =(E18+K18)-T18 -> 0
B19: Bocala, Kevin O. | C19: Technical Head | D19: =#REF! -> #REF! | E19: 9000 | F19: =#REF! -> #REF! | G19: =E19-F19 -> #REF! | J19: =G19+H19+I19 -> #REF! | L19: 810 | M19: 109.23 | S19: 2500 | T19: =SUM(L19:R19) -> 919.23 | U19: =(J19+K19)-T19 -> #REF!
B20: Comoso, Mayca | C20: Office Staff | D20: =COMOSO!J33 -> 74.683333 | E20: =15042.6/2 -> 7521.3 | F20: =COMOSO!N35 -> 327.69231 | G20: =E20-F20 -> 7193.6077 | I20: =COMOSO!N38 -> 1474.6154 | J20: =G20+H20+I20 -> 8668.2231 | L20: 675 | M20: 71.29 | S20: 1510 | T20: =SUM(L20:R20) -> 746.29 | U20: =(J20+K20)-T20 -> 7921.9331
B21: Dagot, Gie Boy | C21: Technical Staff | D21: =DAGOT!J36 -> 127.5 | E21: =15042.6/2 -> 7521.3 | F21: =DAGOT!N38 -> 596.79456 | G21: =E21-F21 -> 6924.5054 | I21: =DAGOT!#REF! -> #REF! | J21: =G21+H21+I21 -> #REF! | L21: 675 | M21: 71.29 | S21: 1350 | T21: =SUM(L21:R21) -> 746.29 | U21: =(J21+K21)-T21 -> #REF!
B22: Sucia, Van Lloyd | C22: Technical Staff | D22: =#REF! -> #REF! | E22: =15042.6/2 -> 7521.3 | F22: =#REF! -> #REF! | G22: =E22-F22 -> #REF! | J22: =G22+H22+I22 -> #REF! | L22: 675 | M22: 71.29 | T22: =SUM(L22:R22) -> 746.29 | U22: =(J22+K22)-T22 -> #REF!
B23: Malazarte, Jan Kayle Mari | C23: Technical Staff | D23: =#REF! -> #REF! | E23: =15042.6/2 -> 7521.3 | F23: =#REF! -> #REF! | G23: =E23-F23 -> #REF! | I23: =#REF! -> #REF! | J23: =G23+H23+I23 -> #REF! | L23: 675 | M23: 71.29 | T23: =SUM(L23:R23) -> 746.29 | U23: =(J23+K23)-T23 -> #REF!
B24: Soledad, Princess Joy | C24: Project Survey Head | D24: =#REF! -> #REF! | E24: 10250 | G24: =E24 -> 10250 | J24: =G24+H24+I24 -> 10250 | L24: 900 | M24: 109.23 | R24: 830 | S24: 1311.94 | T24: =SUM(L24:R24) -> 1839.23 | U24: =(J24+K24)-T24 -> 8410.77
B25: Batul, Shajanli Grace | C25: Procurement Officer | D25: =BATUL!G13 -> 104 | E25: 6000 | F25: =BATUL!M33 -> 0 | G25: =E25-F25 -> 6000 | H25: =BATUL!M35 -> 0 | I25: =BATUL!M36 -> 0 | J25: =G25+H25+I25 -> 6000 | L25: 540 | M25: 142.58 | S25: 833.33 | T25: =SUM(L25:R25) -> 682.58 | U25: =(J25+K25)-T25 -> 5317.42
B26: Juanich, Paul Jerome | C26: Draftsman | D26: =#REF! -> #REF! | E26: 6000 | F26: =#REF! -> #REF! | G26: =E26-F26 -> #REF! | I26: =#REF! -> #REF! | J26: =G26+H26+I26 -> #REF! | L26: 540 | M26: 142.58 | T26: =SUM(L26:R26) -> 682.58 | U26: =(J26+K26)-T26 -> #REF!
B27: Manaeg, Harold | C27: Technical Staff | D27: =ADELANTAR!J33 -> 106.38333 | E27: 6000 | F27: =ADELANTAR!N35 -> 312.28333 | G27: =E27-F27 -> 5687.7167 | H27: =ADELANTAR!N37 -> 153.75 | I27: =ADELANTAR!N38 -> 0 | J27: =G27+H27+I27 -> 5841.4667 | L27: 540 | S27: 1670 | T27: =SUM(L27:R27) -> 540 | U27: =(J27+K27)-T27 -> 5301.4667
B28: Alejandrino, Rey Mark | C28: Laboratory Operator | D28: =#REF! -> #REF! | E28: 6000 | F28: =#REF! -> #REF! | G28: =E28-F28 -> #REF! | I28: =#REF! -> #REF! | J28: =G28+H28+I28 -> #REF! | L28: 540 | T28: =SUM(L28:R28) -> 540 | U28: =(J28+K28)-T28 -> #REF!
B29: Paredes, Matthew | C29: Part Time Draftsman | D29: =#REF! -> #REF! | E29: =#REF! -> #REF! | F29: =#REF! -> #REF! | G29: =E29-F29 -> #REF! | H29: =#REF! -> #REF! | I29: =#REF! -> #REF! | J29: =G29+H29+I29 -> #REF! | U29: =(J29+K29)-T29 -> #REF!
B30: ADMIN | G30: =E30-F30 -> 0 | J30: =G30+H30+I30 -> 0 | U30: =(J30+K30)-T30 -> 0
B31: Gaid, Dorabel Y. | C31: Admin Assistant | D31: =#REF! -> #REF! | E31: 8000 | F31: =#REF! -> #REF! | G31: =E31-F31 -> #REF! | I31: =#REF! -> #REF! | J31: =G31+H31+I31 -> #REF! | L31: 720 | M31: 147.17 | Q31: 1015.19 | S31: 1600 | T31: =SUM(L31:R31) -> 1882.36 | U31: =(J31+K31)-T31 -> #REF!
B32: Guerzo, Jovelyn H. | C32: EHS Head | D32: =#REF! -> #REF! | E32: 9250 | G32: =E32-F32 -> 9250 | J32: =G32+H32+I32 -> 9250 | L32: 832.5 | M32: 109.23 | R32: 500 | S32: 1500 | T32: =SUM(L32:R32) -> 1441.73 | U32: =(J32+K32)-T32 -> 7808.27
B33: Jamelo, Elfren | C33: Amansinaya In-charge | D33: 104 | E33: 7500 | G33: =E33-F33 -> 7500 | J33: =G33+H33+I33 -> 7500 | K33: 2000 | L33: 675 | M33: 109.23 | S33: 3125 | T33: =SUM(L33:R33) -> 784.23 | U33: =(J33+K33)-T33 -> 8715.77
B34: Macatangay, Michael | C34: Company Driver | D34: 104 | E34: 7500 | G34: =E34-F34 -> 7500 | J34: =G34+H34+I34 -> 7500 | K34: 1000 | L34: 675 | M34: 142.58 | S34: 1666.63 | T34: =SUM(L34:R34) -> 817.58 | U34: =(J34+K34)-T34 -> 7682.42
B35: Galedo, Joshua | C35: General Services Staff | D35: =#REF! -> #REF! | E35: 7500 | G35: =E35-F35 -> 7500 | J35: =G35+H35+I35 -> 7500 | L35: 675 | M35: 71.29 | R35: 1000 | S35: 2500 | T35: =SUM(L35:R35) -> 1746.29 | U35: =(J35+K35)-T35 -> 5753.71
B36: Aurelio, Roderic | C36: Utility | D36: =#REF! -> #REF! | E36: 5000 | F36: =#REF! -> #REF! | G36: =E36-F36 -> #REF! | I36: =#REF! -> #REF! | J36: =G36+H36+I36 -> #REF! | L36: 450 | T36: =SUM(L36:R36) -> 450 | U36: =(J36+K36)-T36 -> #REF!
B37: Nacpil, Marilyn | C37: Consultant, EHS | E37: 5000 | J37: 5000 | U37: =(J37+K37)-T37 -> 5000
B38: Grageda, Riza | C38: Psychometrician | E38: 3000 | J38: 3000 | U38: =(J38+K38)-T38 -> 3000
B39: Bacosa, Mary Jel | C39: Consultant, Legal | E39: 3000 | J39: 3000 | R39: 1000 | S39: 1500 | U39: =(J39+K39)-T39 -> 3000
B40: FINANCE | G40: =E40-F40 -> 0 | J40: =G40+H40+I40 -> 0 | U40: =(J40+K40)-T40 -> 0
B41: Acompañado, Nancy | C41: A/R Officer | D41: =#REF! -> #REF! | E41: 8000 | G41: =E41-F41 -> 8000 | I41: =#REF! -> #REF! | J41: =G41+H41+I41 -> #REF! | L41: 720 | M41: 71.29 | P41: 292 | T41: =SUM(L41:R41) -> 1083.29 | U41: =(J41+K41)-T41 -> #REF!
B42: Consuelo, Regine | C42: Finance Assistant | D42: =#REF! -> #REF! | E42: 8500 | G42: =E42-F42 -> 8500 | J42: =G42+H42+I42 -> 8500 | L42: 765 | M42: 71.29 | P42: 292 | T42: =SUM(L42:R42) -> 1128.29 | U42: =(J42+K42)-T42 -> 7371.71
B43: Dobleros, Reden | C43: Accounting Clerk | D43: =#REF! -> #REF! | E43: 6000 | G43: =E43-F43 -> 6000 | I43: =#REF! -> #REF! | J43: =G43+H43+I43 -> #REF! | L43: 540 | M43: 142.58 | T43: =SUM(L43:R43) -> 682.58 | U43: =(J43+K43)-T43 -> #REF!
B44: OPERATION | G44: =E44-F44 -> 0 | J44: =G44+H44+I44 -> 0 | U44: =(J44+K44)-T44 -> 0
B45: Cayapas, Reymond I | C45: Project Team Leader | D45: =#REF! -> #REF! | E45: 6000 | G45: =E45-F45 -> 6000 | J45: =G45+H45+I45 -> 6000 | L45: 540 | M45: 218.46 | T45: =SUM(L45:R45) -> 758.46 | U45: =(J45+K45)-T45 -> 5241.54
B46: Morados, Moses | C46: Laborer | D46: =#REF! -> #REF! | E46: 6000 | F46: =#REF! -> #REF! | G46: =E46-F46 -> #REF! | J46: =G46+H46+I46 -> #REF! | L46: 540 | T46: =SUM(L46:R46) -> 540 | U46: =(J46+K46)-T46 -> #REF!
B47: Caliwanagan, Daryl | C47: Material Engineer | E47: 8000 | G47: 8000 | U47: =G47 -> 8000
B48: Suprecencia, Melvin | C48: Project Supervisor | D48: 13 D | E48: 8500 | G48: =E48-F48 -> 8500 | K48: 2500 | L48: 765 | T48: =SUM(L48:R48) -> 765 | U48: =(G48+K48)-T48 -> 10235
B49: Mitchell, Rey John | C49: Project Supervisor | D49: 13 D | E49: 8500 | G49: =E49-F49 -> 8500 | K49: 2500 | L49: 765 | M49: 142.58 | T49: =SUM(L49:R49) -> 907.58 | U49: =(G49+K49)-T49 -> 10092.42
B50: Samog-oy, Christian Paul | C50: Project Team Leader | D50: 11D | E50: 4701.29 | G50: =E50-F50 -> 4701.29 | K50: 2500 | L50: 585 | T50: =SUM(L50:R50) -> 585 | U50: =(G50+K50)-T50 -> 6616.29
B51: Apgao, Edel John | C51: Project Team Leader | D51: 13 D | E51: 6000 | G51: =E51-F51 -> 6000 | K51: 2500 | M51: 142.58 | T51: =SUM(L51:R51) -> 142.58 | U51: =(G51+K51)-T51 -> 8357.42
B52: Delos Santos, Gemar | C52: Project Team Leader | D52: 13 D | E52: 6000 | G52: =E52-F52 -> 6000 | K52: 2500 | L52: 540 | M52: 218.46 | T52: =SUM(L52:R52) -> 758.46 | U52: =(G52+K52)-T52 -> 7741.54
B53: Basig, Froilan | C53: Project Team Leader | D53: 10D | E53: 3945.2 | G53: =E53-F53 -> 3945.2 | K53: 2500 | L53: 540 | M53: 218.46 | T53: =SUM(L53:R53) -> 758.46 | U53: =(G53+K53)-T53 -> 5686.74
B54: Abis, Oscar | C54: Laborer | D54: 13 D | E54: 5000 | G54: =E54-F54 -> 5000 | K54: 2500 | T54: =SUM(L54:R54) -> 0 | U54: =(G54+K54)-T54 -> 7500
B55: Hilado, Jonathan | C55: Laborer | D55: 13 D | E55: 5000 | G55: =E55-F55 -> 5000 | K55: 2500 | T55: =SUM(L55:R55) -> 0 | U55: =(G55+K55)-T55 -> 7500
B56: Lagrosa, Noibo | C56: Laborer | D56: 13 D | E56: 5000 | G56: =E56-F56 -> 5000 | K56: 2500 | L56: 450 | T56: =SUM(L56:R56) -> 450 | U56: =(G56+K56)-T56 -> 7050
B57: Badang, Jayson | C57: Laborer | D57: 13 D | E57: 5000 | G57: =E57-F57 -> 5000 | K57: 2500 | L57: 450 | T57: =SUM(L57:R57) -> 450 | U57: =(G57+K57)-T57 -> 7050
B58: Becaro, Ronald | C58: Laborer | D58: 13 D | E58: 5000 | G58: =E58-F58 -> 5000 | K58: 2500 | T58: =SUM(L58:R58) -> 0 | U58: =(G58+K58)-T58 -> 7500
B59: Gallo, Aldrin | C59: Laborer | D59: 13 D | E59: 5000 | G59: =E59-F59 -> 5000 | K59: 2500 | T59: =SUM(L59:R59) -> 0 | U59: =(G59+K59)-T59 -> 7500
B60: Bungay, Dennis | C60: Laborer | D60: 13 D | E60: 5000 | G60: =E60-F60 -> 5000 | K60: 2500 | T60: =SUM(L60:R60) -> 0 | U60: =(G60+K60)-T60 -> 7500
B61: Padilla, Benigno | C61: Laborer | D61: 13 D | E61: 5000 | G61: =E61-F61 -> 5000 | K61: 2500 | S61: 1000 | T61: =SUM(L61:R61) -> 0 | U61: =(G61+K61)-T61 -> 7500
B62: Elevera, Dondon | C62: Laborer | D62: 13 D | E62: 5000 | G62: =E62-F62 -> 5000 | K62: 2500 | L62: 450 | T62: =SUM(L62:R62) -> 450 | U62: =(G62+K62)-T62 -> 7050
B63: Andales, Joel | C63: Laborer | D63: 13 D | E63: 5000 | G63: =E63-F63 -> 5000 | K63: 2500 | L63: 450 | T63: =SUM(L63:R63) -> 450 | U63: =(G63+K63)-T63 -> 7050
B64: Tesado, Christopher | C64: Laborer | D64: 13 D | E64: 5000 | G64: =E64-F64 -> 5000 | K64: 2500 | L64: 450 | R64: =SUM(R13:R62) -> 7530 | S64: =SUM(S13:S62) -> 27008.57 | T64: =SUM(L64:R64) -> 7980 | U64: =(G64+K64)-T64 -> -480
B65: Diamad, Donald | C65: Laborer | D65: 13 D | E65: 5000 | G65: =E65-F65 -> 5000 | K65: 2500 | T65: =SUM(L65:R65) -> 0 | U65: =(G65+K65)-T65 -> 7500
B66: Isaak Jardin | C66: Laborer | D66: 13 D | E66: 5000 | G66: =E66-F66 -> 5000 | K66: 2500
B67: Total Payroll | E67: =SUM(E13:E66) -> #REF! | F67: =SUM(F13:F66) -> #REF! | G67: =E67-F67 -> #REF! | H67: =SUM(H13:H66) -> #REF! | I67: =SUM(I13:I65) -> #REF! | K67: =SUM(K13:K66) -> 69250 | L67: =SUM(L13:L66) -> 22410 | M67: =SUM(M13:M66) -> 3329.83 | N67: =SUM(N13:N66) -> 1400.03 | O67: =SUM(O13:O66) -> 2487 | P67: =SUM(P13:P66) -> 10959 | Q67: =SUM(Q13:Q66) -> 1015.19 | T67: =SUM(T13:T65) -> 55661.05 | U67: =SUM(U13:U65) -> #REF!
B69: Prepared By: | G69: Checked By: | N69: Approved By:
B71: DORABEL Y. GAID | G71: LYN M. BELTRAN | N71: KATHERINE J. BACOSA
B72: Admin Assistant | G72: Admn Manager | N72: Finance Manager

Sheet AUG15
A3: BACS CONSTRUCTION SERVICES AND ENGINEERING CONSULTANCY
A4: PAYROLL SUMMARY
A5: COVERED DATE : | B5: Aug 11-25, 2022
A6: PERIOD : | B6: 44804
A8: NAME | B8: DESIGNATION | C8: Hours/Days | D8: Basic Pay | E8: Less: Absent, Late and Undertime | F8: Total Basic Pay | G8: Overtime | H8: Holiday & Premium Pay | I8: GROSS WAGE | J8: De Minimis | O8: DEDUCTIONS | W8: TOTAL DEDUCTION | X8: NET PAY
K10: PHIC | L10: HDMF | M10: SSS | N10: INSURANCE | O10: Income Tax | P10: COMM. ALLOWANCE | Q10: Other Deduction | R10: SSS Loan | S10: TRAVEL | T10: LOAN | U10: CASH ADVANCE | V10: FOR RETRO
N11: BPI
A13: Bacosa , Cesario Jr | B13: CEO/ PRESIDENT | D13: 15000 | F13: =D13-E13 -> 15000 | I13: =F13+G13+H13 -> 15000 | J13: 2500 | N13: 147.17 | P13: 1524.75 | Q13: 5000 | S13: 500 | U13: 9024.15 | W13: =SUM(M13:U13) -> 16196.07 | X13: =(D13+J13)-W13 -> 1303.93
A14: Villegas, Gabby G. | B14: Project Manager | D14: 13250 | F14: =D14-E14 -> 13250 | I14: =F14+G14+H14 -> 13250 | J14: 4250 | K14: 397.5 | L14: 300 | N14: 147.17 | O14: =1333.33/2 -> 666.665 | P14: 1107.75 | Q14: 187.5 | S14: 1000 | T14: 2691.67 | W14: =SUM(M14:U14) -> 5800.755 | X14: =(D14+J14)-W14 -> 11699.245
A15: Germina, Mark Jayson H | B15: Operation Manager | D15: 11250 | F15: =D15-E15 -> 11250 | I15: =F15+G15+H15 -> 11250 | J15: 4250 | K15: 337.5 | L15: 300 | N15: 147.17 | O15: =533.4/2 -> 266.7 | P15: 1107.75 | Q15: 187.5 | S15: 500 | T15: 2250 | U15: 500 | W15: =SUM(M15:U15) -> 4959.12 | X15: =(D15+J15)-W15 -> 10540.88
A16: Beltran, Lyn M. | B16: Admin Manager | D16: 12750 | F16: =D16-E16 -> 12750 | I16: =F16+G16+H16 -> 12750 | J16: 4250 | K16: 382.5 | L16: 500 | N16: 147.17 | O16: =1133.33/2 -> 566.665 | P16: 250 | S16: 1700 | W16: =SUM(M16:U16) -> 2663.835 | X16: =(D16+J16)-W16 -> 14336.165
A17: Bacosa, Katherine J. | B17: Finance Manager | D17: 11000 | F17: =D17-E17 -> 11000 | I17: =F17+G17+H17 -> 11000 | J17: 3500 | N17: 147.17 | P17: 1462.25 | Q17: 5000 | S17: 500 | U17: 1500 | W17: =SUM(M17:U17) -> 8609.42 | X17: =(D17+J17)-W17 -> 5890.58
A18: PROJECT MANAGEMENT | X18: =(D18+J18)-W18 -> 0
A19: Bocala, Kevin O. | B19: Technical Head | D19: 9000 | E19: 1384.64 | F19: =D19-E19 -> 7615.36 | I19: =F19+G19+H19 -> 7615.36 | K19: 225 | L19: 100 | N19: 109.23 | T19: 2500 | U19: 1000 | W19: =SUM(M19:U19) -> 3609.23 | X19: =(I19+J19)-W19 -> 4006.13
A20: Comoso, Mayca | B20: Office Staff | D20: 8099.84 | E20: 103.66 | F20: =D20-E20 -> 7996.18 | I20: =F20+G20+H20 -> 7996.18 | K20: 225.64 | L20: 100 | N20: 71.29 | T20: 1510 | U20: 1000 | W20: =SUM(M20:U20) -> 2581.29 | X20: =(I20+J20)-W20 -> 5414.89
A21: Dagot, Gie Boy | B21: Technical Staff | D21: 8099.84 | F21: =D21-E21 -> 8099.84 | I21: =F21+G21+H21 -> 8099.84 | K21: 225.64 | L21: 100 | N21: 71.29 | T21: 1350 | W21: =SUM(M21:U21) -> 1421.29 | X21: =(I21+J21)-W21 -> 6678.55
A22: Sucia, Van Lloyd | B22: Technical Staff | D22: 8099.84 | E22: 253.12 | F22: =D22-E22 -> 7846.72 | I22: =F22+G22+H22 -> 7846.72 | K22: 225.64 | L22: 100 | N22: 71.29 | U22: 1000 | W22: =SUM(M22:U22) -> 1071.29 | X22: =(I22+J22)-W22 -> 6775.43
A23: Malazarte, Jan Kayle Mari | B23: Technical Staff | D23: 8099.84 | E23: 335.08 | F23: =D23-E23 -> 7764.76 | I23: =F23+G23+H23 -> 7764.76 | K23: 225.64 | L23: 100 | N23: 71.29 | W23: =SUM(M23:U23) -> 71.29 | X23: =(I23+J23)-W23 -> 7693.47
A24: Soledad, Princess Joy | B24: Project Survey Head | D24: 10250 | F24: =D24-E24 -> 10250 | I24: =F24+G24+H24 -> 10250 | K24: 307.5 | L24: 100 | N24: 109.23 | S24: 830 | T24: 1311.94 | W24: =SUM(M24:U24) -> 2251.17 | X24: =(I24+J24)-W24 -> 7998.83
A25: Batul, Shajanli Grace | B25: Procurement Officer | D25: 8076.92 | E25: 843.75 | F25: =D25-E25 -> 7233.17 | G25: 540.87 | I25: =F25+G25+H25 -> 7774.04 | K25: 180 | L25: 100 | N25: 142.58 | T25: 833.33 | U25: 1000 | W25: =SUM(M25:U25) -> 1975.91 | X25: =(I25+J25)-W25 -> 5798.13
A26: Juanich, Paul Jerome | B26: Draftsman | D26: 6461.28 | E26: 1396.1 | F26: =D26-E26 -> 5065.18 | I26: =F26+G26+H26 -> 5065.18 | N26: 285.16 | W26: =SUM(M26:U26) -> 285.16 | X26: =(I26+J26)-W26 -> 4780.02
A27: Manaeg, Harold | B27: Technical Staff | C27: =ADELANTAR!J33 -> 106.38333 | D27: 6000 | E27: 1846.08 | F27: =D27-E27 -> 4153.92 | G27: 144.23 | I27: =F27+G27+H27 -> 4298.15 | K27: 180 | L27: 100 | N27: 285.16 | T27: 1670 | W27: =SUM(M27:U27) -> 1955.16 | X27: =(I27+J27)-W27 -> 2342.99
A28: Alejandrino, Rey Mark | B28: Laboratory Operator | D28: 6461.54 | E28: 230.77 | F28: =D28-E28 -> 6230.77 | I28: =F28+G28+H28 -> 6230.77 | K28: 180 | L28: 100 | N28: 171.1 | U28: 1000 | W28: =SUM(M28:U28) -> 1171.1 | X28: =(I28+J28)-W28 -> 5059.67
A29: Paredes, Matthew | B29: Part Time Draftsman | D29: 4380 | E29: 377.17 | F29: =D29-E29 -> 4002.83 | G29: =399.22+231.34 -> 630.56 | I29: =F29+G29+H29 -> 4633.39 | W29: =SUM(M29:U29) -> 0 | X29: =(I29+J29)-W29 -> 4633.39
A30: ADMIN | F30: =D30-E30 -> 0 | I30: =F30+G30+H30 -> 0 | X30: =(I30+J30)-W30 -> 0
A31: Gaid, Dorabel Y. | B31: Admin Assistant | D31: 8615.38 | E31: 907.7 | F31: =D31-E31 -> 7707.68 | I31: =F31+G31+H31 -> 7707.68 | K31: 240 | L31: 500 | N31: 147.17 | R31: 500 | T31: 1600 | U31: 1500 | W31: =SUM(M31:U31) -> 3747.17 | X31: =(I31+J31)-W31 -> 3960.51
A32: Guerzo, Jovelyn H. | B32: EHS Head | D32: 9250 | F32: =D32-E32 -> 9250 | I32: =F32+G32+H32 -> 9250 | K32: 277.5 | L32: 100 | N32: 109.23 | S32: 500 | T32: 1500 | U32: 1000 | W32: =SUM(M32:U32) -> 3109.23 | X32: =(I32+J32)-W32 -> 6140.77
A33: Grageda, Riza | B33: Psychometrician | D33: - | I33: =F33+G33+H33 -> 0 | X33: 3000
A34: Nacpil, Marilyn | B34: Consultant, EHS | D34: - | X34: 5000
A35: Bacosa, Mary Jel | B35: Consultant, Legal | D35: - | X35: 3000
A36: Jamelo, Elfren | B36: Amansinaya In-charge | D36: 7500 | F36: =D36-E36 -> 7500 | I36: =F36+G36+H36 -> 7500 | J36: 2000 | K36: 225 | N36: 109.23 | T36: 3125 | U36: 500 | W36: =SUM(M36:U36) -> 3734.23 | X36: =(I36+J36)-W36 -> 5765.77
A37: Macatangay, Michael | B37: Company Driver | D37: 7500 | F37: =D37-E37 -> 7500 | I37: =F37+G37+H37 -> 7500 | J37: 1000 | K37: 225 | L37: 100 | N37: 142.58 | T37: 1666.63 | U37: 1000 | W37: =SUM(M37:U37) -> 2809.21 | X37: =(I37+J37)-W37 -> 5690.79
A38: Galedo, Joshua | B38: General Services Staff | D38: 7500 | F38: =D38-E38 -> 7500 | I38: =F38+G38+H38 -> 7500 | K38: 225 | L38: 100 | N38: 71.29 | S38: 1000 | T38: 2500 | U38: 500 | W38: =SUM(M38:U38) -> 4071.29 | X38: =(I38+J38)-W38 -> 3428.71
A39: Aurelio, Roderic | B39: Utility | D39: 5384.62 | F39: =D39-E39 -> 5384.62 | I39: =F39+G39+H39 -> 5384.62 | K39: 150 | L39: 100 | W39: =SUM(M39:U39) -> 0 | X39: =(I39+J39)-W39 -> 5384.62
A40: FINANCE | F40: =D40-E40 -> 0 | I40: =F40+G40+H40 -> 0 | X40: =(I40+J40)-W40 -> 0
A41: Acompañado, Nancy | B41: A/R Officer | D41: 8615.38 | F41: =D41-E41 -> 8615.38 | I41: =F41+G41+H41 -> 8615.38 | K41: 240 | L41: 100 | N41: 71.29 | Q41: 292 | U41: 1000 | W41: =SUM(M41:U41) -> 1363.29 | X41: =(I41+J41)-W41 -> 7252.09
A42: Consuelo, Regine | B42: Finance Assistant | D42: 8500 | F42: =D42-E42 -> 8500 | I42: =F42+G42+H42 -> 8500 | K42: 255 | L42: 100 | N42: 71.29 | Q42: 292 | S42: 1000 | T42: 1500 | U42: 500 | W42: =SUM(M42:U42) -> 3363.29 | X42: =(I42+J42)-W42 -> 5136.71
A43: Dobleros, Reden | B43: Accounting Clerk | D43: 7277.5 | E43: 520.9 | F43: =D43-E43 -> 6756.6 | I43: =F43+G43+H43 -> 6756.6 | K43: 180 | L43: 100 | N43: 142.58 | U43: 1000 | W43: =SUM(M43:U43) -> 1142.58 | X43: =(I43+J43)-W43 -> 5614.02
A44: OPERATION | F44: =D44-E44 -> 0 | I44: =F44+G44+H44 -> 0 | X44: =(I44+J44)-W44 -> 0
A45: Calinawagan, Daryl | B45: Consultant, Material | W45: 4000 | X45: 4000
A46: Cayapas, Reymond I | B46: Project Team Leader | C46: 11D | D46: 6000 | E46: 1384.56 | F46: =D46-E46 -> 4615.44 | I46: =F46+G46+H46 -> 4615.44 | K46: 180 | W46: =SUM(M46:U46) -> 0 | X46: =(I46+J46)-W46 -> 4615.44
A47: Morados, Moses | B47: Laborer | C47: 14D | D47: 6461.54 | E47: 8.65 | F47: =D47-E47 -> 6452.89 | I47: =F47+G47+H47 -> 6452.89 | K47: 255 | L47: 100 | W47: =SUM(M47:U47) -> 0 | X47: =(I47+J47)-W47 -> 6452.89
A48: Suprecencia, Melvin | B48: Project Supervisor | C48: 14D | D48: 8500 | F48: =D48-E48 -> 8500 | I48: =F48+G48+H48 -> 8500 | J48: 2500 | K48: 255 | L48: 100 | N48: 218.46 | W48: =SUM(M48:U48) -> 218.46 | X48: =(I48+J48)-W48 -> 10781.54
A49: Mitchell, Rey John | B49: Project Supervisor | C49: 14D | D49: 8500 | F49: =D49-E49 -> 8500 | I49: =F49+G49+H49 -> 8500 | J49: 2500 | K49: 210 | L49: 100 | N49: 142.58 | W49: =SUM(M49:U49) -> 142.58 | X49: =(I49+J49)-W49 -> 10857.42
A50: Samog-oy, Christian Paul | B50: Project Team Leader | C50: 14D | D50: 6500 | F50: =D50-E50 -> 6500 | I50: =F50+G50+H50 -> 6500 | J50: 2500 | K50: 195 | L50: 100 | N50: 218.46 | W50: =SUM(M50:U50) -> 218.46 | X50: =(F50+J50+V50)-W50 -> 8781.54
A51: Apgao, Edel John | B51: Project Team Leader | C51: 14D | D51: 6000 | F51: =D51-E51 -> 6000 | I51: =F51+G51+H51 -> 6000 | J51: 2500 | K51: 180 | L51: 100 | N51: 142.58 | W51: =SUM(M51:U51) -> 142.58 | X51: =(I51+J51)-W51 -> 8357.42
A52: Delos Santos, Gemar | B52: Project Team Leader | C52: 14D | D52: 6000 | E52: 394.52 | F52: =D52-E52 -> 5605.48 | I52: =F52+G52+H52 -> 5605.48 | J52: 2500 | K52: 180 | L52: 100 | N52: 142.58 | U52: 500 | W52: =SUM(M52:U52) -> 642.58 | X52: =(I52+J52)-W52 -> 7462.9
A53: Basig, Froilan | B53: Project Team Leader | C53: 14D | D53: 6000 | F53: =D53-E53 -> 6000 | I53: =F53+G53+H53 -> 6000 | J53: 2500 | K53: 150 | N53: 218.46 | W53: =SUM(M53:U53) -> 218.46 | X53: =(I53+J53)-W53 -> 8281.54
A54: Abis, Oscar | B54: Laborer | C54: 14D | D54: 5000 | F54: =D54-E54 -> 5000 | I54: =F54+G54+H54 -> 5000 | J54: 2500 | W54: =SUM(M54:U54) -> 0 | X54: =(I54+J54)-W54 -> 7500
A55: Hilado, Jonathan | B55: Laborer | C55: 14D | D55: 5000 | F55: =D55-E55 -> 5000 | I55: =F55+G55+H55 -> 5000 | J55: 2500 | K55: 150 | L55: 100 | U55: 1000 | W55: =SUM(M55:U55) -> 1000 | X55: =(I55+J55)-W55 -> 6500
A56: Lagrosa, Noibo | B56: Laborer | C56: 14D | D56: 5000 | F56: =D56-E56 -> 5000 | I56: =F56+G56+H56 -> 5000 | J56: 2500 | K56: 150 | L56: 100 | U56: 500 | W56: =SUM(M56:U56) -> 500 | X56: =(I56+J56)-W56 -> 7000
A57: Badang, Jayson | B57: Laborer | C57: 14D | D57: 5000 | F57: =D57-E57 -> 5000 | I57: =F57+G57+H57 -> 5000 | J57: 2500 | K57: 150 | U57: 500 | W57: =SUM(M57:U57) -> 500 | X57: =(I57+J57)-W57 -> 7000
A58: Becaro, Ronald | B58: Laborer | C58: 14D | D58: 5000 | F58: =D58-E58 -> 5000 | I58: =F58+G58+H58 -> 5000 | J58: 2500 | U58: 750 | W58: =SUM(M58:U58) -> 750 | X58: =(I58+J58)-W58 -> 6750
A59: Gallo, Aldrin | B59: Laborer | C59: 14D | D59: 5000 | F59: =D59-E59 -> 5000 | I59: =F59+G59+H59 -> 5000 | J59: 2500 | K59: 150 | L59: 100 | U59: 500 | W59: =SUM(M59:U59) -> 500 | X59: =(I59+J59)-W59 -> 7000
A60: Padilla, Benigno | B60: Laborer | C60: 14D | D60: 5000 | F60: =D60-E60 -> 5000 | I60: =F60+G60+H60 -> 5000 | J60: 2500 | K60: 150 | U60: 500 | W60: =SUM(M60:U60) -> 500 | X60: =(I60+J60)-W60 -> 7000
A61: Elevera, Dondon | B61: Laborer | C61: 14D | D61: 5000 | F61: =D61-E61 -> 5000 | I61: =F61+G61+H61 -> 5000 | J61: 2500 | K61: 150 | W61: =SUM(M61:U61) -> 0 | X61: =(I61+J61)-W61 -> 7500
A62: Andales, Joel | B62: Laborer | C62: 14D | D62: 5000 | F62: =D62-E62 -> 5000 | I62: =F62+G62+H62 -> 5000 | J62: 2500 | K62: 150 | L62: 100 | W62: =SUM(M62:U62) -> 0 | X62: =(I62+J62)-W62 -> 7500
A63: Tesado, Christopher | B63: Laborer | C63: 14D | D63: 5000 | F63: =D63-E63 -> 5000 | I63: =F63+G63+H63 -> 5000 | J63: 2500 | K63: 150 | L63: 100 | W63: =SUM(M63:U63) -> 0 | X63: =(I63+J63)-W63 -> 7500
A64: Diamad, Donald | B64: Laborer | C64: 14D | D64: 5000 | F64: =D64-E64 -> 5000 | I64: =F64+G64+H64 -> 5000 | J64: 2500 | K64: 150 | T64: 1000 | W64: =SUM(M64:U64) -> 1000 | X64: =(I64+J64)-W64 -> 6500
A65: Isaak Jardin | B65: Laborer | C65: 14D | D65: 5000 | F65: =D65-E65 -> 5000 | I65: =F65+G65+H65 -> 5000 | J65: 2500 | K65: 150 | L65: 100 | W65: =SUM(M65:U65) -> 0 | X65: =(I65+J65)-W65 -> 7500
A67: Total Payroll | D67: =SUM(D13:D65) -> 330383.52 | E67: =SUM(E13:E65) -> 9986.7 | F67: =D67-E67 -> 320396.82 | G67: =SUM(G13:G65) -> 1315.66 | H67: =SUM(H13:H65) -> 0 | I67: =SUM(I13:I65) -> 321712.48 | J67: =SUM(J13:J65) -> 66750 | N67: =SUM(N13:N65) -> 4071.25 | O67: =SUM(O13:O65) -> 1500.03 | P67: =SUM(P13:P65) -> 5452.5 | Q67: =SUM(Q13:Q65) -> 10959 | R67: =SUM(R13:R65) -> 500 | S67: =SUM(S13:S65) -> 7530 | T67: =SUM(T13:T65) -> 27008.57 | U67: =SUM(U12:U65) -> 27274.15 | V67: =SUM(V12:V65) -> 0 | W67: =SUM(W13:W65) -> 88295.5 | X67: =SUM(X13:X65) -> 319166.98
A69: Prepared By: | F69: Checked By: | O69: Approved By: | V69: Noted by:
A71: DORABEL Y. GAID | F71: LYN M. BELTRAN | O71: KATHERINE J. BACOSA | V71: CESARIO A. BACOSA JR.
A72: Admin Assistant | F72: Admn Manager | O72: Finance Manager | V72: CEO/President

Sheet SEPT 30
A1: BACS CONSTRUCTION SERVICES AND ENGINEERING CONSULTANCY
A2: PAYROLL SUMMARY
A3: COVERED DATE : | B3: SEPTEMBER 11-25, 2026
A4: PERIOD : | B4: 46295
A6: NAME | B6: DESIGNATION | C6: Hours/Days | D6: Basic Pay | E6: Less: Absent, Late and Undertime | F6: Total Basic Pay | G6: Overtime | H6: Holiday & Premium Pay | I6: GROSS WAGE | J6: De Minimis | K6: DEDUCTIONS | S6: FOR RETRO | T6: TOTAL DEDUCTION | U6: NET PAY | V6: BNM SAVINGS | W6: BNM LOAN | X6: Membership Fee | Z6: BNM | AA6: SALARY
K8: SSS | L8: Income Tax | M8: Pag-ibig Loan | N8: SSS Loan | O8: RCBC Loan | P8: Medical Pooling | Q8: CASH ADVANCE | R8: Other Deduction
F15: =D15-E15 -> 0 | I15: =SUM(F15:H15) -> 0 | T15: =SUM(K15:R15) -> 0 | U15: =I15+J15+S15-T15 -> 0 | AD15: =AB15-AC15 -> 0
B16: Laboratory Operator | D16: =PAALAN!N33 -> 7000 | E16: =PAALAN!N34 -> 0 | F16: =D16-E16 -> 7000 | G16: =PAALAN!N36 -> 0 | H16: =PAALAN!N37 -> 0 | I16: =SUM(F16:H16) -> 7000 | K16: 700 | P16: 100 | S16: 0 | T16: =SUM(K16:R16) -> 800 | U16: =I16+J16+S16-T16 -> 6200 | Y16: =U16-SUM(V16:X16) -> 6200 | AB16: =Y16+Z16+AA16 -> 6200 | AC16: 5998.08 | AD16: =AB16-AC16 -> 201.92
B17: Proj. Technical Supervisor | D17: =PATRICIO!N33 -> 9216.64 | E17: =PATRICIO!N34 -> 0 | F17: =D17-E17 -> 9216.64 | H17: =PATRICIO!N37 -> 0 | I17: =SUM(F17:H17) -> 9216.64 | J17: 1500 | K17: 925 | N17: 0 | P17: 200 | T17: =SUM(K17:R17) -> 1125 | U17: =I17+J17+S17-T17 -> 9591.64 | V17: 1000 | W17: 2809.77 | Y17: =U17-SUM(V17:X17) -> 5781.87 | AB17: =Y17+Z17+AA17 -> 5781.87 | AC17: 5250.14 | AD17: =AB17-AC17 -> 531.73
B18: Junior Office Engineer | D18: ='Fixed Salary - Sample'!N32 -> 10000 | E18: ='Fixed Salary - Sample'!N33 -> 480.76923 | F18: =D18-E18 -> 9519.2308 | H18: ='Fixed Salary - Sample'!N36 -> 0 | I18: =SUM(F18:H18) -> 9519.2308 | J18: 1500 | K18: 925 | P18: 100 | Q18: 0 | T18: =SUM(K18:R18) -> 1025 | U18: =I18+J18+S18-T18 -> 9994.2308 | V18: 1000 | W18: 30 | Y18: =U18-SUM(V18:X18) -> 8964.2308 | AB18: =Y18+Z18+AA18 -> 8964.2308 | AC18: 8868.08 | AD18: =AB18-AC18 -> 96.150769
B19: Technical Staff | D19: =MALAZARTE!N33 -> 9963.4803 | E19: =MALAZARTE!N34 -> 863.50162 | F19: =D19-E19 -> 9099.9787 | G19: =MALAZARTE!N36 -> 1186.1286 | H19: =MALAZARTE!N37 -> 0 | I19: =SUM(F19:H19) -> 10286.107 | K19: 975 | N19: 800 | O19: 500 | P19: 100 | R19: 538.4 | T19: =SUM(K19:R19) -> 2913.4 | U19: =I19+J19+S19-T19 -> 7372.7073 | V19: 1000 | W19: 2000 | Y19: =U19-SUM(V19:X19) -> 4372.7073 | AB19: =Y19+Z19+AA19 -> 4372.7073 | AC19: 5262.2 | AD19: =AB19-AC19 -> -889.49273
B20: Draftsman | D20: =PAREDES!N33 -> 8661.8286 | E20: =PAREDES!N34 -> 46.746377 | F20: =D20-E20 -> 8615.0822 | G20: =PAREDES!N36 -> 1237.4041 | H20: =PAREDES!N37 -> 0 | I20: =SUM(F20:H20) -> 9852.4863 | K20: 850 | O20: 750 | P20: 100 | T20: =SUM(K20:R20) -> 1700 | U20: =I20+J20+S20-T20 -> 8152.4863 | V20: 1000 | W20: 1622.25 | Y20: =U20-SUM(V20:X20) -> 5530.2363 | AB20: =Y20+Z20+AA20 -> 5530.2363 | AC20: 4438.57 | AD20: =AB20-AC20 -> 1091.6663
B21: Technical Staff | D21: =BUNGAY!N33 -> 6562.5 | E21: =BUNGAY!N34 -> 0 | F21: =D21-E21 -> 6562.5 | G21: =BUNGAY!N36 -> 703.125 | H21: =BUNGAY!N37 -> 0 | I21: =SUM(F21:H21) -> 7265.625 | K21: 650 | O21: 0 | P21: 100 | T21: =SUM(K21:R21) -> 750 | U21: =I21+J21+S21-T21 -> 6515.625 | V21: 500 | Y21: =U21-SUM(V21:X21) -> 6015.625 | AB21: =Y21+Z21+AA21 -> 6015.625 | AC21: 6028.13 | AD21: =AB21-AC21 -> -12.505
B22: Laboratory Operator | D22: =BASA!N33 -> 8532.4161 | E22: =BASA!N34 -> 570.18209 | F22: =D22-E22 -> 7962.234 | G22: =BASA!N36 -> 0 | H22: =BASA!N37 -> 0 | I22: =SUM(F22:H22) -> 7962.234 | K22: 850 | P22: 100 | T22: =SUM(K22:R22) -> 950 | U22: =I22+J22+S22-T22 -> 7012.234 | V22: 1000 | W22: 1734.11 | Y22: =U22-SUM(V22:X22) -> 4278.124 | AB22: =Y22+Z22+AA22 -> 4278.124 | AC22: 4335.01 | AD22: =AB22-AC22 -> -56.885986
B23: Technical Staff | D23: =ADRIANO!N33 -> 6562.5 | E23: =ADRIANO!N34 -> 250 | F23: =D23-E23 -> 6312.5 | G23: =ADRIANO!N36 -> 625 | H23: =ADRIANO!N37 -> 0 | I23: =SUM(F23:H23) -> 6937.5 | K23: 650 | P23: 100 | T23: =SUM(K23:R23) -> 750 | U23: =I23+J23+S23-T23 -> 6187.5 | Y23: =U23-SUM(V23:X23) -> 6187.5 | AB23: =Y23+Z23+AA23 -> 6187.5 | AC23: 6184.38 | AD23: =AB23-AC23 -> 3.12
B24: Technical Staff | D24: =AZMAN!N33 -> 6562.5 | E24: =AZMAN!N34 -> 2937.5 | F24: =D24-E24 -> 3625 | G24: =AZMAN!N36 -> 234.375 | H24: =AZMAN!N37 -> 0 | I24: =SUM(F24:H24) -> 3859.375 | K24: 650 | P24: 100 | T24: =SUM(K24:R24) -> 750 | U24: =I24+J24+S24-T24 -> 3109.375 | Y24: =U24-SUM(V24:X24) -> 3109.375 | AB24: 0 | AD24: 0
AD25: =AB25-AC25 -> 0
B26: Jr. Sales | D26: =BARORO!N33 -> 6562.5 | E26: =BARORO!N34 -> 187.5 | F26: =D26-E26 -> 6375 | G26: =BARORO!N36 -> 1015.625 | H26: =BARORO!N37 -> 0 | I26: =SUM(F26:H26) -> 7390.625 | J26: 1300 | K26: 650 | O26: 0 | P26: 100 | T26: =SUM(K26:R26) -> 750 | U26: =I26+J26+S26-T26 -> 7940.625 | V26: 1000 | W26: 322.94 | Y26: =U26-SUM(V26:X26) -> 6617.685 | AB26: =Y26+Z26+AA26 -> 6617.685 | AC26: 5770.81 | AD26: =AB26-AC26 -> 846.875
B27: Sales & Marketing | D27: =RUIZ!N33 -> 6562.5 | E27: =RUIZ!N34 -> 3.125 | F27: =D27-E27 -> 6559.375 | G27: =RUIZ!N36 -> 1015.625 | H27: =RUIZ!N37 -> 0 | I27: =SUM(F27:H27) -> 7575 | J27: 0 | K27: 650 | O27: 0 | P27: 100 | T27: =SUM(K27:R27) -> 750 | U27: =I27+J27+S27-T27 -> 6825 | Y27: =U27-SUM(V27:X27) -> 6825 | AB27: =Y27+Z27+AA27 -> 6825 | AC27: 5981.25 | AD27: =AB27-AC27 -> 843.75
F28: =D28-E28 -> 0 | I28: =SUM(F28:H28) -> 0 | T28: =SUM(K28:R28) -> 0 | U28: =I28+J28+S28-T28 -> 0 | Y28: =U28-SUM(V28:X28) -> 0 | AB28: =Y28+Z28+AA28 -> 0 | AD28: =AB28-AC28 -> 0
B29: IT | D29: =GAID!N33 -> 9020 | E29: =GAID!N34 -> 346.92308 | F29: =D29-E29 -> 8673.0769 | G29: =GAID!N36 -> 0 | H29: =GAID!N37 -> 0 | I29: =SUM(F29:H29) -> 8673.0769 | J29: 0 | K29: 900 | L29: 0 | M29: 600 | N29: 800 | O29: 0 | P29: 200 | R29: 0 | T29: =SUM(K29:R29) -> 2500 | U29: =I29+J29+S29-T29 -> 6173.0769 | V29: 2000 | W29: 3500 | Y29: =U29-SUM(V29:X29) -> 673.07692 | AA29: =Y62 -> 7627.8846 | AB29: =Y29+Z29+AA29 -> 8300.9615 | AC29: 6788.65 | AD29: =AB29-AC29 -> 1512.3115
B30: EHS Head | D30: =GUERZO!N33 -> 10270 | E30: =GUERZO!N34 -> 0 | F30: =D30-E30 -> 10270 | H30: =GUERZO!N37 -> 0 | I30: =SUM(F30:H30) -> 10270 | J30: 2500 | K30: 1025 | N30: 1000 | O30: 3500 | P30: 100 | T30: =SUM(K30:R30) -> 5625 | U30: =I30+J30+S30-T30 -> 7145 | V30: 1000 | W30: 3500 | Y30: =U30-SUM(V30:X30) -> 2645 | AB30: =Y30+Z30+AA30 -> 2645 | AC30: 2645 | AD30: =AB30-AC30 -> 0
B31: Company Driver | D31: =MACATANGAY!N33 -> 8520 | E31: =MACATANGAY!N34 -> 0 | F31: =D31-E31 -> 8520 | H31: =MACATANGAY!N37 -> 0 | I31: =SUM(F31:H31) -> 8520 | J31: 1000 | K31: 850 | P31: 100 | Q31: 500 | R31: 250 | T31: =SUM(K31:R31) -> 1700 | U31: =I31+J31+S31-T31 -> 7820 | V31: 1000 | W31: 2061.65 | Y31: =U31-SUM(V31:X31) -> 4758.35 | AB31: =Y31+Z31+AA31 -> 4758.35 | AC31: 5008.35 | AD31: =AB31-AC31 -> -250
B32: GSS | D32: =ALEJANDRINO!N33 -> 8579.335 | E32: =ALEJANDRINO!N34 -> 0 | F32: =D32-E32 -> 8579.335 | H32: =ALEJANDRINO!N37 -> 0 | I32: =SUM(F32:H32) -> 8579.335 | J32: 1500 | K32: 850 | N32: 750 | P32: 100 | T32: =SUM(K32:R32) -> 1700 | U32: =I32+J32+S32-T32 -> 8379.335 | V32: 2000 | W32: 2668.94 | Y32: =U32-SUM(V32:X32) -> 3710.395 | AB32: =Y32+Z32+AA32 -> 3710.395 | AC32: 3710.4 | AD32: =AB32-AC32 -> -0.005
B33: Repair & Maintenance | D33: ='DELA CRUZ'!N33 -> 7067.3077 | E33: ='DELA CRUZ'!N34 -> 816.66667 | F33: =D33-E33 -> 6250.641 | G33: ='DELA CRUZ'!N36 -> 0 | H33: ='DELA CRUZ'!N37 -> 0 | I33: =SUM(F33:H33) -> 6250.641 | J33: 0 | K33: 700 | N33: 0 | P33: 100 | T33: =SUM(K33:R33) -> 800 | U33: =I33+J33+S33-T33 -> 5450.641 | V33: 1000 | W33: 961.59 | Y33: =U33-SUM(V33:X33) -> 3489.051 | AA33: =Y59 -> 3137.62 | AB33: =Y33+Z33+AA33 -> 6626.671 | AC33: 6798.15 | AD33: =AB33-AC33 -> -171.47897
B34: Staff | D34: =ABREA!N33 -> 6000 | E34: =ABREA!N34 -> 0 | F34: =D34-E34 -> 6000 | G34: =ABREA!N36 -> 312.5 | H34: =ABREA!N37 -> 0 | I34: =SUM(F34:H34) -> 6312.5 | J34: 0 | K34: 650 | P34: 100 | Q34: 750 | R34: 250 | S34: 0 | T34: =SUM(K34:R34) -> 1750 | U34: =I34+J34+S34-T34 -> 4562.5 | V34: 3000 | W34: 822.16 | Y34: =U34-SUM(V34:X34) -> 740.34 | AB34: =Y34+Z34+AA34 -> 740.34 | AC34: 1409.09 | AD34: =AB34-AC34 -> -668.75
B35: Company Driver | D35: 7500 | F35: =D35-E35 -> 7500 | I35: =SUM(F35:H35) -> 7500 | J35: 2500 | K35: 750 | P35: 100 | Q35: 0 | S35: 0 | T35: =SUM(K35:R35) -> 850 | U35: =I35+J35+S35-T35 -> 9150 | V35: 2000 | W35: 2055.41 | Y35: =U35-SUM(V35:X35) -> 5094.59 | AA35: =-Y35 -> -5094.59 | AB35: =Y35+Z35+AA35 -> 0 | AD35: =AB35-AC35 -> 0
B36: Company Driver | D36: 7500 | F36: =D36-E36 -> 7500 | I36: =SUM(F36:H36) -> 7500 | J36: 2500 | K36: 750 | P36: 100 | Q36: 1250 | T36: =SUM(K36:R36) -> 2100 | U36: =I36+J36+S36-T36 -> 7900 | Y36: =U36-SUM(V36:X36) -> 7900 | AA36: =-Y36 -> -7900 | AB36: =Y36+Z36+AA36 -> 0 | AD36: =AB36-AC36 -> 0
B37: Company Driver | D37: 7500 | F37: =D37-E37 -> 7500 | I37: =SUM(F37:H37) -> 7500 | J37: 2500 | K37: 750 | P37: 100 | Q37: 0 | T37: =SUM(K37:R37) -> 850 | U37: =I37+J37+S37-T37 -> 9150 | Y37: =U37-SUM(V37:X37) -> 9150 | AA37: =-Y37 -> -9150 | AB37: =Y37+Z37+AA37 -> 0 | AD37: =AB37-AC37 -> 0
B38: Admin Asst. | D38: =ELEAZAR!N33 -> 6562.5 | E38: =ELEAZAR!N34 -> 3750 | F38: =D38-E38 -> 2812.5 | G38: =ELEAZAR!N36 -> 468.75 | H38: =ELEAZAR!N37 -> 0 | I38: =SUM(F38:H38) -> 3281.25 | P38: 0 | T38: =SUM(K38:R38) -> 0 | U38: =I38+J38+S38-T38 -> 3281.25 | Y38: =U38-SUM(V38:X38) -> 3281.25 | AA38: 0 | AB38: 0
F39: =D39-E39 -> 0 | I39: =SUM(F39:H39) -> 0 | T39: =SUM(K39:R39) -> 0 | U39: =I39+J39+S39-T39 -> 0 | AD39: =AB39-AC39 -> 0
B40: A/R Officer | D40: =ACOMPAÑADO!N33 -> 9106.7308 | E40: =ACOMPAÑADO!N34 -> 2892.4712 | F40: =D40-E40 -> 6214.2596 | G40: =ACOMPAÑADO!N36 -> 0 | H40: =ACOMPAÑADO!N37 -> 0 | I40: =SUM(F40:H40) -> 6214.2596 | J40: 1500 | K40: 900 | M40: 600 | N40: 1000 | O40: 2000 | P40: 100 | Q40: 750 | T40: =SUM(K40:R40) -> 5350 | U40: =I40+J40+S40-T40 -> 2364.2596 | V40: 2500 | W40: 1000 | Y40: =U40-SUM(V40:X40) -> -1135.7404 | Z40: =V67+W67+X67+P64 -> 99534.05 | AB40: =Y40+Z40+AA40 -> 98398.31 | AC40: 121866.96 | AD40: =AB40-AC40 -> -23468.65
B41: Finance Assistant | D41: =CONSUELO!N33 -> 10520 | E41: =CONSUELO!N34 -> 2023.0769 | F41: =D41-E41 -> 8496.9231 | H41: =CONSUELO!N37 -> 0 | I41: =SUM(F41:H41) -> 8496.9231 | J41: 1000 | K41: 1050 | N41: 1500 | O41: 1000 | P41: 100 | Q41: 1500 | T41: =SUM(K41:R41) -> 5150 | U41: =I41+J41+S41-T41 -> 4346.9231 | V41: 2500 | W41: 2500 | Y41: =U41-SUM(V41:X41) -> -653.07692 | AB41: =Y41+Z41+AA41 -> -653.07692 | AC41: 965.38 | AD41: =AB41-AC41 -> -1618.4569
B42: Accounting Clerk | D42: ='Accntng Clerk Salary Sample '!N33 -> 8661.8286 | E42: ='Accntng Clerk Salary Sample '!N34 -> 1653.9968 | F42: =D42-E42 -> 7007.8318 | G42: ='Accntng Clerk Salary Sample '!N36 -> 412.46803 | H42: ='Accntng Clerk Salary Sample '!N37 -> 0 | I42: =SUM(F42:H42) -> 7420.2998 | K42: 850 | M42: 500 | N42: 500 | O42: 2000 | P42: 100 | T42: =SUM(K42:R42) -> 3950 | U42: =I42+J42+S42-T42 -> 3470.2998 | V42: 1500 | W42: 2000 | Y42: =U42-SUM(V42:X42) -> -29.700161 | AB42: =Y42+Z42+AA42 -> -29.700161 | AC42: 737.49 | AD42: =AB42-AC42 -> -767.19016
B43: Bookkeeper | D43: =HERRERA!N33 -> 8224.0543 | E43: =HERRERA!N34 -> 0 | F43: =D43-E43 -> 8224.0543 | G43: =HERRERA!N36 -> 0 | H43: =HERRERA!N37 -> 0 | I43: =SUM(F43:H43) -> 8224.0543 | J43: 0 | K43: 825 | N43: 1667.95 | P43: 100 | T43: =SUM(K43:R43) -> 2592.95 | U43: =I43+J43+S43-T43 -> 5631.1043 | V43: 1000 | W43: 2500 | Y43: =U43-SUM(V43:X43) -> 2131.1043 | AB43: =Y43+Z43+AA43 -> 2131.1043 | AC43: 2342.58 | AD43: =AB43-AC43 -> -211.47567
F44: =D44-E44 -> 0 | I44: =SUM(F44:H44) -> 0 | T44: =SUM(K44:R44) -> 0 | U44: =I44+J44+S44-T44 -> 0 | Y44: =U44-SUM(V44:X44) -> 0 | AB44: =Y44+Z44+AA44 -> 0 | AD44: =AB44-AC44 -> 0
B45: Field Engineer | D45: =CAYAPAS!N33 -> 10201.62 | E45: =CAYAPAS!N34 -> 0 | F45: =D45-E45 -> 10201.62 | H45: =CAYAPAS!N37 -> 0 | I45: =SUM(F45:H45) -> 10201.62 | J45: 1500 | K45: 1025 | N45: 1000 | P45: 100 | T45: =SUM(K45:R45) -> 2125 | U45: =I45+J45+S45-T45 -> 9576.62 | V45: 1000 | W45: 4000 | Y45: =U45-SUM(V45:X45) -> 4576.62 | AB45: =Y45+Z45+AA45 -> 4576.62 | AC45: 4576.62 | AD45: =AB45-AC45 -> 0
B46: Field Staff | D46: 7000 | F46: =D46-E46 -> 7000 | I46: =SUM(F46:H46) -> 7000 | J46: 2500 | K46: 600 | N46: 43.95 | P46: 100 | Q46: 1000 | T46: =SUM(K46:R46) -> 1743.95 | U46: =I46+J46+S46-T46 -> 7756.05 | V46: 1000 | Y46: =U46-SUM(V46:X46) -> 6756.05 | AB46: =Y46+Z46+AA46 -> 6756.05 | AC46: 6756.05 | AD46: =AB46-AC46 -> 0
B47: Project Team Leader | D47: 9000 | F47: =D47-E47 -> 9000 | I47: =SUM(F47:H47) -> 9000 | J47: 3000 | K47: 900 | P47: 100 | T47: =SUM(K47:R47) -> 1000 | U47: =I47+J47+S47-T47 -> 11000 | V47: 3000 | W47: 1479.89 | Y47: =U47-SUM(V47:X47) -> 6520.11 | AB47: =Y47+Z47+AA47 -> 6520.11 | AC47: 6520.11 | AD47: =AB47-AC47 -> 0
B48: Project Team Leader | D48: 9500 | F48: =D48-E48 -> 9500 | I48: =SUM(F48:H48) -> 9500 | J48: 3000 | K48: 900 | P48: 100 | Q48: 1250 | S48: 0 | T48: =SUM(K48:R48) -> 2250 | U48: =I48+J48+S48-T48 -> 10250 | V48: 1000 | W48: 3367.83 | Y48: =U48-SUM(V48:X48) -> 5882.17 | AA48: =Y36+Y61 -> 14450 | AB48: =Y48+Z48+AA48 -> 20332.17 | AC48: 20332.17 | AD48: =AB48-AC48 -> 0
B49: Project Team Leader | D49: 8000 | F49: =D49-E49 -> 8000 | I49: =SUM(F49:H49) -> 8000 | J49: 3000 | K49: 800 | P49: 100 | T49: =SUM(K49:R49) -> 900 | U49: =I49+J49+S49-T49 -> 10100 | V49: 2500 | W49: 1225.41 | Y49: =U49-SUM(V49:X49) -> 6374.59 | AA49: =Y37+Y56 -> 16950 | AB49: =Y49+Z49+AA49 -> 23324.59 | AC49: 23324.59 | AD49: =AB49-AC49 -> 0
B50: Field Staff | D50: 7000 | F50: =D50-E50 -> 7000 | I50: =SUM(F50:H50) -> 7000 | J50: 2500 | K50: 700 | P50: 100 | T50: =SUM(K50:R50) -> 800 | U50: =I50+J50+S50-T50 -> 8700 | V50: 1000 | Y50: =U50-SUM(V50:X50) -> 7700 | AB50: =Y50+Z50+AA50 -> 7700 | AC50: 7700 | AD50: =AB50-AC50 -> 0
B51: Field Staff | D51: 7000 | F51: =D51-E51 -> 7000 | I51: =SUM(F51:H51) -> 7000 | J51: 2500 | K51: 700 | P51: 100 | Q51: 1500 | T51: =SUM(K51:R51) -> 2300 | U51: =I51+J51+S51-T51 -> 7200 | Y51: =U51-SUM(V51:X51) -> 7200 | AB51: =Y51+Z51+AA51 -> 7200 | AC51: 7200 | AD51: =AB51-AC51 -> 0
B52: Field Staff | D52: 7000 | F52: =D52-E52 -> 7000 | I52: =SUM(F52:H52) -> 7000 | J52: 2500 | K52: 600 | P52: 100 | T52: =SUM(K52:R52) -> 700 | U52: =I52+J52+S52-T52 -> 8800 | Y52: =U52-SUM(V52:X52) -> 8800 | AB52: =Y52+Z52+AA52 -> 8800 | AC52: 8800 | AD52: =AB52-AC52 -> 0
B53: Field Staff | D53: 7000 | F53: =D53-E53 -> 7000 | I53: =SUM(F53:H53) -> 7000 | J53: 2500 | K53: 600 | P53: 100 | T53: =SUM(K53:R53) -> 700 | U53: =I53+J53+S53-T53 -> 8800 | V53: 2000 | W53: 1194.63 | Y53: =U53-SUM(V53:X53) -> 5605.37 | AB53: =Y53+Z53+AA53 -> 5605.37 | AC53: 5605.37 | AD53: =AB53-AC53 -> 0
B54: Field Staff | D54: 6000 | F54: =D54-E54 -> 6000 | I54: =SUM(F54:H54) -> 6000 | J54: 2500 | K54: 600 | P54: 100 | T54: =SUM(K54:R54) -> 700 | U54: =I54+J54+S54-T54 -> 7800 | V54: 1000 | W54: 1923.18 | Y54: =U54-SUM(V54:X54) -> 4876.82 | AB54: =Y54+Z54+AA54 -> 4876.82 | AC54: 4876.82 | AD54: =AB54-AC54 -> 0
B55: Field Staff | D55: 6000 | F55: =D55-E55 -> 6000 | I55: =SUM(F55:H55) -> 6000 | J55: 2500 | K55: 600 | P55: 100 | Q55: 500 | T55: =SUM(K55:R55) -> 1200 | U55: =I55+J55+S55-T55 -> 7300 | Y55: =U55-SUM(V55:X55) -> 7300 | AB55: =Y55+Z55+AA55 -> 7300 | AC55: 7300 | AD55: =AB55-AC55 -> 0
B56: Field Staff | D56: 6000 | F56: =D56-E56 -> 6000 | I56: =SUM(F56:H56) -> 6000 | J56: 2500 | K56: 600 | P56: 100 | R56: 0 | T56: =SUM(K56:R56) -> 700 | U56: =I56+J56+S56-T56 -> 7800 | Y56: =U56-SUM(V56:X56) -> 7800 | AA56: =-Y56 -> -7800 | AB56: =Y56+Z56+AA56 -> 0 | AD56: =AB56-AC56 -> 0
B57: Field Staff | D57: 250 | F57: =D57-E57 -> 250 | I57: =SUM(F57:H57) -> 250 | J57: 2000 | K57: 250 | P57: 100 | T57: =SUM(K57:R57) -> 350 | U57: =I57+J57+S57-T57 -> 1900 | Y57: =U57-SUM(V57:X57) -> 1900 | AB57: =Y57+Z57+AA57 -> 1900 | AC57: 1900 | AD57: =AB57-AC57 -> 0
B58: Project Team Leader | D58: 8500 | F58: =D58-E58 -> 8500 | I58: =SUM(F58:H58) -> 8500 | J58: 3000 | K58: 850 | P58: 100 | S58: 0 | T58: =SUM(K58:R58) -> 950 | U58: =I58+J58+S58-T58 -> 10550 | V58: 3000 | W58: 3441.91 | Y58: =U58-SUM(V58:X58) -> 4108.09 | AA58: =Y35+Y60 -> 12894.59 | AB58: =Y58+Z58+AA58 -> 17002.68 | AC58: 17002.68 | AD58: =AB58-AC58 -> 0
B59: Field Staff | D59: =GALLARDO!N33 -> 8500 | E59: =GALLARDO!N34 -> 0 | F59: =D59-E59 -> 8500 | H59: =GALLARDO!N37 -> 0 | I59: =SUM(F59:H59) -> 8500 | K59: 850 | P59: 100 | Q59: 1000 | R59: 250 | T59: =SUM(K59:R59) -> 2200 | U59: =I59+J59+S59-T59 -> 6300 | V59: 1000 | W59: 2162.38 | Y59: =U59-SUM(V59:X59) -> 3137.62 | AA59: =-Y59 -> -3137.62 | AB59: =Y59+Z59+AA59 -> 0 | AD59: =AB59-AC59 -> 0
B60: Field Staff | D60: 6000 | F60: =D60-E60 -> 6000 | I60: =SUM(F60:H60) -> 6000 | J60: 2500 | K60: 600 | P60: 100 | Q60: 0 | T60: =SUM(K60:R60) -> 700 | U60: =I60+J60+S60-T60 -> 7800 | W60: . | Y60: =U60-SUM(V60:X60) -> 7800 | AA60: =-Y60 -> -7800 | AB60: =Y60+Z60+AA60 -> 0 | AD60: =AB60-AC60 -> 0
B61: Field Staff | D61: 6000 | F61: =D61-E61 -> 6000 | I61: =SUM(F61:H61) -> 6000 | J61: 2500 | K61: 600 | P61: 100 | Q61: 1250 | T61: =SUM(K61:R61) -> 1950 | U61: =I61+J61+S61-T61 -> 6550 | W61: . | Y61: =U61-SUM(V61:X61) -> 6550 | AA61: =-Y61 -> -6550 | AB61: =Y61+Z61+AA61 -> 0 | AD61: =AB61-AC61 -> 0
B62: Asst. Field Engineer | D62: =EDON!N32 -> 9500 | E62: =EDON!N33 -> 822.11538 | F62: =D62-E62 -> 8677.8846 | H62: =EDON!N36 -> 0 | I62: =SUM(F62:H62) -> 8677.8846 | K62: 950 | P62: 100 | Q62: 0 | T62: =SUM(K62:R62) -> 1050 | U62: =I62+J62+S62-T62 -> 7627.8846 | W62: . | Y62: =U62-SUM(V62:X62) -> 7627.8846 | AA62: =-Y62 -> -7627.8846 | AB62: =Y62+Z62+AA62 -> 0 | AD62: =AB62-AC62 -> 0
F63: =D63-E63 -> 0 | I63: =SUM(F63:H63) -> 0 | T63: =SUM(K63:R63) -> 0 | U63: =I63+J63+S63-T63 -> 0 | Y63: =U63-SUM(V63:W63) -> 0 | AB63: =Y63+Z63+AA63 -> 0 | AD63: =AB63-AC63 -> 0
A64: Total Payroll | D64: =SUM(D10:D63) -> 329670.24 | E64: =SUM(E10:E63) -> 17644.574 | F64: =SUM(F10:F63) -> 312025.67 | G64: =SUM(G10:G63) -> 7211.0007 | H64: =SUM(H10:H63) -> 0 | I64: =SUM(I10:I63) -> 319236.67 | J64: =SUM(J10:J63) -> 59800 | K64: =SUM(K10:K63) -> 32050 | ... AD64: =SUM(AD10:AD63) -> -22987.367
Y65: =U65-V65-W65 -> 0
S66: Noted by: | T66: Kian | U66: 5000 | V66: 1500 | X66: 250 | Y66: =U66-V66-W66-X66 -> 3250 | AB66: =Y66+Z66 -> 3250 | AC66: 3250 | AD66: 3250
A67: Prepared By: | F67: Checked By: | N67: Approved By: | U67: =U64+U65+U66 -> 314536.37 | V67: =V64+V66 -> 44000 | W67: =W64+W66 -> 50884.05 | X67: =X64+X66 -> 250 | Y67: =Y64+Y66+Y65 -> 219402.32 | Z67: =Z64+Z66 -> 99534.05 | AA67: =AA64+AA66 -> 0 | AB67: =AB64+AB66+AB65 -> 312545.74 | AC67: =SUM(AC64:AC66) -> 335533.11 | AD67: =AD64+AD65+AD66 -> -19737.367
S68: CESARIO A. BACOSA JR.
S69: CEO/President
A72: Note Retro:

Sheet ADMIN (2)
B7: NAME: | C7: Beltran, Lyn M. | D7: PERIOD: | E7: APRIL 25- MAY 10, 2022 | G7: NAME: | H7: Gaid, Dorabel | I7: PERIOD: | J7: =E7 -> APRIL 25- MAY 10, 2022
B8: DESIGNATION: | C8: Admin | D8: Release Date: | E8: 44696 | G8: DESIGNATION: | H8: Admin Assistant | I8: Release Date: | J8: 44696
B11: EARNINGS | D11: DEDUCTION | E11: AMOUNT | G11: EARNINGS | I11: DEDUCTION | J11: AMOUNT
B12: Basic Salary | C12: 12750 | D12: Absences/Tardiness/ Undertime | E12: #REF! | G12: Basic Salary | H12: 8000 | I12: Absences/Tardiness/ Undertime | J12: =#REF! -> #REF!
B13: De Minimis | C13: 4250 | D13: Cash Advance / Loan | E13: 3480 | G13: De Minimis | I13: Cash Advance / Loan
B14: Refund / Retro | D14: SSS | G14: Refund / Retro | I14: SSS
B15: Overtime Pay | D15: PhilHealth | E15: 382.5 | G15: Overtime Pay | H15: =#REF! -> #REF! | I15: PhilHealth
B16: Holiday Pay | D16: Pag-Ibig | E16: 500 | G16: Holiday Pay | I16: Pag-Ibig
B17: Premium Pay | D17: Income Tax | E17: 466.7 | G17: Premium Pay | I17: Income Tax
D18: Insurance/s | E18: 147.17 | I18: Insurance/s
D19: Communication Allow. | E19: 250 | I19: Communication Allow.
B21: TOTAL EARNINGS: | C21: =SUM(C12:C19) -> 17000 | D21: TOTAL DEDUCTION: | E21: =SUM(E13:E19) -> 5226.37 | G21: TOTAL EARNINGS: | H21: =SUM(H12:H19) -> #REF! | I21: TOTAL DEDUCTION: | J21: =SUM(J12:J19) -> #REF!
B23: NET PAY: | E23: =C21-E21 -> 11773.63 | G23: NET PAY: | J23: =H21-J21 -> #REF!
B25: Prepared By: | C25: Approved By: | D25: Received By | G25: Prepared By: | H25: Approved By: | I25: Received By
B27: DORABEL Y. GAID | C27: KATHERINE J. BACOSA | D27: _____________________________ | G27: DORABEL Y. GAID | H27: KATHERINE J. BACOSA | I27: _____________________________
B28: Admin Assistant | C28: Finance Manager | D28: Employee's Signature w/ Printed Name | G28: Admin Assistant | H28: Finance Manager | I28: Employee's Signature w/ Printed Name
B37: NAME: | C37: Guerzo, Jovelyn H. | D37: PERIOD: | E37: APRIL 25- MAY 10, 2022 | G37: NAME: | H37: Jamelo, Elfren | I37: PERIOD: | J37: APRIL 25- MAY 10, 2022
B38: DESIGNATION: | C38: EHS Head | D38: Release Date: | E38: 44696 | G38: DESIGNATION: | H38: Amansinaya | I38: Release Date: | J38: 44696
B40: EARNINGS | D40: DEDUCTION | E40: AMOUNT | G40: EARNINGS | I40: DEDUCTION | J40: AMOUNT
B41: Basic Salary | C41: 9250 | D41: Absences/Tardiness/ Undertime | E41: #REF! | G41: Basic Salary | H41: 7500 | I41: Absences/Tardiness/ Undertime | J41: #REF!
B42: De Minimis | D42: Cash Advance / Loan | E42: #REF! | G42: De Minimis | H42: 2000 | I42: Cash Advance / Loan | J42: #REF!
B43: Refund / Retro | D43: SSS | G43: Refund / Retro | I43: SSS
B44: Overtime Pay | D44: PhilHealth | E44: 277.5 | G44: Overtime Pay | I44: PhilHealth | J44: 225
B45: Holiday Pay | D45: Pag-Ibig | E45: 100 | G45: Holiday Pay | I45: Pag-Ibig | J45: #REF!
B46: Premium Pay | D46: Income Tax | G46: Premium Pay | I46: Income Tax
D47: Insurance/s | E47: 109.23 | I47: Insurance/s | J47: 109.23
D48: Communication Allow. | I48: Communication Allow.
B50: TOTAL EARNINGS: | C50: =SUM(C41:C48) -> 9250 | D50: TOTAL DEDUCTION: | E50: =SUM(E42:E48) -> #REF! | G50: TOTAL EARNINGS: | H50: =SUM(H41:H48) -> 9500 | I50: TOTAL DEDUCTION: | J50: =SUM(J42:J48) -> #REF!
B52: NET PAY: | E52: =C50-E50 -> #REF! | G52: NET PAY: | J52: =H50-J50 -> #REF!
B54: Prepared By: | C54: Approved By: | D54: Received By | G54: Prepared By: | H54: Approved By: | I54: Received By
B56: DORABEL Y. GAID | C56: KATHERINE J. BACOSA | D56: _____________________________ | G56: DORABEL Y. GAID | H56: KATHERINE J. BACOSA | I56: _____________________________
B57: Admin Assistant | C57: Finance Manager | D57: Employee's Signature w/ Printed Name | G57: Admin Assistant | H57: Finance Manager | I57: Employee's Signature w/ Printed Name
B64: NAME: | C64: Macatangay, Michael | D64: PERIOD: | E64: APRIL 25- MAY 10, 2022 | G64: NAME: | H64: Aurelio, Roderic | I64: PERIOD: | J64: APRIL 25- MAY 10, 2022
B65: DESIGNATION: | C65: Company Driver | D65: Release Date: | E65: 44696 | G65: DESIGNATION: | H65: Utility | I65: Release Date: | J65: 44696
B67: EARNINGS | D67: DEDUCTION | E67: AMOUNT | G67: EARNINGS | I67: DEDUCTION | J67: AMOUNT
B68: Basic Salary | C68: 7500 | D68: Absences/Tardiness/ Undertime | E68: #REF! | G68: Basic Salary | H68: 5000 | I68: Absences/Tardiness/ Undertime | J68: 384.62
B69: De Minimis | C69: 1000 | D69: Cash Advance / Loan | E69: #REF! | G69: De Minimis | H69: #REF! | I69: Cash Advance / Loan | J69: #REF!
B70: Refund / Retro | D70: SSS | G70: Refund / Retro | I70: SSS
B71: Overtime Pay | D71: PhilHealth | E71: 225 | G71: Overtime Pay | I71: PhilHealth | J71: 150
B72: Holiday Pay | D72: Pag-Ibig | E72: 100 | G72: Holiday Pay | H72: 1269.23 | I72: Pag-Ibig | J72: 100
B73: Premium Pay | D73: Income Tax | G73: Premium Pay | I73: Income Tax
D74: Insurance/s | E74: 142.58 | I74: Insurance/s
D75: Communication Allow. | I75: Communication Allow.
B77: TOTAL EARNINGS: | C77: =SUM(C68:C75) -> 8500 | D77: TOTAL DEDUCTION: | E77: =SUM(E69:E75) -> #REF! | G77: TOTAL EARNINGS: | H77: =SUM(H68:H75) -> #REF! | I77: TOTAL DEDUCTION: | J77: =SUM(J68:J75) -> #REF!
B79: NET PAY: | E79: =C77-E77 -> #REF! | G79: NET PAY: | J79: =H77-J77 -> #REF!
B81: Prepared By: | C81: Approved By: | D81: Received By | G81: Prepared By: | H81: Approved By: | I81: Received By
B83: DORABEL Y. GAID | C83: KATHERINE J. BACOSA | D83: _____________________________ | G83: DORABEL Y. GAID | H83: KATHERINE J. BACOSA | I83: _____________________________
B84: Admin Assistant | C84: Finance Manager | D84: Employee's Signature w/ Printed Name | G84: Admin Assistant | H84: Finance Manager | I84: Employee's Signature w/ Printed Name
B92: NAME: | C92: Galedo, Joshua Jover | D92: PERIOD: | E92: APRIL 25- MAY 10, 2022
B93: DESIGNATION: | C93: GSS | D93: Release Date: | E93: 44696
B95: EARNINGS | D95: DEDUCTION | E95: AMOUNT
B96: Basic Salary | C96: 7500 | D96: Absences/Tardiness/ Undertime | E96: #REF!
B97: De Minimis | C97: #REF! | D97: Cash Advance / Loan | E97: #REF!
B98: Refund / Retro | D98: SSS
B99: Overtime Pay | D99: PhilHealth | E99: 225
B100: Holiday Pay | D100: Pag-Ibig | E100: 100
B101: Premium Pay | D101: Income Tax
D102: Insurance/s | E102: 71.29
D103: Communication Allow.
B105: TOTAL EARNINGS: | C105: =SUM(C96:C103) -> #REF! | D105: TOTAL DEDUCTION: | E105: =SUM(E97:E103) -> #REF!
B107: NET PAY: | E107: =C105-E105 -> #REF!
B109: Prepared By: | C109: Approved By: | D109: Received By
B111: DORABEL Y. GAID | C111: KATHERINE J. BACOSA | D111: _____________________________
B112: Admin Assistant | C112: Finance Manager | D112: Employee's Signature w/ Printed Name

Sheet Data
A1: Years | B1: Months | C1: Days | D1: Weekend | F1: Check Box
A2: 2015 | B2: January | C2: 1 | D2: No Weekend | F2: TRUE
A3: 2016 | B3: February | C3: 2 | D3: Sat & Sun
A4: 2017 | B4: March | C4: 3 | D4: Sun & Mon
A5: 2018 | B5: April | C5: 4 | D5: Mon & Tue
A6: 2019 | B6: May | C6: 5 | D6: Tue & Wed
A7: 2020 | B7: June | C7: 6 | D7: Wed & Thu
A8: 2021 | B8: July | C8: 7 | D8: Thu & Fri
A9: 2022 | B9: August | C9: 8 | D9: Fri & Sat
A10: 2023 | B10: September | C10: 9 | D10: Mon Only
A11: 2024 | B11: October | C11: 10 | D11: Tue Only
A12: 2025 | B12: November | C12: 11 | D12: Wed Only
A13: 2026 | B13: December | C13: 12 | D13: Thu Only
A14: 2027 | C14: 13 | D14: Fri Only
A15: 2028 | C15: 14 | D15: Sat Only
C16: 15 | D16: Sun Only
C17: 16
C18: 17
C19: 18
C20: 19
C21: 20
C22: 21
C23: 22
C24: 23
C25: 24
C26: 25
C27: 26
C28: 27
... C32: 31

Sheet PS(G)
A6: NAME | B6: : LYN M. BELTRAN | E6: NAME | F6: : KATHERINE J. BACOSA
A7: PAYROLL DATE | B7: : 30 JUNE 2026 | E7: PAYROLL DATE | F7: =B7 -> : 30 JUNE 2026
A8: DATE COVERED | B8: : 06/11/2026 - 06/25/2026 | E8: DATE COVERED | F8: =B8 -> : 06/11/2026 - 06/25/2026
A9: DEPARTMENT | B9: : Admin | E9: DEPARTMENT | F9: : Finance
A10: POSITION | B10: : Head | E10: POSITION | F10: : Finance Manager
A11: COMPENSATION | C11: DEDUCTIONS | E11: COMPENSATION | G11: DEDUCTIONS
A12: BASIC | B12: ='SEPT 30'!D12 -> 0 | C12: CASH ADVANCE | D12: 0 | E12: BASIC | F12: 12020 | G12: CASH ADVANCE | H12: 0
A13: DE MINIMIS BENEFITS | B13: 4250 | C13: PHONE LOAN | D13: 0 | E13: DE MINIMIS BENEFITS | F13: 3500 | G13: PHONE LOAN | H13: 0
A14: OVERTIME | B14: 0 | C14: ALLOWANCE | D14: 0 | E14: OVERTIME | F14: 0 | G14: SSS LOAN | H14: 1500
A15: HOLIDAY PAY | B15: 0 | C15: RCBC | D15: 1500 | E15: HOLIDAY PAY | F15: 0 | G15: RCBC | H15: 0
A16: INCENTIVES/REFUND | B16: 0 | C16: SSS | D16: 1375 | E16: INCENTIVES/REFUND | F16: 0 | G16: SSS | H16: 1200
C17: SSS LOAN | D17: 2000 | G17: BPI INSURANCE | H17: 0
C18: BPI INSURANCE | D18: 0 | G18: PHILHEALTH | H18: 0
C19: HDMF | D19: 0 | G19: HDMF | H19: 0
C20: TAX | D20: ='SEPT 30'!L12 -> 0 | G20: TAX | H20: 0
C21: MEDICAL POOLING | D21: 400 | G21: MEDICAL POOLING | H21: 100
A22: TOTAL COMPENSATION | B22: =SUM(B12:B21) -> 4250 | C22: TOTAL DEDUCTIONS | D22: =SUM(D12:D21) -> 5275 | E22: TOTAL COMPENSATION | F22: =SUM(F12:F21) -> 15520 | G22: TOTAL DEDUCTIONS | H22: =SUM(H12:H21) -> 2800
A23: NET PAY | C23: =B22-D22 -> -1025 | E23: NET PAY | G23: =F22-H22 -> 12720
A25: Prepared By: | C25: Approved By: | E25: Prepared By: | G25: Approved By:
A27: DORABEL Y. GAID | C27: KATHERINE J. BACOSA | E27: DORABEL Y. GAID | G27: KATHERINE J. BACOSA
A28: Admin Assistant | C28: Finance Manager | E28: Admin Assistant | G28: Finance Manager
A38: NAME | B38: : JOVELYN H. GUERZO | E38: NAME | F38: : REGINE C. CONSUELO
A39: PAYROLL DATE | B39: =B7 -> : 30 JUNE 2026 | E39: PAYROLL DATE | F39: =B7 -> : 30 JUNE 2026
A40: DATE COVERED | B40: =B8 -> : 06/11/2026 - 06/25/2026 | E40: DATE COVERED | F40: =B8 -> : 06/11/2026 - 06/25/2026
A41: DEPARTMENT | B41: : Admin | E41: DEPARTMENT | F41: : Finance
A42: POSITION | B42: : EHS Head | E42: POSITION | F42: : Finance Assistant
A43: COMPENSATION | C43: DEDUCTIONS | E43: COMPENSATION | G43: DEDUCTIONS
A44: BASIC | B44: ='SEPT 30'!D30 -> 10270 | C44: CASH ADVANCE | D44: 0 | E44: BASIC | F44: ='SEPT 30'!D41 -> 10520 | G44: CASH ADVANCE | H44: 1500
A45: DE MINIMIS BENEFITS | B45: 2500 | C45: RCBC | D45: 3000 | E45: DE MINIMIS BENEFITS | F45: 1000 | G45: RCBC | H45: 1000
A46: OVERTIME | B46: 0 | C46: SSS | D46: 1025 | E46: OVERTIME | F46: 0 | G46: SSS | H46: 1050
A47: HOLIDAY PAY | B47: ='SEPT 30'!H30 -> 0 | C47: SSS LOAN | D47: 900 | E47: HOLIDAY PAY | F47: ='SEPT 30'!H41 -> 0 | G47: SSS LOAN | H47: 1000
A48: INCENTIVES/REFUND | B48: 0 | C48: PHILHEALTH | D48: 0 | E48: INCENTIVES/REFUND | F48: 0 | G48: PHILHEALTH | H48: 0
C49: HDMF | D49: 0 | G49: HDMF | H49: 0
C50: HDMF LOAN | G50: HDMF LOAN | H50: 500
A51: LATE & ABSENCES | B51: ='SEPT 30'!E30 -> 0 | C51: PHONE LOAN | E51: LATE & ABSENCES | F51: ='SEPT 30'!E41 -> 2023.0769 | G51: PHONE LOAN | H51: 0
C52: MEDICAL POOLING | D52: 100 | G52: MEDICAL POOLING | H52: 100
H53: 0
A54: TOTAL COMPENSATION | B54: =SUM(B44:B48)-B51 -> 12770 | C54: TOTAL DEDUCTIONS | D54: =SUM(D44:D53) -> 5025 | E54: TOTAL COMPENSATION | F54: =SUM(F44:F48)-F51 -> 9496.9231 | G54: TOTAL DEDUCTIONS | H54: =SUM(H44:H53) -> 5150
A55: NET PAY | C55: =B54-D54 -> 7745 | E55: NET PAY | G55: =F54-H54 -> 4346.9231
A57: Prepared By: | C57: Approved By: | E57: Prepared By: | G57: Approved By:
A59: DORABEL Y. GAID | C59: KATHERINE J. BACOSA | E59: DORABEL Y. GAID | G59: KATHERINE J. BACOSA
A60: Admin Assistant | C60: Finance Manager | E60: Admin Assistant | G60: Finance Manager
A68: NAME | B68: : DORABEL GAID | E68: NAME | F68: : ENGR. MECHELLE PATRICIO
A69: PAYROLL DATE | B69: =B7 -> : 30 JUNE 2026 | E69: PAYROLL DATE | F69: =B7 -> : 30 JUNE 2026
A70: DATE COVERED | B70: =B8 -> : 06/11/2026 - 06/25/2026 | E70: DATE COVERED | F70: =B8 -> : 06/11/2026 - 06/25/2026
A71: DEPARTMENT | B71: : Admin | E71: DEPARTMENT | F71: : Project Management & Operation & Operation
A72: POSITION | B72: : Administrative Head | E72: POSITION | F72: : Geotechnical Supervisor
A73: COMPENSATION | C73: DEDUCTIONS | E73: COMPENSATION | G73: DEDUCTIONS
A74: BASIC | B74: ='SEPT 30'!D29 -> 9020 | C74: CASH ADVANCE | D74: 0 | E74: BASIC | F74: ='SEPT 30'!D17 -> 9216.64 | G74: CASH ADVANCE | H74: 0
A75: DE MINIMIS BENEFITS | B75: 0 | C75: RCBC | D75: 0 | E75: DE MINIMIS BENEFITS | F75: 1500 | G75: RCBC | H75: 0
A76: OVERTIME | B76: ='SEPT 30'!G29 -> 0 | C76: SSS | D76: 900 | E76: OVERTIME | F76: ='SEPT 30'!G17 -> 0 | G76: SSS | H76: 925
A77: HOLIDAY PAY | B77: ='SEPT 30'!H29 -> 0 | C77: SSS LOAN | D77: 0 | E77: HOLIDAY PAY | F77: ='SEPT 30'!H17 -> 0 | G77: SSS LOAN | H77: 0
A78: INCENTIVES/REFUND | B78: 0 | C78: PHILHEALTH | D78: 0 | E78: INCENTIVES/REFUND | F78: ='SEPT 30'!S17 -> 0 | G78: PHILHEALTH | H78: 0
C79: HDMF | D79: 0 | G79: HDMF | H79: 0
C80: HDMF LOAN | D80: 500 | G80: HDMF LOAN | H80: 0
A81: LATE & ABSENCES | B81: ='SEPT 30'!E29 -> 346.92308 | C81: PHONE LOAN | D81: 0 | E81: LATE & ABSENCES | F81: ='SEPT 30'!E17 -> 0 | G81: PHONE LOAN | H81: 0
C82: MEDICAL POOLING | D82: 200 | G82: MEDICAL POOLING | H82: 200
A84: TOTAL COMPENSATION | B84: =SUM(B74:B78)-B81 -> 8673.0769 | C84: TOTAL DEDUCTIONS | D84: =SUM(D74:D83) -> 1600 | E84: TOTAL COMPENSATION | F84: =SUM(F74:F78)-F81 -> 10716.64 | G84: TOTAL DEDUCTIONS | H84: =SUM(H74:H83) -> 1125
A85: NET PAY | C85: =B84-D84 -> 7073.0769 | E85: NET PAY | G85: =F84-H84 -> 9591.64
A87: Prepared By: | C87: Approved By: | E87: Prepared By: | G87: Approved By:
A89: DORABEL Y. GAID | C89: KATHERINE J. BACOSA | E89: DORABEL Y. GAID | G89: KATHERINE J. BACOSA
A90: Admin Assistant | C90: Finance Manager | E90: Admin Assistant | G90: Finance Manager
A100: NAME | B100: : NANCY A. ACOMPAÑADO | E100: NAME | F100: : JANELLE BUNGAY
A101: PAYROLL DATE | B101: =B7 -> : 30 JUNE 2026 | E101: PAYROLL DATE | F101: =B7 -> : 30 JUNE 2026
A102: DATE COVERED | B102: =B8 -> : 06/11/2026 - 06/25/2026 | E102: DATE COVERED | F102: =B8 -> : 06/11/2026 - 06/25/2026
A103: DEPARTMENT | B103: : Finance | E103: DEPARTMENT | F103: : Project Management & Operation & Operation
A104: POSITION | B104: : Accounts Receivable Officer | E104: POSITION | F104: : Technical Staff
A105: COMPENSATION | C105: DEDUCTIONS | E105: COMPENSATION | G105: DEDUCTIONS
A106: BASIC | B106: ='SEPT 30'!D40 -> 9106.7308 | C106: CASH ADVANCE | D106: 750 | E106: BASIC | F106: ='SEPT 30'!D21 -> 6562.5 | G106: CASH ADVANCE | H106: 0
A107: DE MINIMIS BENEFITS | B107: 1500 | C107: RCBC | D107: 2000 | E107: DE MINIMIS BENEFITS | F107: 0 | G107: RCBC | H107: 0
A108: OVERTIME | B108: ='SEPT 30'!G40 -> 0 | C108: SSS | D108: 900 | E108: OVERTIME | F108: ='SEPT 30'!G21 -> 703.125 | G108: SSS | H108: 650
A109: HOLIDAY PAY | B109: ='SEPT 30'!H40 -> 0 | C109: SSS LOAN | D109: 1000 | E109: HOLIDAY PAY | F109: ='SEPT 30'!H21 -> 0 | G109: SSS LOAN | H109: 0
A110: INCENTIVES/REFUND | B110: 0 | C110: PHILHEALTH | D110: 0 | E110: INCENTIVES/REFUND | F110: 0 | G110: PHILHEALTH | H110: 0
C111: HDMF | D111: 0 | G111: HDMF | H111: 0
C112: HDMF LOAN | D112: 600 | G112: HDMF LOAN | H112: 0
A113: LATE & ABSENCES | B113: ='SEPT 30'!E40 -> 2892.4712 | C113: PHONE LOAN | D113: 0 | E113: LATE & ABSENCES | F113: ='SEPT 30'!E21 -> 0 | G113: PHONE LOAN
C114: MEDICAL POOLING | D114: 100 | G114: MEDICAL POOLING | H114: 100
D115: 0 | H115: 0
A116: TOTAL COMPENSATION | B116: =SUM(B106:B110)-B113 -> 7714.2596 | C116: TOTAL DEDUCTIONS | D116: =SUM(D106:D115) -> 5350 | E116: TOTAL COMPENSATION | F116: =SUM(F106:F110)-F113 -> 7265.625 | G116: TOTAL DEDUCTIONS | H116: =SUM(H106:H115) -> 750
A117: NET PAY | C117: =B116-D116 -> 2364.2596 | E117: NET PAY | G117: =F116-H116 -> 6515.625
A119: Prepared By: | C119: Approved By: | E119: Prepared By: | G119: Approved By:
A121: DORABEL Y. GAID | C121: KATHERINE J. BACOSA | E121: DORABEL Y. GAID | G121: KATHERINE J. BACOSA
A122: Admin Assistant | C122: Finance Manager | E122: Admin Assistant | G122: Finance Manager
A130: NAME | B130: : JAN KAYLE MARI MALAZARTE | E130: NAME | F130: : JENNYVELLE BARORO
A131: PAYROLL DATE | B131: =B7 -> : 30 JUNE 2026 | E131: PAYROLL DATE | F131: =B7 -> : 30 JUNE 2026
A132: DATE COVERED | B132: =B8 -> : 06/11/2026 - 06/25/2026 | E132: DATE COVERED | F132: =B8 -> : 06/11/2026 - 06/25/2026
A133: DEPARTMENT | B133: : Project Management & Operation & Operation | E133: DEPARTMENT | F133: :
A134: POSITION | B134: : Survey & Technical Staff | E134: POSITION | F134: : Jr. Sales Engineer
A135: COMPENSATION | C135: DEDUCTIONS | E135: COMPENSATION | G135: DEDUCTIONS
A136: BASIC | B136: ='SEPT 30'!D19 -> 9963.4803 | C136: CASH ADVANCE | D136: 0 | E136: BASIC | F136: ='SEPT 30'!D26 -> 6562.5 | G136: CASH ADVANCE | H136: 0
A137: DE MINIMIS BENEFITS | B137: 0 | C137: RCBC | D137: 500 | E137: DE MINIMIS BENEFITS | F137: 1300 | G137: RCBC | H137: 0
A138: OVERTIME | B138: ='SEPT 30'!G19 -> 1186.1286 | C138: SSS | D138: 1000 | E138: OVERTIME | F138: ='SEPT 30'!G26 -> 1015.625 | G138: SSS | H138: 650
A139: HOLIDAY PAY | B139: ='SEPT 30'!H19 -> 0 | C139: SSS LOAN | D139: 800 | E139: HOLIDAY PAY | F139: ='SEPT 30'!H26 -> 0 | G139: SSS LOAN | H139: 0
A140: INCENTIVES/REFUND | B140: 0 | C140: PHILHEALTH | D140: 0 | E140: INCENTIVES/REFUND | F140: ='SEPT 30'!S26 -> 0 | G140: PHILHEALTH | H140: 0
C141: HDMF | D141: 0 | G141: HDMF | H141: 0
C142: HDMF LOAN | D142: 0 | G142: HDMF LOAN | H142: 0
A143: LATE & ABSENCES | B143: ='SEPT 30'!E19 -> 863.50162 | C143: PHONE LOAN | D143: 0 | E143: LATE & ABSENCES | F143: ='SEPT 30'!E26 -> 187.5 | G143: PHONE LOAN
C144: MEDICAL POOLING | D144: 100 | G144: MEDICAL POOLING | H144: 100
H145: 0
A146: TOTAL COMPENSATION | B146: =SUM(B136:B140)-B143 -> 10286.107 | C146: TOTAL DEDUCTIONS | D146: =SUM(D136:D145) -> 2400 | E146: TOTAL COMPENSATION | F146: =SUM(F136:F140)-F143 -> 8690.625 | G146: TOTAL DEDUCTIONS | H146: =SUM(H136:H145) -> 750
...

Sheet PS(B)
A6: NAME | B6: : ENGR. CESARIO A. BACOSA JR. | E6: NAME | F6: : ENGR. GERALD S. FERNANDEZ
A7: PAYROLL DATE | B7: : 30 JUNE 2026 | E7: PAYROLL DATE | F7: =B7 -> : 30 JUNE 2026
A8: DATE COVERED | B8: : 06/11/2026 - 06/25/2026 | E8: DATE COVERED | F8: =B8 -> : 06/11/2026 - 06/25/2026
A9: DEPARTMENT | B9: : | E9: DEPARTMENT | F9: : Project Management & Operation
A10: POSITION | B10: : CEO | E10: POSITION | F10: : Jr. Office Engineer
A11: COMPENSATION | C11: DEDUCTIONS | E11: COMPENSATION | G11: DEDUCTIONS
A12: BASIC | B12: 20000 | C12: CASH ADVANCE | D12: 0 | E12: BASIC | F12: ='SEPT 30'!D18 -> 10000 | G12: CASH ADVANCE | H12: 0
A13: DE MINIMIS BENEFITS | B13: 5000 | C13: OTHER DEDUCTION | D13: 0 | E13: DE MINIMIS BENEFITS | F13: 1500 | G13: RCBC | H13: 0
A14: OVERTIME | B14: 0 | C14: ALLOWANCE | D14: 0 | E14: OVERTIME | F14: ='SEPT 30'!G18 -> 0 | G14: SSS | H14: 925
A15: HOLIDAY PAY | B15: 0 | C15: RCBC | D15: 0 | E15: HOLIDAY PAY | F15: ='SEPT 30'!H18 -> 0 | G15: SSS LOAN | H15: 0
A16: INCENTIVES/REFUND | B16: 0 | C16: SSS | D16: 0 | E16: INCENTIVES/REFUND | F16: 0 | G16: PHILHEALTH | H16: 0
C17: MEDICAL POOLING | D17: 100 | G17: HDMF | H17: 0
C18: PHILHEALTH | D18: 0 | G18: HDMF LOAN | H18: 0
C19: HDMF | D19: 0 | E19: LATE & ABSENCES | F19: ='SEPT 30'!E18 -> 480.76923 | G19: PHONE LOAN | H19: 0
C20: TAX | D20: 0 | G20: MEDICAL POOLING | H20: 100
H21: 0
A22: TOTAL COMPENSATION | B22: =SUM(B12:B21) -> 25000 | C22: TOTAL DEDUCTIONS | D22: =SUM(D12:D21) -> 100 | E22: TOTAL COMPENSATION | F22: =SUM(F12:F16)-F19 -> 11019.231 | G22: TOTAL DEDUCTIONS | H22: =SUM(H12:H21) -> 1025
A23: NET PAY | C23: =B22-D22 -> 24900 | E23: NET PAY | G23: =F22-H22 -> 9994.2308
A25: Prepared By: | C25: Approved By: | E25: Prepared By: | G25: Approved By:
A27: DORABEL Y. GAID | C27: KATHERINE J. BACOSA | E27: DORABEL Y. GAID | G27: KATHERINE J. BACOSA
A28: Admin Assistant | C28: Finance Manager | E28: Admin Assistant | G28: Finance Manager
A38: NAME | B38: : MARK JAYSON H. GERMINA | E38: NAME | F38: : BASA, CRIS JANREY
A39: PAYROLL DATE | B39: =B7 -> : 30 JUNE 2026 | E39: PAYROLL DATE | F39: =B7 -> : 30 JUNE 2026
A40: DATE COVERED | B40: =B8 -> : 06/11/2026 - 06/25/2026 | E40: DATE COVERED | F40: =B8 -> : 06/11/2026 - 06/25/2026
A41: DEPARTMENT | B41: : Project Management & Operation | E41: DEPARTMENT | F41: : Project Management & Operation
A42: POSITION | B42: : Head | E42: POSITION | F42: : Laboratory Operator
A43: COMPENSATION | C43: DEDUCTIONS | E43: COMPENSATION | G43: DEDUCTIONS
A44: BASIC | B44: 14250 | C44: CASH ADVANCE | D44: 513.75 | E44: BASIC | F44: ='SEPT 30'!D22 -> 8532.4161 | G44: CASH ADVANCE | H44: 0
A45: DE MINIMIS BENEFITS | B45: 7442.5 | C45: RCBC | D45: 3169.87 | E45: DE MINIMIS BENEFITS | F45: 0 | G45: RCBC | H45: 0
A46: OVERTIME | B46: 0 | C46: SSS | D46: 1225 | E46: OVERTIME | F46: ='SEPT 30'!G22 -> 0 | G46: SSS | H46: 850
A47: HOLIDAY PAY | B47: 0 | C47: SSS LOAN | D47: 0 | E47: HOLIDAY PAY | F47: ='SEPT 30'!H22 -> 0 | G47: SSS LOAN | H47: 0
A48: INCENTIVES/REFUND | B48: 0 | C48: PHILHEALTH | D48: 0 | E48: INCENTIVES/REFUND | F48: 0 | G48: PHILHEALTH | H48: 0
C49: HDMF | D49: 0 | G49: HDMF | H49: 0
C50: HDMF LOAN | D50: 0 | G50: HDMF LOAN | H50: 0
A51: LATE & ABSENCES | C51: PHONE LOAN | D51: 0 | E51: LATE & ABSENCES | F51: ='SEPT 30'!E22 -> 570.18209 | G51: PHONE LOAN | H51: 0
C52: MEDICAL POOLING | D52: 100 | G52: MEDICAL POOLING | H52: 100
C53: TAX | D53: ='SEPT 30'!L11 -> 0
A54: TOTAL COMPENSATION | B54: =SUM(B44:B53) -> 21692.5 | C54: TOTAL DEDUCTIONS | D54: =SUM(D44:D53) -> 5008.62 | E54: TOTAL COMPENSATION | F54: =SUM(F44:F48)-F51 -> 7962.234 | G54: TOTAL DEDUCTIONS | H54: =SUM(H44:H53) -> 950
A55: NET PAY | C55: =B54-D54 -> 16683.88 | E55: NET PAY | G55: =F54-H54 -> 7012.234
A57: Prepared By: | C57: Approved By: | E57: Prepared By: | G57: Approved By:
A59: DORABEL Y. GAID | C59: KATHERINE J. BACOSA | E59: DORABEL Y. GAID | G59: KATHERINE J. BACOSA
A60: Admin Assistant | C60: Finance Manager | E60: Admin Assistant | G60: Finance Manager
A68: NAME | B68: : ENGR. REYMOND CAYAPAS | E68: NAME | F68: : MATTHEW JOHN CLIFFORD D. PAREDES
A69: PAYROLL DATE | B69: =B7 -> : 30 JUNE 2026 | E69: PAYROLL DATE | F69: =B7 -> : 30 JUNE 2026
A70: DATE COVERED | B70: =B8 -> : 06/11/2026 - 06/25/2026 | E70: DATE COVERED | F70: =B8 -> : 06/11/2026 - 06/25/2026
A71: DEPARTMENT | B71: : Project Management & Operation | E71: DEPARTMENT | F71: : Project Management & Operation
A72: POSITION | B72: : Field Engineer | E72: POSITION | F72: : Draftsman
A73: COMPENSATION | C73: DEDUCTIONS | E73: COMPENSATION | G73: DEDUCTIONS
A74: BASIC | B74: ='SEPT 30'!D45 -> 10201.62 | C74: CASH ADVANCE | D74: 0 | E74: BASIC | F74: ='SEPT 30'!D20 -> 8661.8286 | G74: CASH ADVANCE | H74: 0
A75: DE MINIMIS BENEFITS | B75: 1500 | C75: RCBC | D75: 0 | E75: DE MINIMIS BENEFITS | F75: 0 | G75: RCBC | H75: 750
A76: OVERTIME | B76: ='SEPT 30'!G45 -> 0 | C76: SSS | D76: 1025 | E76: OVERTIME | F76: ='SEPT 30'!G20 -> 1237.4041 | G76: SSS | H76: 875
A77: HOLIDAY PAY | B77: ='SEPT 30'!H45 -> 0 | C77: SSS LOAN | D77: 1000 | E77: HOLIDAY PAY | F77: ='SEPT 30'!H20 -> 0 | G77: SSS LOAN | H77: 0
A78: INCENTIVES/REFUND | B78: 0 | C78: PHILHEALTH | D78: 0 | E78: INCENTIVES/REFUND | F78: 0 | G78: PHILHEALTH | H78: 0
C79: HDMF | D79: 0 | G79: HDMF | H79: 0
C80: HDMF LOAN | D80: 0 | G80: HDMF LOAN | H80: 0
A81: LATE & ABSENCES | B81: ='SEPT 30'!E45 -> 0 | C81: PHONE LOAN | D81: 0 | E81: LATE & ABSENCES | F81: ='SEPT 30'!E20 -> 46.746377 | G81: PHONE LOAN | H81: 0
C82: MEDICAL POOLING | D82: 100 | G82: MEDICAL POOLING | H82: 100
A84: TOTAL COMPENSATION | B84: =SUM(B74:B78)-B81 -> 11701.62 | C84: TOTAL DEDUCTIONS | D84: =SUM(D74:D83) -> 2125 | E84: TOTAL COMPENSATION | F84: =SUM(F74:F78)-F81 -> 9852.4863 | G84: TOTAL DEDUCTIONS | H84: =SUM(H74:H83) -> 1725
A85: NET PAY | C85: =B84-D84 -> 9576.62 | E85: NET PAY | G85: =F84-H84 -> 8127.4863
A87: Prepared By: | C87: Approved By: | E87: Prepared By: | G87: Approved By:
A89: DORABEL Y. GAID | C89: KATHERINE J. BACOSA | E89: DORABEL Y. GAID | G89: KATHERINE J. BACOSA
A90: Admin Assistant | C90: Finance Manager | E90: Admin Assistant | G90: Finance Manager
A100: NAME | B100: : REY MARK A. ALEJANDRINO | E100: NAME | F100: : ALLAN JAMES ABREA
A101: PAYROLL DATE | B101: =B7 -> : 30 JUNE 2026 | E101: PAYROLL DATE | F101: =B7 -> : 30 JUNE 2026
A102: DATE COVERED | B102: =B8 -> : 06/11/2026 - 06/25/2026 | E102: DATE COVERED | F102: =B8 -> : 06/11/2026 - 06/25/2026
A103: DEPARTMENT | B103: : Admin | E103: DEPARTMENT | F103: : Admin
A104: POSITION | B104: : GSS | E104: POSITION | F104: : Admin Staff-Utility
A105: COMPENSATION | C105: DEDUCTIONS | E105: COMPENSATION | G105: DEDUCTIONS
A106: BASIC | B106: ='SEPT 30'!D32 -> 8579.335 | C106: CASH ADVANCE | D106: 0 | E106: BASIC | F106: ='SEPT 30'!D34 -> 6000 | G106: CASH ADVANCE | H106: 500
A107: DE MINIMIS BENEFITS | B107: 1500 | C107: RCBC | D107: 0 | E107: DE MINIMIS BENEFITS | F107: 0 | G107: RCBC | H107: 0
A108: OVERTIME | B108: ='SEPT 30'!G32 -> 0 | C108: SSS | D108: 875 | E108: OVERTIME | F108: ='SEPT 30'!G34 -> 312.5 | G108: SSS | H108: 650
A109: HOLIDAY PAY | B109: ='SEPT 30'!H32 -> 0 | C109: SSS LOAN | D109: 750 | E109: HOLIDAY PAY | F109: ='SEPT 30'!H34 -> 0 | G109: SSS LOAN | H109: 0
A110: INCENTIVES/REFUND | B110: 0 | C110: PHILHEALTH | D110: 0 | E110: INCENTIVES/REFUND | F110: 0 | G110: PHILHEALTH | H110: 0
C111: HDMF | D111: 0 | G111: HDMF | H111: 0
C112: HDMF LOAN | D112: 0 | G112: HDMF LOAN | H112: 0
A113: LATE & ABSENCES | B113: ='SEPT 30'!E32 -> 0 | C113: PHONE LOAN | D113: 0 | E113: LATE & ABSENCES | F113: ='SEPT 30'!E34 -> 0 | G113: PHONE LOAN | H113: 0
C114: MEDICAL POOLING | D114: 100 | G114: MEDICAL POOLING | H114: 100
A116: TOTAL COMPENSATION | B116: =SUM(B106:B110)-B113 -> 10079.335 | C116: TOTAL DEDUCTIONS | D116: =SUM(D106:D115) -> 1725 | E116: TOTAL COMPENSATION | F116: =SUM(F106:F110)-F113 -> 6312.5 | G116: TOTAL DEDUCTIONS | H116: =SUM(H106:H115) -> 1250
A117: NET PAY | C117: =B116-D116 -> 8354.335 | E117: NET PAY | G117: =F116-H116 -> 5062.5
A119: Prepared By: | C119: Approved By: | E119: Prepared By: | G119: Approved By:
A121: DORABEL Y. GAID | C121: KATHERINE J. BACOSA | E121: DORABEL Y. GAID | G121: KATHERINE J. BACOSA
A122: Admin Assistant | C122: Finance Manager | E122: Admin Assistant | G122: Finance Manager
A130: NAME | B130: : REDEN D. DOBLEROS | E130: NAME | F130: : PIERCEVAL RUIZ
A131: PAYROLL DATE | B131: =B7 -> : 30 JUNE 2026 | E131: PAYROLL DATE | F131: =B7 -> : 30 JUNE 2026
A132: DATE COVERED | B132: =B8 -> : 06/11/2026 - 06/25/2026 | E132: DATE COVERED | F132: =B8 -> : 06/11/2026 - 06/25/2026
A133: DEPARTMENT | B133: : Finance | E133: DEPARTMENT | F133: :
A134: POSITION | B134: : Accounting Staff | E134: POSITION | F134: : Marketing Staff
A135: COMPENSATION | C135: DEDUCTIONS | E135: COMPENSATION | G135: DEDUCTIONS
A136: BASIC | B136: ='SEPT 30'!D42 -> 8661.8286 | C136: CASH ADVANCE | D136: 0 | E136: BASIC | F136: ='SEPT 30'!D27 -> 6562.5 | G136: CASH ADVANCE | H136: 0
A137: DE MINIMIS BENEFITS | B137: 0 | C137: RCBC | D137: 2000 | E137: DE MINIMIS BENEFITS | F137: 0 | G137: RCBC | H137: 0
A138: OVERTIME | B138: ='SEPT 30'!G42 -> 412.46803 | C138: SSS | D138: 875 | E138: OVERTIME | F138: ='SEPT 30'!G27 -> 1015.625 | G138: SSS | H138: 650
A139: HOLIDAY PAY | B139: ='SEPT 30'!H42 -> 0 | C139: SSS LOAN | D139: 500 | E139: HOLIDAY PAY | F139: ='SEPT 30'!H27 -> 0 | G139: SSS LOAN | H139: 0
A140: INCENTIVES/REFUND | B140: 0 | C140: PHILHEALTH | D140: 0 | E140: INCENTIVES/REFUND | F140: 0 | G140: PHILHEALTH | H140: 0
C141: HDMF | D141: 0 | G141: HDMF | H141: 0
C142: HDMF LOAN | D142: 500 | G142: HDMF LOAN | H142: 0
A143: LATE & ABSENCES | B143: ='SEPT 30'!E42 -> 1653.9968 | C143: PHONE LOAN | D143: 0 | E143: LATE & ABSENCES | F143: ='SEPT 30'!E27 -> 3.125 | G143: PHONE LOAN | H143: 0
C144: MEDICAL POOLING | D144: 100 | G144: MEDICAL POOLING | H144: 100
H145: 0
A146: TOTAL COMPENSATION | B146: =SUM(B136:B140)-B143 -> 7420.2998 | C146: TOTAL DEDUCTIONS | D146: =SUM(D136:D145) -> 3975 | E146: TOTAL COMPENSATION | F146: =SUM(F136:F140)-F143 -> 7575 | G146: TOTAL DEDUCTIONS | H146: =SUM(H136:H145) -> 750
A147: NET PAY | C147: =B146-D146 -> 3445.2998 | E147: NET PAY | G147: =F146-H146 -> 6825
...

Sheet PS(F)
A6: NAME | B6: : REY JOHN G. MITCHELL | E6: NAME | F6: : JORGE A. ALDAMAR JR.
A7: PAYROLL DATE | B7: : 30 JUNE 2026 | E7: PAYROLL DATE | F7: =B7 -> : 30 JUNE 2026
A8: DATE COVERED | B8: : 06/11/2026 - 06/25/2026 | E8: DATE COVERED | F8: =B8 -> : 06/11/2026 - 06/25/2026
A9: DEPARTMENT | B9: : Project Management & Operation | E9: DEPARTMENT | F9: : Project Management & Operation
A10: POSITION | B10: : Project Area Supervisor | E10: POSITION | F10: : Project Area Supervisor
A11: COMPENSATION | C11: DEDUCTIONS | E11: COMPENSATION | G11: DEDUCTIONS
A12: BASIC | B12: 9500 | C12: CASH ADVANCE | D12: 1250 | E12: BASIC | F12: 9000 | G12: CASH ADVANCE | H12: 0
A13: DE MINIMIS BENEFITS | B13: 3000 | C13: RCBC | D13: 0 | E13: DE MINIMIS BENEFITS | F13: 3000 | G13: RCBC | H13: 0
A14: OVERTIME | B14: 0 | C14: SSS | D14: 900 | E14: OVERTIME | F14: 0 | G14: SSS | H14: 900
A15: HOLIDAY PAY | B15: 0 | C15: SSS LOAN | D15: 0 | E15: HOLIDAY PAY | F15: 0 | G15: SSS LOAN | H15: 0
A16: INCENTIVES/REFUND | B16: 0 | C16: PHILHEALTH | D16: 0 | E16: INCENTIVES/REFUND | F16: 0 | G16: PHILHEALTH | H16: 0
C17: HDMF | D17: 0 | G17: HDMF | H17: 0
C18: HDMF LOAN | D18: 0 | G18: HDMF LOAN | H18: 0
A19: LATE AND ABSENCES | B19: 0 | C19: PHONE LOAN | D19: 0 | G19: PHONE LOAN | H19: 0
C20: MEDICAL POOLING | D20: 100 | G20: MEDICAL POOLING | H20: 100
A22: TOTAL COMPENSATION | B22: =SUM(B12:B21) -> 12500 | C22: TOTAL DEDUCTIONS | D22: =SUM(D12:D21) -> 2250 | E22: TOTAL COMPENSATION | F22: =SUM(F12:F21) -> 12000 | G22: TOTAL DEDUCTIONS | H22: =SUM(H12:H21) -> 1000
A23: NET PAY | C23: =B22-D22 -> 10250 | E23: NET PAY | G23: =F22-H22 -> 11000
A25: Prepared By: | C25: Approved By: | E25: Prepared By: | G25: Approved By:
A27: DORABEL Y. GAID | C27: KATHERINE J. BACOSA | E27: DORABEL Y. GAID | G27: KATHERINE J. BACOSA
A28: Admin Assistant | C28: Finance Manager | E28: Admin Assistant | G28: Finance Manager
A38: NAME | B38: : MOSES O. MORADOS | E38: NAME | F38: : OSCAR D. ABIS
A39: PAYROLL DATE | B39: =B7 -> : 30 JUNE 2026 | E39: PAYROLL DATE | F39: =B7 -> : 30 JUNE 2026
A40: DATE COVERED | B40: =B8 -> : 06/11/2026 - 06/25/2026 | E40: DATE COVERED | F40: =B8 -> : 06/11/2026 - 06/25/2026
A41: DEPARTMENT | B41: : Project Management & Operation | E41: DEPARTMENT | F41: : Project Management & Operation
A42: POSITION | B42: : Field Staff | E42: POSITION | F42: : Field Staff
A43: COMPENSATION | C43: DEDUCTIONS | E43: COMPENSATION | G43: DEDUCTIONS
A44: BASIC | B44: 7000 | C44: CASH ADVANCE | D44: 0 | E44: BASIC | F44: 7000 | G44: CASH ADVANCE | H44: 0
A45: DE MINIMIS BENEFITS | B45: 2500 | C45: RCBC | D45: 1097 | E45: DE MINIMIS BENEFITS | F45: 2500 | G45: RCBC | H45: 0
A46: OVERTIME | B46: 0 | C46: SSS | D46: 600 | E46: OVERTIME | F46: 0 | G46: SSS | H46: 700
A47: HOLIDAY PAY | B47: 0 | C47: SSS LOAN | D47: 0 | E47: HOLIDAY PAY | F47: 0 | G47: SSS LOAN | H47: 0
A48: INCENTIVES/REFUND | B48: 0 | C48: PHILHEALTH | D48: 0 | E48: INCENTIVES/REFUND | F48: 0 | G48: PHILHEALTH | H48: 0
C49: HDMF | D49: 0 | G49: HDMF | H49: 0
C50: HDMF LOAN | D50: 0 | G50: HDMF LOAN | H50: 0
C51: PHONE LOAN | D51: 0 | G51: PHONE LOAN | H51: 0
C52: MEDICAL POOLING | D52: 100 | G52: MEDICAL POOLING | H52: 100
D53: 0 | H53: 0
A54: TOTAL COMPENSATION | B54: =SUM(B44:B53) -> 9500 | C54: TOTAL DEDUCTIONS | D54: =SUM(D44:D53) -> 1797 | E54: TOTAL COMPENSATION | F54: =SUM(F44:F53) -> 9500 | G54: TOTAL DEDUCTIONS | H54: =SUM(H44:H53) -> 800
A55: NET PAY | C55: =B54-D54 -> 7703 | E55: NET PAY | G55: =F54-H54 -> 8700
A57: Prepared By: | C57: Approved By: | E57: Prepared By: | G57: Approved By:
A59: DORABEL Y. GAID | C59: KATHERINE J. BACOSA | E59: DORABEL Y. GAID | G59: KATHERINE J. BACOSA
A60: Admin Assistant | C60: Finance Manager | E60: Admin Assistant | G60: Finance Manager
A68: NAME | B68: : NOIBO A. LAGROSA | E68: NAME | F68: : NORMAN G. MACATANGAY
A69: PAYROLL DATE | B69: =B7 -> : 30 JUNE 2026 | E69: PAYROLL DATE | F69: =B7 -> : 30 JUNE 2026
A70: DATE COVERED | B70: =B8 -> : 06/11/2026 - 06/25/2026 | E70: DATE COVERED | F70: =B8 -> : 06/11/2026 - 06/25/2026
A71: DEPARTMENT | B71: : Project Management & Operation | E71: DEPARTMENT | F71: : Project Management & Operation
A72: POSITION | B72: : Field Staff | E72: POSITION | F72: : Field Staff
A73: COMPENSATION | C73: DEDUCTIONS | E73: COMPENSATION | G73: DEDUCTIONS
A74: BASIC | B74: 7000 | C74: CASH ADVANCE | D74: 0 | E74: BASIC | F74: 7000 | G74: CASH ADVANCE | H74: 0
A75: DE MINIMIS BENEFITS | B75: 2500 | C75: RCBC | D75: 0 | E75: DE MINIMIS BENEFITS | F75: 2500 | G75: RCBC | H75: 0
A76: OVERTIME | B76: 0 | C76: SSS | D76: 700 | E76: OVERTIME | F76: 0 | G76: SSS | H76: 600
A77: HOLIDAY PAY | B77: 0 | C77: SSS LOAN | D77: 0 | E77: HOLIDAY PAY | F77: 0 | G77: SSS LOAN | H77: 0
A78: INCENTIVES/REFUND | B78: 0 | C78: PHILHEALTH | D78: 0 | E78: INCENTIVES/REFUND | F78: 0 | G78: PHILHEALTH | H78: 0
C79: HDMF | D79: 0 | G79: HDMF | H79: 0
C80: HDMF LOAN | D80: 500 | G80: HDMF LOAN | H80: 0
C81: PHONE LOAN | D81: 0 | G81: PHONE LOAN | H81: 0
C82: MEDICAL POOLING | D82: 100 | G82: MEDICAL POOLING | H82: 100
H83: 0
A84: TOTAL COMPENSATION | B84: =SUM(B74:B83) -> 9500 | C84: TOTAL DEDUCTIONS | D84: =SUM(D74:D83) -> 1300 | E84: TOTAL COMPENSATION | F84: =SUM(F74:F83) -> 9500 | G84: TOTAL DEDUCTIONS | H84: =SUM(H74:H83) -> 700
A85: NET PAY | C85: =B84-D84 -> 8200 | E85: NET PAY | G85: =F84-H84 -> 8800
A87: Prepared By: | C87: Approved By: | E87: Prepared By: | G87: Approved By:
A89: DORABEL Y. GAID | C89: KATHERINE J. BACOSA | E89: DORABEL Y. GAID | G89: KATHERINE J. BACOSA
A90: Admin Assistant | C90: Finance Manager | E90: Admin Assistant | G90: Finance Manager
A100: NAME | B100: : RONALD BECARO | E100: NAME | F100: : JAY AR RHYAN LORENZO
A101: PAYROLL DATE | B101: =B7 -> : 30 JUNE 2026 | E101: PAYROLL DATE | F101: =B7 -> : 30 JUNE 2026
A102: DATE COVERED | B102: =B8 -> : 06/11/2026 - 06/25/2026 | E102: DATE COVERED | F102: =B8 -> : 06/11/2026 - 06/25/2026
A103: DEPARTMENT | B103: : Project Management & Operation | E103: DEPARTMENT | F103: : Project Management & Operation
A104: POSITION | B104: : Project Area Supervisor | E104: POSITION | F104: : Project Area Supervisor
A105: COMPENSATION | C105: DEDUCTIONS | E105: COMPENSATION | G105: DEDUCTIONS
A106: BASIC | B106: 8000 | C106: CASH ADVANCE | D106: 0 | E106: BASIC | F106: 8500 | G106: CASH ADVANCE | H106: 0
A107: DE MINIMIS BENEFITS | B107: 3000 | C107: RCBC | D107: 0 | E107: DE MINIMIS BENEFITS | F107: 3000 | G107: RCBC | H107: 0
A108: OVERTIME | B108: 0 | C108: SSS | D108: 800 | E108: OVERTIME | F108: 0 | G108: SSS | H108: 850
A109: HOLIDAY PAY | B109: 0 | C109: SSS LOAN | D109: 0 | E109: HOLIDAY PAY | F109: 0 | G109: SSS LOAN | H109: 0
A110: INCENTIVES/REFUND | B110: 0 | C110: PHILHEALTH | D110: 0 | E110: INCENTIVES/REFUND | F110: 0 | G110: PHILHEALTH | H110: 0
C111: HDMF | D111: 0 | G111: HDMF | H111: 0
C112: HDMF LOAN | D112: 0 | G112: HDMF LOAN | H112: 0
C113: PHONE LOAN | D113: 0 | E113: LATE AND ABSENCES | F113: 0 | G113: PHONE LOAN | H113: 0
C114: MEDICAL POOLING | D114: 100 | G114: MEDICAL POOLING | H114: 100
D115: 0
A116: TOTAL COMPENSATION | B116: =SUM(B106:B115) -> 11000 | C116: TOTAL DEDUCTIONS | D116: =SUM(D106:D115) -> 900 | E116: TOTAL COMPENSATION | F116: =SUM(F106:F115) -> 11500 | G116: TOTAL DEDUCTIONS | H116: =SUM(H106:H115) -> 950
A117: NET PAY | C117: =B116-D116 -> 10100 | E117: NET PAY | G117: =F116-H116 -> 10550
A119: Prepared By: | C119: Approved By: | E119: Prepared By: | G119: Approved By:
A121: DORABEL Y. GAID | C121: KATHERINE J. BACOSA | E121: DORABEL Y. GAID | G121: KATHERINE J. BACOSA
A122: Admin Assistant | C122: Finance Manager | E122: Admin Assistant | G122: Finance Manager
A130: NAME | B130: : DONDON ELEVERA | E130: NAME | F130: : MARK JOHN CABASAL
A131: PAYROLL DATE | B131: =B7 -> : 30 JUNE 2026 | E131: PAYROLL DATE | F131: =B69 -> : 30 JUNE 2026
A132: DATE COVERED | B132: =B8 -> : 06/11/2026 - 06/25/2026 | E132: DATE COVERED | F132: =B70 -> : 06/11/2026 - 06/25/2026
A133: DEPARTMENT | B133: : Project Management & Operation | E133: DEPARTMENT | F133: : Project Management & Operation
A134: POSITION | B134: : Field Staff | E134: POSITION | F134: : Field Staff
A135: COMPENSATION | C135: DEDUCTIONS | E135: COMPENSATION | G135: DEDUCTIONS
A136: BASIC | B136: 7000 | C136: CASH ADVANCE | D136: 0 | E136: BASIC | F136: 6000 | G136: CASH ADVANCE | H136: 0
A137: DE MINIMIS BENEFITS | B137: 2500 | C137: RCBC | D137: 0 | E137: DE MINIMIS BENEFITS | F137: 2500 | G137: RCBC | H137: 0
A138: OVERTIME | B138: 0 | C138: SSS | D138: 600 | E138: OVERTIME | F138: 0 | G138: SSS | H138: 600
A139: HOLIDAY PAY | B139: 0 | C139: SSS LOAN | D139: 0 | E139: HOLIDAY PAY | F139: 0 | G139: SSS LOAN | H139: 0
A140: INCENTIVES/REFUND | B140: 0 | C140: PHILHEALTH | D140: 0 | E140: INCENTIVES/REFUND | F140: 0 | G140: PHILHEALTH | H140: 0
C141: HDMF | D141: 0 | G141: HDMF | H141: 0
C142: HDMF LOAN | D142: 0 | G142: HDMF LOAN | H142: 0
C143: PHONE LOAN | D143: 0 | G143: PHONE LOAN | H143: 0
C144: MEDICAL POOLING | D144: 100 | G144: MEDICAL POOLING | H144: 100
D145: 0 | H145: 0
A146: TOTAL COMPENSATION | B146: =SUM(B136:B145) -> 9500 | C146: TOTAL DEDUCTIONS | D146: =SUM(D136:D145) -> 700 | E146: TOTAL COMPENSATION | F146: =SUM(F136:F145) -> 8500 | G146: TOTAL DEDUCTIONS | H146: =SUM(H136:H145) -> 700
...

Sheet PAALAN
C7: Employee Name: | G7: ENGELBERT PAALAN | J7: Period: | L7: September 11-25, 2026
C8: Position: | G8: Laboratory Head | J8: Payroll Date: | L8: 9/31/2026
B10: Year | C10: Month | D10: Date | G10: Weekend
B11: 2026 | C11: September | D11: 11 | G11: Sun Only
B13: Start Time | C13: Regular Hours | D13: Regular Pay (hourly) | G13: Overtime Pay (hourly) | H13: Total # of Hours per Cut off
B14: 0.33333333 | C14: 10 | D14: =(14000/26)/8 -> 67.307692 | G14: =(D14*25%)+D14 -> 84.134615 | H14: 104
C16: Day | D16: Date | E16: In Time | F16: Grace period | G16: In Time | H16: Out Time | I16: Break Hrs | J16: Regular Hrs | K16: OT Hours | L16: Late | M16: Late Amount | N16: Total Pay
B17: 1 | C17: =DATE($B$11,MATCH($C$11,Data!$B$2:$B$13,0),PAALAN!$D$11) -> 46276 | D17: =DATE($B$11,MATCH($C$11,Data!$B$2:$B$13,0),PAALAN!$D$11) -> 46276 | E17: 0.33333333 | F17: 0 | G17: =E17-F17 -> 0.33333333 | H17: 0.75 | I17: 1 | J17: =IFERROR(IF(AND(G17<>"",H17<>""),IF(G17>$B$14+TIME($C$14,($C$14-INT($C$14))*60,0),0,IF(H17>$B$14+TIME($C$14,($C$14-INT($C$14))*60,0),MIN(TIME($C$14,($C$14-INT($C$14))*60,0),($B$14+TIME($C$14,($C$14-INT($C$14))*60,0)-G17)),MIN(IF((H17-$B$14)<0,0,(H17-$B$14)),(H17-G17))))*24,"")-I17,"") -> 9 | K17: 0 | L17: =E17-B14 -> 0 | M17: =(D14/60)*0 -> 0 | N17: =IFERROR(J17*IF(AND(ISNUMBER(SEARCH(TEXT(C17,"ddd"),$G$11)),Data!$F$2),$G$14,$D$14)+K17*$G$14,"") -> 605.76923 | O17: =M17+N17 -> 605.76923
B18: 2 | C18: =C17+1 -> 46277 | D18: =D17+1 -> 46277 | E18: 0.375 | F18: 0 | G18: =E18-F18 -> 0.375 | H18: 0.5 | I18: 0 | J18: =IFERROR(IF(AND(G18<>"",H18<>""),IF(G18>$B$14+TIME($C$14,($C$14-INT($C$14))*60,0),0,IF(H18>$B$14+TIME($C$14,($C$14-INT($C$14))*60,0),MIN(TIME($C$14,($C$14-INT($C$14))*60,0),($B$14+TIME($C$14,($C$14-INT($C$14))*60,0)-G18)),MIN(IF((H18-$B$14)<0,0,(H18-$B$14)),(H18-G18))))*24,"")-I18,"") -> 3 | K18: 0 | L18: =E18-B14 -> 0.041666667 | M18: =(D14/60)*0 -> 0 | N18: =IFERROR(J18*IF(AND(ISNUMBER(SEARCH(TEXT(C18,"ddd"),$G$11)),Data!$F$2),$G$14,$D$14)+K18*$G$14,"") -> 201.92308 | O18: =M18+N18 -> 201.92308
C19: =C18+1 -> 46278 | D19: =D18+1 -> 46278 | E19: 0 | F19: 0 | G19: =E19-F19 -> 0 | H19: 0 | I19: 0 | J19: =IFERROR(IF(AND(G19<>"",H19<>""),IF(G19>$B$14+TIME($C$14,($C$14-INT($C$14))*60,0),0,IF(H19>$B$14+TIME($C$14,($C$14-INT($C$14))*60,0),MIN(TIME($C$14,($C$14-INT($C$14))*60,0),($B$14+TIME($C$14,($C$14-INT($C$14))*60,0)-G19)),MIN(IF((H19-$B$14)<0,0,(H19-$B$14)),(H19-G19))))*24,"")-I19,"") -> 0 | K19: 0 | L19: 0 | M19: =(D14/60)*0 -> 0 | N19: =IFERROR(J19*IF(AND(ISNUMBER(SEARCH(TEXT(C19,"ddd"),$G$11)),Data!$F$2),$G$14,$D$14)+K19*$G$14,"") -> 0
B20: 3 | C20: =C19+1 -> 46279 | D20: =D19+1 -> 46279 | E20: 0.33333333 | F20: 0 | G20: =E20-F20 -> 0.33333333 | H20: 0.75 | I20: 1 | J20: =IFERROR(IF(AND(G20<>"",H20<>""),IF(G20>$B$14+TIME($C$14,($C$14-INT($C$14))*60,0),0,IF(H20>$B$14+TIME($C$14,($C$14-INT($C$14))*60,0),MIN(TIME($C$14,($C$14-INT($C$14))*60,0),($B$14+TIME($C$14,($C$14-INT($C$14))*60,0)-G20)),MIN(IF((H20-$B$14)<0,0,(H20-$B$14)),(H20-G20))))*24,"")-I20,"") -> 9 | K20: 0 | L20: =E20-B14 -> 0 | M20: =(D14/60)*0 -> 0 | N20: =IFERROR(J20*IF(AND(ISNUMBER(SEARCH(TEXT(C20,"ddd"),$G$11)),Data!$F$2),$G$14,$D$14)+K20*$G$14,"") -> 605.76923 | O20: 615.36
B21: 4 | C21: =C20+1 -> 46280 | D21: =D20+1 -> 46280 | E21: 0.33333333 | F21: 0 | G21: =E21-F21 -> 0.33333333 | H21: 0.75 | I21: 1 | J21: =IFERROR(IF(AND(G21<>"",H21<>""),IF(G21>$B$14+TIME($C$14,($C$14-INT($C$14))*60,0),0,IF(H21>$B$14+TIME($C$14,($C$14-INT($C$14))*60,0),MIN(TIME($C$14,($C$14-INT($C$14))*60,0),($B$14+TIME($C$14,($C$14-INT($C$14))*60,0)-G21)),MIN(IF((H21-$B$14)<0,0,(H21-$B$14)),(H21-G21))))*24,"")-I21,"") -> 9 | K21: 0 | L21: =G21-B14 -> 0 | M21: =(D14/60)*0 -> 0 | N21: =IFERROR(J21*IF(AND(ISNUMBER(SEARCH(TEXT(C21,"ddd"),$G$11)),Data!$F$2),$G$14,$D$14)+K21*$G$14,"") -> 605.76923 | O21: =M21+N21 -> 605.76923
B22: 5 | C22: =C21+1 -> 46281 | D22: =D21+1 -> 46281 | E22: 0.3375 | F22: 0 | G22: =E22-F22 -> 0.3375 | H22: 0.71388889 | I22: 1 | J22: =IFERROR(IF(AND(G22<>"",H22<>""),IF(G22>$B$14+TIME($C$14,($C$14-INT($C$14))*60,0),0,IF(H22>$B$14+TIME($C$14,($C$14-INT($C$14))*60,0),MIN(TIME($C$14,($C$14-INT($C$14))*60,0),($B$14+TIME($C$14,($C$14-INT($C$14))*60,0)-G22)),MIN(IF((H22-$B$14)<0,0,(H22-$B$14)),(H22-G22))))*24,"")-I22,"") -> 8.0333333 | K22: 0 | L22: =E22-B14 -> 0.0041666667 | M22: =(D14/60)*0 -> 0 | N22: =IFERROR(J22*IF(AND(ISNUMBER(SEARCH(TEXT(C22,"ddd"),$G$11)),Data!$F$2),$G$14,$D$14)+K22*$G$14,"") -> 540.70513 | O22: =M22+N22 -> 540.70513
B23: 6 | C23: =C22+1 -> 46282 | D23: =D22+1 -> 46282 | E23: 0.33333333 | F23: 0 | G23: =E23-F23 -> 0.33333333 | H23: 0.67777778 | I23: 1 | J23: =IFERROR(IF(AND(G23<>"",H23<>""),IF(G23>$B$14+TIME($C$14,($C$14-INT($C$14))*60,0),0,IF(H23>$B$14+TIME($C$14,($C$14-INT($C$14))*60,0),MIN(TIME($C$14,($C$14-INT($C$14))*60,0),($B$14+TIME($C$14,($C$14-INT($C$14))*60,0)-G23)),MIN(IF((H23-$B$14)<0,0,(H23-$B$14)),(H23-G23))))*24,"")-I23,"") -> 7.2666667 | K23: 0 | L23: =G23-B14 -> 0 | M23: =(D14/60)*0 -> 0 | N23: =IFERROR(J23*IF(AND(ISNUMBER(SEARCH(TEXT(C23,"ddd"),$G$11)),Data!$F$2),$G$14,$D$14)+K23*$G$14,"") -> 489.10256 | O23: =M23+N23 -> 489.10256
B24: 7 | C24: =C23+1 -> 46283 | D24: =D23+1 -> 46283 | E24: 0.33333333 | F24: 0 | G24: =E24-F24 -> 0.33333333 | H24: 0.75 | I24: 1 | J24: =IFERROR(IF(AND(G24<>"",H24<>""),IF(G24>$B$14+TIME($C$14,($C$14-INT($C$14))*60,0),0,IF(H24>$B$14+TIME($C$14,($C$14-INT($C$14))*60,0),MIN(TIME($C$14,($C$14-INT($C$14))*60,0),($B$14+TIME($C$14,($C$14-INT($C$14))*60,0)-G24)),MIN(IF((H24-$B$14)<0,0,(H24-$B$14)),(H24-G24))))*24,"")-I24,"") -> 9 | K24: 0 | L24: =E24-B14 -> 0 | M24: =(D14/60)*0 -> 0 | N24: =IFERROR(J24*IF(AND(ISNUMBER(SEARCH(TEXT(C24,"ddd"),$G$11)),Data!$F$2),$G$14,$D$14)+K24*$G$14,"") -> 605.76923 | O24: =M24+N24 -> 605.76923
B25: 8 | C25: =C24+1 -> 46284 | D25: =D24+1 -> 46284 | E25: 0.375 | F25: 0 | G25: =E25-F25 -> 0.375 | H25: 0.5 | I25: 0 | J25: =IFERROR(IF(AND(G25<>"",H25<>""),IF(G25>$B$14+TIME($C$14,($C$14-INT($C$14))*60,0),0,IF(H25>$B$14+TIME($C$14,($C$14-INT($C$14))*60,0),MIN(TIME($C$14,($C$14-INT($C$14))*60,0),($B$14+TIME($C$14,($C$14-INT($C$14))*60,0)-G25)),MIN(IF((H25-$B$14)<0,0,(H25-$B$14)),(H25-G25))))*24,"")-I25,"") -> 3 | K25: 0 | L25: =E25-B14 -> 0.041666667 | M25: =(D14/60)*0 -> 0 | N25: 0 | O25: =M25+N25 -> 0
C26: =C25+1 -> 46285 | D26: =D25+1 -> 46285 | E26: 0 | F26: 0 | G26: =E26-F26 -> 0 | H26: 0 | I26: 0 | J26: =IFERROR(IF(AND(G26<>"",H26<>""),IF(G26>$B$14+TIME($C$14,($C$14-INT($C$14))*60,0),0,IF(H26>$B$14+TIME($C$14,($C$14-INT($C$14))*60,0),MIN(TIME($C$14,($C$14-INT($C$14))*60,0),($B$14+TIME($C$14,($C$14-INT($C$14))*60,0)-G26)),MIN(IF((H26-$B$14)<0,0,(H26-$B$14)),(H26-G26))))*24,"")-I26,"") -> 0 | K26: 0 | L26: 0 | M26: =(D14/60)*0 -> 0 | N26: =IFERROR(J26*IF(AND(ISNUMBER(SEARCH(TEXT(C26,"ddd"),$G$11)),Data!$F$2),$G$14,$D$14)+K26*$G$14,"") -> 0 | O26: =M26+N26 -> 0
B27: 9 | C27: =C26+1 -> 46286 | D27: =D26+1 -> 46286 | E27: 0.33333333 | F27: 0 | G27: =E27-F27 -> 0.33333333 | H27: 0.75 | I27: 1 | J27: =IFERROR(IF(AND(G27<>"",H27<>""),IF(G27>$B$14+TIME($C$14,($C$14-INT($C$14))*60,0),0,IF(H27>$B$14+TIME($C$14,($C$14-INT($C$14))*60,0),MIN(TIME($C$14,($C$14-INT($C$14))*60,0),($B$14+TIME($C$14,($C$14-INT($C$14))*60,0)-G27)),MIN(IF((H27-$B$14)<0,0,(H27-$B$14)),(H27-G27))))*24,"")-I27,"") -> 9 | K27: =IF(AND(G27<>"",H27<>""),((IF(G27<$B$14,MIN($B$14-G27,H27-G27),0)+IF(H27>$B$14+TIME($C$14,($C$14-INT($C$14))*60,0),MIN((H27-$B$14-TIME($C$14,($C$14-INT($C$14))*60,0)),(H27-G27)),0))*24),"") -> 0 | L27: 0 | M27: =(D14/60)*0 -> 0 | N27: =IFERROR(J27*IF(AND(ISNUMBER(SEARCH(TEXT(C27,"ddd"),$G$11)),Data!$F$2),$G$14,$D$14)+K27*$G$14,"") -> 605.76923 | O27: =M27+N27 -> 605.76923
B28: 10 | C28: =C27+1 -> 46287 | D28: =D27+1 -> 46287 | E28: 0.33333333 | F28: 0 | G28: =E28-F28 -> 0.33333333 | H28: 0.75 | I28: 1 | J28: =IFERROR(IF(AND(G28<>"",H28<>""),IF(G28>$B$14+TIME($C$14,($C$14-INT($C$14))*60,0),0,IF(H28>$B$14+TIME($C$14,($C$14-INT($C$14))*60,0),MIN(TIME($C$14,($C$14-INT($C$14))*60,0),($B$14+TIME($C$14,($C$14-INT($C$14))*60,0)-G28)),MIN(IF((H28-$B$14)<0,0,(H28-$B$14)),(H28-G28))))*24,"")-I28,"") -> 9 | K28: 0 | L28: 0 | M28: =(D14/60)*0 -> 0 | N28: =IFERROR(J28*IF(AND(ISNUMBER(SEARCH(TEXT(C28,"ddd"),$G$11)),Data!$F$2),$G$14,$D$14)+K28*$G$14,"") -> 605.76923 | O28: =M28+N28 -> 605.76923
B29: 11 | C29: =C28+1 -> 46288 | D29: =D28+1 -> 46288 | E29: 0.33333333 | F29: 0 | G29: =E29-F29 -> 0.33333333 | H29: 0.73888889 | I29: 1 | J29: =IFERROR(IF(AND(G29<>"",H29<>""),IF(G29>$B$14+TIME($C$14,($C$14-INT($C$14))*60,0),0,IF(H29>$B$14+TIME($C$14,($C$14-INT($C$14))*60,0),MIN(TIME($C$14,($C$14-INT($C$14))*60,0),($B$14+TIME($C$14,($C$14-INT($C$14))*60,0)-G29)),MIN(IF((H29-$B$14)<0,0,(H29-$B$14)),(H29-G29))))*24,"")-I29,"") -> 8.7333333 | K29: 0 | L29: 0 | M29: 0 | N29: =IFERROR(J29*IF(AND(ISNUMBER(SEARCH(TEXT(C29,"ddd"),$G$11)),Data!$F$2),$G$14,$D$14)+K29*$G$14,"") -> 587.82051 | O29: =M29+N29 -> 587.82051
B30: 12 | C30: =C29+1 -> 46289 | D30: =D29+1 -> 46289 | E30: 0.33333333 | F30: 0 | G30: =E30-F30 -> 0.33333333 | H30: 0.75 | I30: 1 | J30: =IFERROR(IF(AND(G30<>"",H30<>""),IF(G30>$B$14+TIME($C$14,($C$14-INT($C$14))*60,0),0,IF(H30>$B$14+TIME($C$14,($C$14-INT($C$14))*60,0),MIN(TIME($C$14,($C$14-INT($C$14))*60,0),($B$14+TIME($C$14,($C$14-INT($C$14))*60,0)-G30)),MIN(IF((H30-$B$14)<0,0,(H30-$B$14)),(H30-G30))))*24,"")-I30,"") -> 9 | K30: 0 | L30: =G30-B14 -> 0 | M30: =(D14/60)*0 -> 0 | N30: =IFERROR(J30*IF(AND(ISNUMBER(SEARCH(TEXT(C30,"ddd"),$G$11)),Data!$F$2),$G$14,$D$14)+K30*$G$14,"") -> 605.76923 | O30: =M30+N30 -> 605.76923
B31: 13 | C31: =C30+1 -> 46290 | D31: =D30+1 -> 46290 | E31: 0.33333333 | F31: 0 | G31: =E31-F31 -> 0.33333333 | H31: 0.75 | I31: 1 | J31: =IFERROR(IF(AND(G31<>"",H31<>""),IF(G31>$B$14+TIME($C$14,($C$14-INT($C$14))*60,0),0,IF(H31>$B$14+TIME($C$14,($C$14-INT($C$14))*60,0),MIN(TIME($C$14,($C$14-INT($C$14))*60,0),($B$14+TIME($C$14,($C$14-INT($C$14))*60,0)-G31)),MIN(IF((H31-$B$14)<0,0,(H31-$B$14)),(H31-G31))))*24,"")-I31,"") -> 9 | K31: 0 | L31: =E31-B14 -> 0 | M31: =(D15/60)*0 -> 0 | N31: =IFERROR(J31*IF(AND(ISNUMBER(SEARCH(TEXT(C31,"ddd"),$G$11)),Data!$F$2),$G$14,$D$14)+K31*$G$14,"") -> 605.76923 | O31: =M31+N31 -> 605.76923
G32: Total Hours | I32: =SUM(I17:I31) -> 11 | J32: =SUM(J17:J31) -> 102.03333 | K32: =SUM(K17:K31) -> 0 | L32: =SUM(L17:L31) -> 0.0875 | M32: =SUM(M17:M31) -> 0
G33: Basic Pay | L33: =(D14/60)*0 -> 0 | N33: =(H14*D14)-N37 -> 7000 | O33: =SUM(O17:O31) -> 6675.2959 | P33: =N33-O33 -> 324.7041
G34: Absences, Late & Undertime | J34: =H14-J32 -> 1.9666667 | N34: =M32 -> 0 | O34: =N37 -> 0
G35: Total Basic Pay | N35: =N33-N34 -> 7000 | O35: =M32 -> 0
G36: Overtime Pay | N36: =D14*K32 -> 0 | O36: =O33-O34-O35 -> 6675.2959
G37: Holiday Pay | N37: 0 | O37: =N37 -> 0
G38: Gross Pay | N38: =N35+N36+N37 -> 7000 | O38: =O36+O37 -> 6675.2959
B41: HOLIDAY PAY
D43: Regular Holiday
D44: Year | G44: Month | H44: Date | I44: Weekend
D45: 2026 | G45: June | H45: 12 | I45: Sat & Sun
D47: Start Time | G47: Regular Hours | H47: Regular Pay (hourly) | I47: Overtime Pay (hourly)
D48: 0.33333333 | G48: 10 | H48: =D14 -> 67.307692 | I48: =(H48*30%)+H48 -> 87.5
C50: Day | D50: Date | G50: In Time | H50: Out Time | I50: Break Hrs | J50: Regular Hrs | K50: OT Hours | N50: Total Pay
C51: Fri | D51: =DATE($B$11,MATCH($G$45,Data!$B$2:$B$13,0),PAALAN!$H$45) -> 46185 | G51: 0.33333333 | H51: 0.75 | I51: 1 | J51: =IFERROR(IF(AND(G51<>"",H51<>""),IF(G51>$B$14+TIME($C$14,($C$14-INT($C$14))*60,0),0,IF(H51>$B$14+TIME($C$14,($C$14-INT($C$14))*60,0),MIN(TIME($C$14,($C$14-INT($C$14))*60,0),($B$14+TIME($C$14,($C$14-INT($C$14))*60,0)-G51)),MIN(IF((H51-$B$14)<0,0,(H51-$B$14)),(H51-G51))))*24,"")-I51,"") -> 9 | K51: =IF(AND(G51<>"",H51<>""),((IF(G51<$D$48,MIN($D$48-G51,H51-G51),0)+IF(H51>$D$48+TIME($G$48,($G$48-INT($G$48))*60,0),MIN((H51-$D$48-TIME($G$48,($G$48-INT($G$48))*60,0)),(H51-G51)),0))*24),"") -> 0 | N51: =J51*H48 -> 605.76923
C52: Tue | D52: 23 | G52: 0 | H52: 0 | I52: 0 | J52: =IFERROR(IF(AND(G52<>"",H52<>""),IF(G52>$B$14+TIME($C$14,($C$14-INT($C$14))*60,0),0,IF(H52>$B$14+TIME($C$14,($C$14-INT($C$14))*60,0),MIN(TIME($C$14,($C$14-INT($C$14))*60,0),($B$14+TIME($C$14,($C$14-INT($C$14))*60,0)-G52)),MIN(IF((H52-$B$14)<0,0,(H52-$B$14)),(H52-G52))))*24,"")-I52,"") -> 0 | K52: =IF(AND(G52<>"",H52<>""),((IF(G52<$D$48,MIN($D$48-G52,H52-G52),0)+IF(H52>$D$48+TIME($G$48,($G$48-INT($G$48))*60,0),MIN((H52-$D$48-TIME($G$48,($G$48-INT($G$48))*60,0)),(H52-G52)),0))*24),"") -> 0 | N52: =J52*H48 -> 0
N53: =SUM(N51:N52) -> 605.76923
D56: Special (Non-working) Day
D59: 44981 | G59: 0 | H59: BASIC PAY/DAY
G60: =G59*H60 -> 0 | H60: 0.3
H62: =G60 -> 0
C72: LYN M. BELTRAN
C73: Admin Manager

Sheet PATRICIO
C7: Employee Name: | G7: MECHELLE PATRICIO | J7: Period: | L7: =PAALAN!L7 -> September 11-25, 2026
C8: Position: | G8: Project Technical Supervisor | J8: Payroll Date: | L8: =PAALAN!L8 -> 9/31/2026
B10: Year | C10: Month | D10: Date | G10: Weekend
B11: 2026 | C11: September | D11: 11 | G11: Sun Only
B13: Start Time | C13: Regular Hours | D13: Regular Pay (hourly) | G13: Overtime Pay (hourly) | H13: Total # of Hours per Cut off | O13: Start Time | P13: Regular Hours | Q13: Regular Pay (hourly) | T13: Overtime Pay (hourly) | U13: Total # of Hours per Cut off
B14: 0.33333333 | C14: 10 | D14: =(18433.28/26)/8 -> 88.621538 | G14: =(D14*25%)+D14 -> 110.77692 | H14: 104 | O14: 0.375 | P14: 3 | Q14: =(13040/26)/8 -> 62.692308 | T14: =(Q14*25%)+Q14 -> 78.365385 | U14: 105
C16: Day | D16: Date | E16: In Time | F16: Grace period | G16: In Time | H16: Out Time | I16: Break Hrs | J16: Regular Hrs | K16: OT Hours | L16: Late | M16: Late Amount | N16: Total Pay
B17: 1 | C17: =DATE($B$11,MATCH($C$11,Data!$B$2:$B$13,0),PATRICIO!$D$11) -> 46276 | D17: =DATE($B$11,MATCH($C$11,Data!$B$2:$B$13,0),PATRICIO!$D$11) -> 46276 | E17: 0.33333333 | F17: 0 | G17: =E17-F17 -> 0.33333333 | H17: 0.75 | I17: 1 | J17: =IFERROR(IF(AND(G17<>"",H17<>""),IF(G17>$B$14+TIME($C$14,($C$14-INT($C$14))*60,0),0,IF(H17>$B$14+TIME($C$14,($C$14-INT($C$14))*60,0),MIN(TIME($C$14,($C$14-INT($C$14))*60,0),($B$14+TIME($C$14,($C$14-INT($C$14))*60,0)-G17)),MIN(IF((H17-$B$14)<0,0,(H17-$B$14)),(H17-G17))))*24,"")-I17,"") -> 9 | K17: =IF(AND(G17<>"",H17<>""),((IF(G17<$B$14,MIN($B$14-G17,H17-G17),0)+IF(H17>$B$14+TIME($C$14,($C$14-INT($C$14))*60,0),MIN((H17-$B$14-TIME($C$14,($C$14-INT($C$14))*60,0)),(H17-G17)),0))*24),"") -> 0 | L17: 0 | M17: =(D14/60)*0 -> 0 | N17: =IFERROR(J17*IF(AND(ISNUMBER(SEARCH(TEXT(C17,"ddd"),$G$11)),Data!$F$2),$G$14,$D$14)+K17*$G$14,"") -> 797.59385 | O17: =M17+N17 -> 797.59385
B18: 2 | C18: =C17+1 -> 46277 | D18: =D17+1 -> 46277 | E18: 0.375 | F18: 0 | G18: =E18-F18 -> 0.375 | H18: 0.5 | I18: 0 | J18: =IFERROR(IF(AND(G18<>"",H18<>""),IF(G18>$B$14+TIME($C$14,($C$14-INT($C$14))*60,0),0,IF(H18>$B$14+TIME($C$14,($C$14-INT($C$14))*60,0),MIN(TIME($C$14,($C$14-INT($C$14))*60,0),($B$14+TIME($C$14,($C$14-INT($C$14))*60,0)-G18)),MIN(IF((H18-$B$14)<0,0,(H18-$B$14)),(H18-G18))))*24,"")-I18,"") -> 3 | K18: 0 | L18: 0 | M18: =(D14/60)*0 -> 0 | N18: =IFERROR(J18*IF(AND(ISNUMBER(SEARCH(TEXT(C18,"ddd"),$G$11)),Data!$F$2),$G$14,$D$14)+K18*$G$14,"") -> 265.86462 | O18: =M18+N18 -> 265.86462
C19: =C18+1 -> 46278 | D19: =D18+1 -> 46278 | E19: 0 | F19: 0 | G19: =E19-F19 -> 0 | H19: 0 | I19: 0 | J19: =IFERROR(IF(AND(G19<>"",H19<>""),IF(G19>$B$14+TIME($C$14,($C$14-INT($C$14))*60,0),0,IF(H19>$B$14+TIME($C$14,($C$14-INT($C$14))*60,0),MIN(TIME($C$14,($C$14-INT($C$14))*60,0),($B$14+TIME($C$14,($C$14-INT($C$14))*60,0)-G19)),MIN(IF((H19-$B$14)<0,0,(H19-$B$14)),(H19-G19))))*24,"")-I19,"") -> 0 | K19: =IF(AND(G19<>"",H19<>""),((IF(G19<$B$14,MIN($B$14-G19,H19-G19),0)+IF(H19>$B$14+TIME($C$14,($C$14-INT($C$14))*60,0),MIN((H19-$B$14-TIME($C$14,($C$14-INT($C$14))*60,0)),(H19-G19)),0))*24),"") -> 0 | L19: 0 | M19: =(D14/60)*0 -> 0 | N19: =IFERROR(J19*IF(AND(ISNUMBER(SEARCH(TEXT(C19,"ddd"),$G$11)),Data!$F$2),$G$14,$D$14)+K19*$G$14,"") -> 0
B20: 3 | C20: =C19+1 -> 46279 | D20: =D19+1 -> 46279 | E20: 0.35694444 | F20: 0 | G20: =E20-F20 -> 0.35694444 | H20: 0.75 | I20: 1 | J20: =IFERROR(IF(AND(G20<>"",H20<>""),IF(G20>$B$14+TIME($C$14,($C$14-INT($C$14))*60,0),0,IF(H20>$B$14+TIME($C$14,($C$14-INT($C$14))*60,0),MIN(TIME($C$14,($C$14-INT($C$14))*60,0),($B$14+TIME($C$14,($C$14-INT($C$14))*60,0)-G20)),MIN(IF((H20-$B$14)<0,0,(H20-$B$14)),(H20-G20))))*24,"")-I20,"") -> 8.4333333 | K20: =IF(AND(G20<>"",H20<>""),((IF(G20<$B$14,MIN($B$14-G20,H20-G20),0)+IF(H20>$B$14+TIME($C$14,($C$14-INT($C$14))*60,0),MIN((H20-$B$14-TIME($C$14,($C$14-INT($C$14))*60,0)),(H20-G20)),0))*24),"") -> 0 | L20: =G20-B14 -> 0.023611111 | M20: =(D14/60)*0 -> 0 | N20: =IFERROR(J20*IF(AND(ISNUMBER(SEARCH(TEXT(C20,"ddd"),$G$11)),Data!$F$2),$G$14,$D$14)+K20*$G$14,"") -> 747.37497 | O20: 615.36
B21: 4 | C21: =C20+1 -> 46280 | D21: =D20+1 -> 46280 | E21: 0.33333333 | F21: 0 | G21: =E21-F21 -> 0.33333333 | H21: 0.75 | I21: 1 | J21: =IFERROR(IF(AND(G21<>"",H21<>""),IF(G21>$B$14+TIME($C$14,($C$14-INT($C$14))*60,0),0,IF(H21>$B$14+TIME($C$14,($C$14-INT($C$14))*60,0),MIN(TIME($C$14,($C$14-INT($C$14))*60,0),($B$14+TIME($C$14,($C$14-INT($C$14))*60,0)-G21)),MIN(IF((H21-$B$14)<0,0,(H21-$B$14)),(H21-G21))))*24,"")-I21,"") -> 9 | K21: =IF(AND(G21<>"",H21<>""),((IF(G21<$B$14,MIN($B$14-G21,H21-G21),0)+IF(H21>$B$14+TIME($C$14,($C$14-INT($C$14))*60,0),MIN((H21-$B$14-TIME($C$14,($C$14-INT($C$14))*60,0)),(H21-G21)),0))*24),"") -> 0 | L21: 0 | M21: =(D14/60)*0 -> 0 | N21: =IFERROR(J21*IF(AND(ISNUMBER(SEARCH(TEXT(C21,"ddd"),$G$11)),Data!$F$2),$G$14,$D$14)+K21*$G$14,"") -> 797.59385 | O21: =M21+N21 -> 797.59385
B22: 5 | C22: =C21+1 -> 46281 | D22: =D21+1 -> 46281 | E22: 0.33333333 | F22: 0 | G22: =E22-F22 -> 0.33333333 | H22: 0.75 | I22: 1 | J22: =IFERROR(IF(AND(G22<>"",H22<>""),IF(G22>$B$14+TIME($C$14,($C$14-INT($C$14))*60,0),0,IF(H22>$B$14+TIME($C$14,($C$14-INT($C$14))*60,0),MIN(TIME($C$14,($C$14-INT($C$14))*60,0),($B$14+TIME($C$14,($C$14-INT($C$14))*60,0)-G22)),MIN(IF((H22-$B$14)<0,0,(H22-$B$14)),(H22-G22))))*24,"")-I22,"") -> 9 | K22: =IF(AND(G22<>"",H22<>""),((IF(G22<$B$14,MIN($B$14-G22,H22-G22),0)+IF(H22>$B$14+TIME($C$14,($C$14-INT($C$14))*60,0),MIN((H22-$B$14-TIME($C$14,($C$14-INT($C$14))*60,0)),(H22-G22)),0))*24),"") -> 0 | L22: 0 | M22: 0 | N22: =IFERROR(J22*IF(AND(ISNUMBER(SEARCH(TEXT(C22,"ddd"),$G$11)),Data!$F$2),$G$14,$D$14)+K22*$G$14,"") -> 797.59385 | O22: =M22+N22 -> 797.59385
B23: 6 | C23: =C22+1 -> 46282 | D23: =D22+1 -> 46282 | E23: 0.33333333 | F23: 0 | G23: =E23-F23 -> 0.33333333 | H23: 0.75 | I23: 1 | J23: =IFERROR(IF(AND(G23<>"",H23<>""),IF(G23>$B$14+TIME($C$14,($C$14-INT($C$14))*60,0),0,IF(H23>$B$14+TIME($C$14,($C$14-INT($C$14))*60,0),MIN(TIME($C$14,($C$14-INT($C$14))*60,0),($B$14+TIME($C$14,($C$14-INT($C$14))*60,0)-G23)),MIN(IF((H23-$B$14)<0,0,(H23-$B$14)),(H23-G23))))*24,"")-I23,"") -> 9 | K23: =IF(AND(G23<>"",H23<>""),((IF(G23<$B$14,MIN($B$14-G23,H23-G23),0)+IF(H23>$B$14+TIME($C$14,($C$14-INT($C$14))*60,0),MIN((H23-$B$14-TIME($C$14,($C$14-INT($C$14))*60,0)),(H23-G23)),0))*24),"") -> 0 | L23: =G23-B14 -> 0 | M23: =(D14/60)*0 -> 0 | N23: =IFERROR(J23*IF(AND(ISNUMBER(SEARCH(TEXT(C23,"ddd"),$G$11)),Data!$F$2),$G$14,$D$14)+K23*$G$14,"") -> 797.59385 | O23: =M23+N23 -> 797.59385
B24: 7 | C24: =C23+1 -> 46283 | D24: =D23+1 -> 46283 | E24: 0.33333333 | F24: 0 | G24: =E24-F24 -> 0.33333333 | H24: 0.75 | I24: 1 | J24: =IFERROR(IF(AND(G24<>"",H24<>""),IF(G24>$B$14+TIME($C$14,($C$14-INT($C$14))*60,0),0,IF(H24>$B$14+TIME($C$14,($C$14-INT($C$14))*60,0),MIN(TIME($C$14,($C$14-INT($C$14))*60,0),($B$14+TIME($C$14,($C$14-INT($C$14))*60,0)-G24)),MIN(IF((H24-$B$14)<0,0,(H24-$B$14)),(H24-G24))))*24,"")-I24,"") -> 9 | K24: =IF(AND(G24<>"",H24<>""),((IF(G24<$B$14,MIN($B$14-G24,H24-G24),0)+IF(H24>$B$14+TIME($C$14,($C$14-INT($C$14))*60,0),MIN((H24-$B$14-TIME($C$14,($C$14-INT($C$14))*60,0)),(H24-G24)),0))*24),"") -> 0 | L24: 0 | M24: =(D14/60)*0 -> 0 | N24: =IFERROR(J24*IF(AND(ISNUMBER(SEARCH(TEXT(C24,"ddd"),$G$11)),Data!$F$2),$G$14,$D$14)+K24*$G$14,"") -> 797.59385 | O24: =M24+N24 -> 797.59385
B25: 8 | C25: =C24+1 -> 46284 | D25: =D24+1 -> 46284 | E25: 0.375 | F25: 0 | G25: =E25-F25 -> 0.375 | H25: 0.5 | I25: 0 | J25: =IFERROR(IF(AND(G25<>"",H25<>""),IF(G25>$B$14+TIME($C$14,($C$14-INT($C$14))*60,0),0,IF(H25>$B$14+TIME($C$14,($C$14-INT($C$14))*60,0),MIN(TIME($C$14,($C$14-INT($C$14))*60,0),($B$14+TIME($C$14,($C$14-INT($C$14))*60,0)-G25)),MIN(IF((H25-$B$14)<0,0,(H25-$B$14)),(H25-G25))))*24,"")-I25,"") -> 3 | K25: 0 | L25: 0 | M25: =(D14/60)*0 -> 0 | N25: =IFERROR(J25*IF(AND(ISNUMBER(SEARCH(TEXT(C25,"ddd"),$G$11)),Data!$F$2),$G$14,$D$14)+K25*$G$14,"") -> 265.86462 | O25: =M25+N25 -> 265.86462
C26: =C25+1 -> 46285 | D26: =D25+1 -> 46285 | E26: 0 | F26: 0 | G26: =E26-F26 -> 0 | H26: 0 | I26: 0 | J26: =IFERROR(IF(AND(G26<>"",H26<>""),IF(G26>$B$14+TIME($C$14,($C$14-INT($C$14))*60,0),0,IF(H26>$B$14+TIME($C$14,($C$14-INT($C$14))*60,0),MIN(TIME($C$14,($C$14-INT($C$14))*60,0),($B$14+TIME($C$14,($C$14-INT($C$14))*60,0)-G26)),MIN(IF((H26-$B$14)<0,0,(H26-$B$14)),(H26-G26))))*24,"")-I26,"") -> 0 | K26: =IF(AND(G26<>"",H26<>""),((IF(G26<$B$14,MIN($B$14-G26,H26-G26),0)+IF(H26>$B$14+TIME($C$14,($C$14-INT($C$14))*60,0),MIN((H26-$B$14-TIME($C$14,($C$14-INT($C$14))*60,0)),(H26-G26)),0))*24),"") -> 0 | L26: 0 | M26: =(D14/60)*0 -> 0 | N26: =IFERROR(J26*IF(AND(ISNUMBER(SEARCH(TEXT(C26,"ddd"),$G$11)),Data!$F$2),$G$14,$D$14)+K26*$G$14,"") -> 0 | O26: =M26+N26 -> 0
B27: 9 | C27: =C26+1 -> 46286 | D27: =D26+1 -> 46286 | E27: 0.34583333 | F27: 0 | G27: =E27-F27 -> 0.34583333 | H27: 0.75 | I27: 1 | J27: =IFERROR(IF(AND(G27<>"",H27<>""),IF(G27>$B$14+TIME($C$14,($C$14-INT($C$14))*60,0),0,IF(H27>$B$14+TIME($C$14,($C$14-INT($C$14))*60,0),MIN(TIME($C$14,($C$14-INT($C$14))*60,0),($B$14+TIME($C$14,($C$14-INT($C$14))*60,0)-G27)),MIN(IF((H27-$B$14)<0,0,(H27-$B$14)),(H27-G27))))*24,"")-I27,"") -> 8.7 | K27: 0 | L27: =E27-B14 -> 0.0125 | M27: =(D14/60)*0 -> 0 | N27: =IFERROR(J27*IF(AND(ISNUMBER(SEARCH(TEXT(C27,"ddd"),$G$11)),Data!$F$2),$G$14,$D$14)+K27*$G$14,"") -> 771.00738 | O27: =M27+N27 -> 771.00738
B28: 10 | C28: =C27+1 -> 46287 | D28: =D27+1 -> 46287 | E28: 0.33333333 | F28: 0 | G28: =E28-F28 -> 0.33333333 | H28: 0.75 | I28: 1 | J28: =IFERROR(IF(AND(G28<>"",H28<>""),IF(G28>$B$14+TIME($C$14,($C$14-INT($C$14))*60,0),0,IF(H28>$B$14+TIME($C$14,($C$14-INT($C$14))*60,0),MIN(TIME($C$14,($C$14-INT($C$14))*60,0),($B$14+TIME($C$14,($C$14-INT($C$14))*60,0)-G28)),MIN(IF((H28-$B$14)<0,0,(H28-$B$14)),(H28-G28))))*24,"")-I28,"") -> 9 | K28: =IF(AND(G28<>"",H28<>""),((IF(G28<$B$14,MIN($B$14-G28,H28-G28),0)+IF(H28>$B$14+TIME($C$14,($C$14-INT($C$14))*60,0),MIN((H28-$B$14-TIME($C$14,($C$14-INT($C$14))*60,0)),(H28-G28)),0))*24),"") -> 0 | L28: 0 | M28: =(D14/60)*0 -> 0 | N28: =IFERROR(J28*IF(AND(ISNUMBER(SEARCH(TEXT(C28,"ddd"),$G$11)),Data!$F$2),$G$14,$D$14)+K28*$G$14,"") -> 797.59385 | O28: =M28+N28 -> 797.59385
B29: 11 | C29: =C28+1 -> 46288 | D29: =D28+1 -> 46288 | E29: 0.33333333 | F29: 0 | G29: =E29-F29 -> 0.33333333 | H29: 0.75 | I29: 1 | J29: =IFERROR(IF(AND(G29<>"",H29<>""),IF(G29>$B$14+TIME($C$14,($C$14-INT($C$14))*60,0),0,IF(H29>$B$14+TIME($C$14,($C$14-INT($C$14))*60,0),MIN(TIME($C$14,($C$14-INT($C$14))*60,0),($B$14+TIME($C$14,($C$14-INT($C$14))*60,0)-G29)),MIN(IF((H29-$B$14)<0,0,(H29-$B$14)),(H29-G29))))*24,"")-I29,"") -> 9 | K29: =IF(AND(G29<>"",H29<>""),((IF(G29<$B$14,MIN($B$14-G29,H29-G29),0)+IF(H29>$B$14+TIME($C$14,($C$14-INT($C$14))*60,0),MIN((H29-$B$14-TIME($C$14,($C$14-INT($C$14))*60,0)),(H29-G29)),0))*24),"") -> 0 | L29: 0 | M29: =(D14/60)*0 -> 0 | N29: =IFERROR(J29*IF(AND(ISNUMBER(SEARCH(TEXT(C29,"ddd"),$G$11)),Data!$F$2),$G$14,$D$14)+K29*$G$14,"") -> 797.59385 | O29: =M29+N29 -> 797.59385
B30: 12 | C30: =C29+1 -> 46289 | D30: =D29+1 -> 46289 | E30: 0.33333333 | F30: 0 | G30: =E30-F30 -> 0.33333333 | H30: 0.75 | I30: 1 | J30: =IFERROR(IF(AND(G30<>"",H30<>""),IF(G30>$B$14+TIME($C$14,($C$14-INT($C$14))*60,0),0,IF(H30>$B$14+TIME($C$14,($C$14-INT($C$14))*60,0),MIN(TIME($C$14,($C$14-INT($C$14))*60,0),($B$14+TIME($C$14,($C$14-INT($C$14))*60,0)-G30)),MIN(IF((H30-$B$14)<0,0,(H30-$B$14)),(H30-G30))))*24,"")-I30,"") -> 9 | K30: =IF(AND(G30<>"",H30<>""),((IF(G30<$B$14,MIN($B$14-G30,H30-G30),0)+IF(H30>$B$14+TIME($C$14,($C$14-INT($C$14))*60,0),MIN((H30-$B$14-TIME($C$14,($C$14-INT($C$14))*60,0)),(H30-G30)),0))*24),"") -> 0 | L30: =G30-B14 -> 0 | M30: =(D14/60)*0 -> 0 | N30: =IFERROR(J30*IF(AND(ISNUMBER(SEARCH(TEXT(C30,"ddd"),$G$11)),Data!$F$2),$G$14,$D$14)+K30*$G$14,"") -> 797.59385 | O30: =M30+N30 -> 797.59385
B31: 13 | C31: =C30+1 -> 46290 | D31: =D30+1 -> 46290 | E31: 0.33333333 | F31: 0 | G31: =E31-F31 -> 0.33333333 | H31: 0.75 | I31: 1 | J31: =IFERROR(IF(AND(G31<>"",H31<>""),IF(G31>$B$14+TIME($C$14,($C$14-INT($C$14))*60,0),0,IF(H31>$B$14+TIME($C$14,($C$14-INT($C$14))*60,0),MIN(TIME($C$14,($C$14-INT($C$14))*60,0),($B$14+TIME($C$14,($C$14-INT($C$14))*60,0)-G31)),MIN(IF((H31-$B$14)<0,0,(H31-$B$14)),(H31-G31))))*24,"")-I31,"") -> 9 | K31: 0 | L31: 0 | M31: =(D14/60)*0 -> 0 | N31: =IFERROR(J31*IF(AND(ISNUMBER(SEARCH(TEXT(C31,"ddd"),$G$11)),Data!$F$2),$G$14,$D$14)+K31*$G$14,"") -> 797.59385 | O31: =M31+N31 -> 797.59385
G32: Total Hours | I32: =SUM(I17:I31) -> 11 | J32: =SUM(J17:J31) -> 104.13333 | K32: =SUM(K17:K31) -> 0 | L32: =SUM(L17:L31) -> 0.036111111 | M32: =SUM(M17:M31) -> 0
G33: Basic Pay | L33: =(D14/60)*0 -> 0 | N33: =(H14*D14)-N37 -> 9216.64 | O33: =SUM(O17:O31) -> 9096.4412 | P33: =N33-O33 -> 120.19877
G34: Absences, Late & Undertime | J34: =H14-J32 -> -0.13333333 | N34: =M32 -> 0 | O34: =N37 -> 0
G35: Total Basic Pay | N35: =N33-N34 -> 9216.64 | O35: =M32 -> 0
G36: Overtime Pay | J36: 0 | N36: =G14*K32 -> 0 | O36: =O33-O34-O35 -> 9096.4412
G37: Holiday Pay | N37: 0 | O37: =N37 -> 0
G38: Gross Pay | N38: =N35+N36+N37 -> 9216.64 | O38: =O36+O37 -> 9096.4412
B41: HOLIDAY PAY
D43: Regular Holiday
D44: Year | G44: Month | H44: Date | I44: Weekend
D45: 2026 | G45: June | H45: 12 | I45: Sat & Sun
D47: Start Time | G47: Regular Hours | H47: Regular Pay (hourly) | I47: Overtime Pay (hourly)
D48: 0.33333333 | G48: 10 | H48: =D14 -> 88.621538 | I48: =(H48*30%)+H48 -> 115.208
C50: Day | D50: Date | G50: In Time | H50: Out Time | I50: Break Hrs | J50: Regular Hrs | K50: OT Hours | N50: Total Pay
C51: Fri | D51: =DATE($B$11,MATCH($G$45,Data!$B$2:$B$13,0),PATRICIO!$H$45) -> 46185 | G51: 0.33333333 | H51: 0.75 | I51: 1 | J51: =IFERROR(IF(AND(G51<>"",H51<>""),IF(G51>$B$14+TIME($C$14,($C$14-INT($C$14))*60,0),0,IF(H51>$B$14+TIME($C$14,($C$14-INT($C$14))*60,0),MIN(TIME($C$14,($C$14-INT($C$14))*60,0),($B$14+TIME($C$14,($C$14-INT($C$14))*60,0)-G51)),MIN(IF((H51-$B$14)<0,0,(H51-$B$14)),(H51-G51))))*24,"")-I51,"") -> 9 | K51: =IF(AND(G51<>"",H51<>""),((IF(G51<$D$48,MIN($D$48-G51,H51-G51),0)+IF(H51>$D$48+TIME($G$48,($G$48-INT($G$48))*60,0),MIN((H51-$D$48-TIME($G$48,($G$48-INT($G$48))*60,0)),(H51-G51)),0))*24),"") -> 0 | N51: =(J51*H48) -> 797.59385
C52: Tue | D52: 23 | G52: 0 | H52: 0 | I52: 0 | J52: =IFERROR(IF(AND(G52<>"",H52<>""),IF(G52>$B$14+TIME($C$14,($C$14-INT($C$14))*60,0),0,IF(H52>$B$14+TIME($C$14,($C$14-INT($C$14))*60,0),MIN(TIME($C$14,($C$14-INT($C$14))*60,0),($B$14+TIME($C$14,($C$14-INT($C$14))*60,0)-G52)),MIN(IF((H52-$B$14)<0,0,(H52-$B$14)),(H52-G52))))*24,"")-I52,"") -> 0 | K52: =IF(AND(G52<>"",H52<>""),((IF(G52<$D$48,MIN($D$48-G52,H52-G52),0)+IF(H52>$D$48+TIME($G$48,($G$48-INT($G$48))*60,0),MIN((H52-$D$48-TIME($G$48,($G$48-INT($G$48))*60,0)),(H52-G52)),0))*24),"") -> 0 | N52: =(J52*H48) -> 0
N53: =SUM(N51:N52) -> 797.59385
D56: Special (Non-working) Day
D59: 44981 | G59: 0 | H59: BASIC PAY/DAY
G60: =G59*H60 -> 0 | H60: 0.3
H62: =G60 -> 0
C72: LYN M. BELTRAN
C73: Admin Manager

Sheet Fixed Salary - Sample
C6: Employee Name: | J6: Period: | L6: =PAALAN!L7 -> September 11-25, 2026
C7: Position: | G7: Jr. Office Engineer | J7: Payroll Date: | L7: =PAALAN!L8 -> 9/31/2026
B9: Year | C9: Month | D9: Date | G9: Weekend
B10: 2026 | C10: September | D10: 11 | G10: Sun Only
B12: Start Time | C12: Regular Hours | D12: Regular Pay (hourly) | G12: Overtime Pay (hourly) | H12: Total # of Hours per Cut off | O12: Start Time | P12: Regular Hours | Q12: Regular Pay (hourly) | T12: Overtime Pay (hourly) | U12: Total # of Hours per Cut off
B13: 0.33333333 | C13: 10 | D13: =(20000/26)/8 -> 96.153846 | G13: =(D13*25%)+D13 -> 120.19231 | H13: 104 | O13: 0.375 | P13: 3 | Q13: =(17433.28/26)/8 -> 83.813846 | T13: =(Q13*25%)+Q13 -> 104.76731 | U13: 105
C15: Day | D15: Date | G15: In Time | H15: Out Time | I15: Break Hrs | J15: Regular Hrs | K15: OT Hours | L15: Late | M15: Late Amount | N15: Total Pay
B16: 1 | C16: =DATE($B$10,MATCH($C$10,Data!$B$2:$B$13,0),'Fixed Salary - Sample'!$D$10) -> 46276 | D16: =DATE($B$10,MATCH($C$10,Data!$B$2:$B$13,0),'Fixed Salary - Sample'!$D$10) -> 46276 | E16: 0.39930556 | F16: 0 | G16: =E16-F16 -> 0.39930556 | H16: 0.74583333 | I16: 1 | J16: =IFERROR(IF(AND(G16<>"",H16<>""),IF(G16>$B$13+TIME($C$13,($C$13-INT($C$13))*60,0),0,IF(H16>$B$13+TIME($C$13,($C$13-INT($C$13))*60,0),MIN(TIME($C$13,($C$13-INT($C$13))*60,0),($B$13+TIME($C$13,($C$13-INT($C$13))*60,0)-G16)),MIN(IF((H16-$B$13)<0,0,(H16-$B$13)),(H16-G16))))*24,"")-I16,"") -> 7.3166667 | K16: =IF(AND(G16<>"",H16<>""),((IF(G16<$B$13,MIN($B$13-G16,H16-G16),0)+IF(H16>$B$13+TIME($C$13,($C$13-INT($C$13))*60,0),MIN((H16-$B$13-TIME($C$13,($C$13-INT($C$13))*60,0)),(H16-G16)),0))*24),"") -> 0 | L16: =E16-B13 -> 0.065972222 | M16: =(D13/60)*0 -> 0 | N16: =IFERROR(J16*IF(AND(ISNUMBER(SEARCH(TEXT(C16,"ddd"),$G$10)),Data!$F$2),$G$13,$D$13)+K16*$G$13,"") -> 703.52564
B17: 2 | C17: =C16+1 -> 46277 | D17: =D16+1 -> 46277 | E17: 0.41875 | F17: 0 | G17: =E17-F17 -> 0.41875 | H17: 0.5 | I17: 0 | J17: =IFERROR(IF(AND(G17<>"",H17<>""),IF(G17>$B$13+TIME($C$13,($C$13-INT($C$13))*60,0),0,IF(H17>$B$13+TIME($C$13,($C$13-INT($C$13))*60,0),MIN(TIME($C$13,($C$13-INT($C$13))*60,0),($B$13+TIME($C$13,($C$13-INT($C$13))*60,0)-G17)),MIN(IF((H17-$B$13)<0,0,(H17-$B$13)),(H17-G17))))*24,"")-I17,"") -> 1.95 | K17: =IF(AND(G17<>"",H17<>""),((IF(G17<$B$13,MIN($B$13-G17,H17-G17),0)+IF(H17>$B$13+TIME($C$13,($C$13-INT($C$13))*60,0),MIN((H17-$B$13-TIME($C$13,($C$13-INT($C$13))*60,0)),(H17-G17)),0))*24),"") -> 0 | L17: =E17-B13 -> 0.085416667 | M17: =(D13/60)*0 -> 0 | N17: =IFERROR(J17*IF(AND(ISNUMBER(SEARCH(TEXT(C17,"ddd"),$G$10)),Data!$F$2),$G$13,$D$13)+K17*$G$13,"") -> 187.5
C18: =C17+1 -> 46278 | D18: =D17+1 -> 46278 | E18: 0 | F18: 0 | G18: =E18-F18 -> 0 | H18: 0 | I18: 0 | J18: =IFERROR(IF(AND(G18<>"",H18<>""),IF(G18>$B$13+TIME($C$13,($C$13-INT($C$13))*60,0),0,IF(H18>$B$13+TIME($C$13,($C$13-INT($C$13))*60,0),MIN(TIME($C$13,($C$13-INT($C$13))*60,0),($B$13+TIME($C$13,($C$13-INT($C$13))*60,0)-G18)),MIN(IF((H18-$B$13)<0,0,(H18-$B$13)),(H18-G18))))*24,"")-I18,"") -> 0 | K18: =IF(AND(G18<>"",H18<>""),((IF(G18<$B$13,MIN($B$13-G18,H18-G18),0)+IF(H18>$B$13+TIME($C$13,($C$13-INT($C$13))*60,0),MIN((H18-$B$13-TIME($C$13,($C$13-INT($C$13))*60,0)),(H18-G18)),0))*24),"") -> 0 | L18: 0 | M18: =(D13/60)*0 -> 0 | N18: =IFERROR(J18*IF(AND(ISNUMBER(SEARCH(TEXT(C18,"ddd"),$G$10)),Data!$F$2),$G$13,$D$13)+K18*$G$13,"") -> 0
B19: 3 | C19: =C18+1 -> 46279 | D19: =D18+1 -> 46279 | E19: 0.35694444 | F19: 0 | G19: =E19-F19 -> 0.35694444 | H19: 0.75 | I19: 1 | J19: =IFERROR(IF(AND(G19<>"",H19<>""),IF(G19>$B$13+TIME($C$13,($C$13-INT($C$13))*60,0),0,IF(H19>$B$13+TIME($C$13,($C$13-INT($C$13))*60,0),MIN(TIME($C$13,($C$13-INT($C$13))*60,0),($B$13+TIME($C$13,($C$13-INT($C$13))*60,0)-G19)),MIN(IF((H19-$B$13)<0,0,(H19-$B$13)),(H19-G19))))*24,"")-I19,"") -> 8.4333333 | K19: =IF(AND(G19<>"",H19<>""),((IF(G19<$B$13,MIN($B$13-G19,H19-G19),0)+IF(H19>$B$13+TIME($C$13,($C$13-INT($C$13))*60,0),MIN((H19-$B$13-TIME($C$13,($C$13-INT($C$13))*60,0)),(H19-G19)),0))*24),"") -> 0 | L19: =E19-B13 -> 0.023611111 | M19: =(D13/60)*0 -> 0 | N19: =IFERROR(J19*IF(AND(ISNUMBER(SEARCH(TEXT(C19,"ddd"),$G$10)),Data!$F$2),$G$13,$D$13)+K19*$G$13,"") -> 810.89744
B20: 4 | C20: =C19+1 -> 46280 | D20: =D19+1 -> 46280 | E20: 0.33333333 | F20: 0 | G20: =E20-F20 -> 0.33333333 | H20: 0.69583333 | I20: 1 | J20: =IFERROR(IF(AND(G20<>"",H20<>""),IF(G20>$B$13+TIME($C$13,($C$13-INT($C$13))*60,0),0,IF(H20>$B$13+TIME($C$13,($C$13-INT($C$13))*60,0),MIN(TIME($C$13,($C$13-INT($C$13))*60,0),($B$13+TIME($C$13,($C$13-INT($C$13))*60,0)-G20)),MIN(IF((H20-$B$13)<0,0,(H20-$B$13)),(H20-G20))))*24,"")-I20,"") -> 7.7 | K20: =IF(AND(G20<>"",H20<>""),((IF(G20<$B$13,MIN($B$13-G20,H20-G20),0)+IF(H20>$B$13+TIME($C$13,($C$13-INT($C$13))*60,0),MIN((H20-$B$13-TIME($C$13,($C$13-INT($C$13))*60,0)),(H20-G20)),0))*24),"") -> 0 | L20: =E20-B13 -> 0 | M20: =(D13/60)*0 -> 0 | N20: =IFERROR(J20*IF(AND(ISNUMBER(SEARCH(TEXT(C20,"ddd"),$G$10)),Data!$F$2),$G$13,$D$13)+K20*$G$13,"") -> 740.38462
B21: 5 | C21: =C20+1 -> 46281 | D21: =D20+1 -> 46281 | E21: 0.33333333 | F21: 0 | G21: =E21-F21 -> 0.33333333 | H21: 0.75 | I21: 1 | J21: =IFERROR(IF(AND(G21<>"",H21<>""),IF(G21>$B$13+TIME($C$13,($C$13-INT($C$13))*60,0),0,IF(H21>$B$13+TIME($C$13,($C$13-INT($C$13))*60,0),MIN(TIME($C$13,($C$13-INT($C$13))*60,0),($B$13+TIME($C$13,($C$13-INT($C$13))*60,0)-G21)),MIN(IF((H21-$B$13)<0,0,(H21-$B$13)),(H21-G21))))*24,"")-I21,"") -> 9 | K21: =IF(AND(G21<>"",H21<>""),((IF(G21<$B$13,MIN($B$13-G21,H21-G21),0)+IF(H21>$B$13+TIME($C$13,($C$13-INT($C$13))*60,0),MIN((H21-$B$13-TIME($C$13,($C$13-INT($C$13))*60,0)),(H21-G21)),0))*24),"") -> 0 | L21: =E21-B13 -> 0 | M21: =(D13/60)*0 -> 0 | N21: =IFERROR(J21*IF(AND(ISNUMBER(SEARCH(TEXT(C21,"ddd"),$G$10)),Data!$F$2),$G$13,$D$13)+K21*$G$13,"") -> 865.38462
B22: 6 | C22: =C21+1 -> 46282 | D22: =D21+1 -> 46282 | E22: 0.33333333 | F22: 0 | G22: =E22-F22 -> 0.33333333 | H22: 0.75 | I22: 0 | J22: =IFERROR(IF(AND(G22<>"",H22<>""),IF(G22>$B$13+TIME($C$13,($C$13-INT($C$13))*60,0),0,IF(H22>$B$13+TIME($C$13,($C$13-INT($C$13))*60,0),MIN(TIME($C$13,($C$13-INT($C$13))*60,0),($B$13+TIME($C$13,($C$13-INT($C$13))*60,0)-G22)),MIN(IF((H22-$B$13)<0,0,(H22-$B$13)),(H22-G22))))*24,"")-I22,"") -> 10 | K22: 0 | L22: 0 | M22: =(D13/60)*0 -> 0 | N22: =IFERROR(J22*IF(AND(ISNUMBER(SEARCH(TEXT(C22,"ddd"),$G$10)),Data!$F$2),$G$13,$D$13)+K22*$G$13,"") -> 961.53846
B23: 7 | C23: =C22+1 -> 46283 | D23: =D22+1 -> 46283 | E23: 0.33333333 | F23: 0 | G23: =E23-F23 -> 0.33333333 | H23: 0.75 | I23: 0 | J23: =IFERROR(IF(AND(G23<>"",H23<>""),IF(G23>$B$13+TIME($C$13,($C$13-INT($C$13))*60,0),0,IF(H23>$B$13+TIME($C$13,($C$13-INT($C$13))*60,0),MIN(TIME($C$13,($C$13-INT($C$13))*60,0),($B$13+TIME($C$13,($C$13-INT($C$13))*60,0)-G23)),MIN(IF((H23-$B$13)<0,0,(H23-$B$13)),(H23-G23))))*24,"")-I23,"") -> 10 | K23: 0 | L23: 0 | M23: =(D13/60)*0 -> 0 | N23: =IFERROR(J23*IF(AND(ISNUMBER(SEARCH(TEXT(C23,"ddd"),$G$10)),Data!$F$2),$G$13,$D$13)+K23*$G$13,"") -> 961.53846
B24: 8 | C24: =C23+1 -> 46284 | D24: =D23+1 -> 46284 | E24: 0.39166667 | F24: 0 | G24: =E24-F24 -> 0.39166667 | H24: 0.5 | I24: 0 | J24: =IFERROR(IF(AND(G24<>"",H24<>""),IF(G24>$B$13+TIME($C$13,($C$13-INT($C$13))*60,0),0,IF(H24>$B$13+TIME($C$13,($C$13-INT($C$13))*60,0),MIN(TIME($C$13,($C$13-INT($C$13))*60,0),($B$13+TIME($C$13,($C$13-INT($C$13))*60,0)-G24)),MIN(IF((H24-$B$13)<0,0,(H24-$B$13)),(H24-G24))))*24,"")-I24,"") -> 2.6 | K24: =IF(AND(G24<>"",H24<>""),((IF(G24<$B$13,MIN($B$13-G24,H24-G24),0)+IF(H24>$B$13+TIME($C$13,($C$13-INT($C$13))*60,0),MIN((H24-$B$13-TIME($C$13,($C$13-INT($C$13))*60,0)),(H24-G24)),0))*24),"") -> 0 | L24: =E24-B13 -> 0.058333333 | M24: =(D13/60)*0 -> 0 | N24: =IFERROR(J24*IF(AND(ISNUMBER(SEARCH(TEXT(C24,"ddd"),$G$10)),Data!$F$2),$G$13,$D$13)+K24*$G$13,"") -> 250
C25: =C24+1 -> 46285 | D25: =D24+1 -> 46285 | E25: 0 | F25: 0 | G25: =E25-F25 -> 0 | H25: 0 | I25: 0 | J25: =IFERROR(IF(AND(G25<>"",H25<>""),IF(G25>$B$13+TIME($C$13,($C$13-INT($C$13))*60,0),0,IF(H25>$B$13+TIME($C$13,($C$13-INT($C$13))*60,0),MIN(TIME($C$13,($C$13-INT($C$13))*60,0),($B$13+TIME($C$13,($C$13-INT($C$13))*60,0)-G25)),MIN(IF((H25-$B$13)<0,0,(H25-$B$13)),(H25-G25))))*24,"")-I25,"") -> 0 | K25: =IF(AND(G25<>"",H25<>""),((IF(G25<$B$13,MIN($B$13-G25,H25-G25),0)+IF(H25>$B$13+TIME($C$13,($C$13-INT($C$13))*60,0),MIN((H25-$B$13-TIME($C$13,($C$13-INT($C$13))*60,0)),(H25-G25)),0))*24),"") -> 0 | L25: 0 | M25: =(D13/60)*0 -> 0 | N25: =IFERROR(J25*IF(AND(ISNUMBER(SEARCH(TEXT(C25,"ddd"),$G$10)),Data!$F$2),$G$13,$D$13)+K25*$G$13,"") -> 0
B26: 9 | C26: =C25+1 -> 46286 | D26: =D25+1 -> 46286 | E26: 0.34236111 | F26: 0 | G26: =E26-F26 -> 0.34236111 | H26: 0.74236111 | I26: 1 | J26: =IFERROR(IF(AND(G26<>"",H26<>""),IF(G26>$B$13+TIME($C$13,($C$13-INT($C$13))*60,0),0,IF(H26>$B$13+TIME($C$13,($C$13-INT($C$13))*60,0),MIN(TIME($C$13,($C$13-INT($C$13))*60,0),($B$13+TIME($C$13,($C$13-INT($C$13))*60,0)-G26)),MIN(IF((H26-$B$13)<0,0,(H26-$B$13)),(H26-G26))))*24,"")-I26,"") -> 8.6 | K26: =IF(AND(G26<>"",H26<>""),((IF(G26<$B$13,MIN($B$13-G26,H26-G26),0)+IF(H26>$B$13+TIME($C$13,($C$13-INT($C$13))*60,0),MIN((H26-$B$13-TIME($C$13,($C$13-INT($C$13))*60,0)),(H26-G26)),0))*24),"") -> 0 | L26: =E26-B13 -> 0.0090277778 | M26: =(D13/60)*0 -> 0 | N26: =IFERROR(J26*IF(AND(ISNUMBER(SEARCH(TEXT(C26,"ddd"),$G$10)),Data!$F$2),$G$13,$D$13)+K26*$G$13,"") -> 826.92308
B27: 10 | C27: =C26+1 -> 46287 | D27: =D26+1 -> 46287 | E27: 0.37222222 | F27: 0 | G27: =E27-F27 -> 0.37222222 | H27: 0.74722222 | I27: 1 | J27: =IFERROR(IF(AND(G27<>"",H27<>""),IF(G27>$B$13+TIME($C$13,($C$13-INT($C$13))*60,0),0,IF(H27>$B$13+TIME($C$13,($C$13-INT($C$13))*60,0),MIN(TIME($C$13,($C$13-INT($C$13))*60,0),($B$13+TIME($C$13,($C$13-INT($C$13))*60,0)-G27)),MIN(IF((H27-$B$13)<0,0,(H27-$B$13)),(H27-G27))))*24,"")-I27,"") -> 8 | K27: =IF(AND(G27<>"",H27<>""),((IF(G27<$B$13,MIN($B$13-G27,H27-G27),0)+IF(H27>$B$13+TIME($C$13,($C$13-INT($C$13))*60,0),MIN((H27-$B$13-TIME($C$13,($C$13-INT($C$13))*60,0)),(H27-G27)),0))*24),"") -> 0 | L27: =E27-B13 -> 0.038888889 | M27: =(D13/60)*0 -> 0 | N27: =IFERROR(J27*IF(AND(ISNUMBER(SEARCH(TEXT(C27,"ddd"),$G$10)),Data!$F$2),$G$13,$D$13)+K27*$G$13,"") -> 769.23077
B28: 11 | C28: =C27+1 -> 46288 | D28: =D27+1 -> 46288 | E28: 0.39513889 | F28: 0 | G28: =E28-F28 -> 0.39513889 | H28: 0.5 | I28: 0 | J28: =IFERROR(IF(AND(G28<>"",H28<>""),IF(G28>$B$13+TIME($C$13,($C$13-INT($C$13))*60,0),0,IF(H28>$B$13+TIME($C$13,($C$13-INT($C$13))*60,0),MIN(TIME($C$13,($C$13-INT($C$13))*60,0),($B$13+TIME($C$13,($C$13-INT($C$13))*60,0)-G28)),MIN(IF((H28-$B$13)<0,0,(H28-$B$13)),(H28-G28))))*24,"")-I28,"") -> 2.5166667 | K28: =IF(AND(G28<>"",H28<>""),((IF(G28<$B$13,MIN($B$13-G28,H28-G28),0)+IF(H28>$B$13+TIME($C$13,($C$13-INT($C$13))*60,0),MIN((H28-$B$13-TIME($C$13,($C$13-INT($C$13))*60,0)),(H28-G28)),0))*24),"") -> 0 | L28: =E28-B13 -> 0.061805556 | M28: =(D13/60)*300 -> 480.76923 | N28: =IFERROR(J28*IF(AND(ISNUMBER(SEARCH(TEXT(C28,"ddd"),$G$10)),Data!$F$2),$G$13,$D$13)+K28*$G$13,"") -> 241.98718
B29: 12 | C29: =C28+1 -> 46289 | D29: =D28+1 -> 46289 | E29: 0.35833333 | F29: 0 | G29: =E29-F29 -> 0.35833333 | H29: 0.74236111 | I29: 1 | J29: =IFERROR(IF(AND(G29<>"",H29<>""),IF(G29>$B$13+TIME($C$13,($C$13-INT($C$13))*60,0),0,IF(H29>$B$13+TIME($C$13,($C$13-INT($C$13))*60,0),MIN(TIME($C$13,($C$13-INT($C$13))*60,0),($B$13+TIME($C$13,($C$13-INT($C$13))*60,0)-G29)),MIN(IF((H29-$B$13)<0,0,(H29-$B$13)),(H29-G29))))*24,"")-I29,"") -> 8.2166667 | K29: =IF(AND(G29<>"",H29<>""),((IF(G29<$B$13,MIN($B$13-G29,H29-G29),0)+IF(H29>$B$13+TIME($C$13,($C$13-INT($C$13))*60,0),MIN((H29-$B$13-TIME($C$13,($C$13-INT($C$13))*60,0)),(H29-G29)),0))*24),"") -> 0 | L29: =E29-B13 -> 0.025 | M29: =(D13/60)*0 -> 0 | N29: =IFERROR(J29*IF(AND(ISNUMBER(SEARCH(TEXT(C29,"ddd"),$G$10)),Data!$F$2),$G$13,$D$13)+K29*$G$13,"") -> 790.0641
B30: 13 | C30: =C29+1 -> 46290 | D30: =D29+1 -> 46290 | E30: 0.375 | F30: 0 | G30: =E30-F30 -> 0.375 | H30: 0.75 | I30: 1 | J30: =IFERROR(IF(AND(G30<>"",H30<>""),IF(G30>$B$13+TIME($C$13,($C$13-INT($C$13))*60,0),0,IF(H30>$B$13+TIME($C$13,($C$13-INT($C$13))*60,0),MIN(TIME($C$13,($C$13-INT($C$13))*60,0),($B$13+TIME($C$13,($C$13-INT($C$13))*60,0)-G30)),MIN(IF((H30-$B$13)<0,0,(H30-$B$13)),(H30-G30))))*24,"")-I30,"") -> 8 | K30: 0 | L30: =E30-B13 -> 0.041666667 | M30: =(D13/60)*0 -> 0 | N30: =IFERROR(J30*IF(AND(ISNUMBER(SEARCH(TEXT(C30,"ddd"),$G$10)),Data!$F$2),$G$13,$D$13)+K30*$G$13,"") -> 769.23077
G31: Total Hours | I31: 0 | J31: =SUM(J16:J30) -> 92.333333 | K31: =SUM(K16:K30) -> 0 | L31: =SUM(L16:L30) -> 0.40972222 | M31: =SUM(M16:M30) -> 480.76923
G32: Basic Pay | L32: =(D13/60)*180 -> 288.46154 | N32: =(H13*D13)-N36 -> 10000
G33: Absences, Late & Undertime | J33: =H13-J31 -> 11.666667 | N33: =M31 -> 480.76923
G34: Total Basic Pay | N34: =N32-N33 -> 9519.2308
G35: Overtime Pay | N35: =(G13*K31) -> 0
G36: Holiday Pay | N36: 0
G37: Gross Pay | N37: =N34+N35+N36 -> 9519.2308
B42: HOLIDAY PAY
D44: Regular Holiday
D45: Year | G45: Month | H45: Date | I45: Weekend
D46: 2026 | G46: June | H46: 12 | I46: Sat & Sun
D48: Start Time | G48: Regular Hours | H48: Regular Pay (hourly) | I48: Overtime Pay (hourly)
D49: 0.33333333 | G49: 10 | H49: =D13 -> 96.153846 | I49: =(H49*30%)+H49 -> 125
C51: Day | D51: Date | G51: In Time | H51: Out Time | I51: Break Hrs | J51: Regular Hrs | K51: OT Hours | N51: Total Pay
C52: Fri | D52: =DATE($B$11,MATCH($G$46,Data!$B$2:$B$13,0),'Fixed Salary - Sample'!$H$46) -> 164 | G52: 0.33333333 | H52: 0.75 | I52: 1 | J52: =IFERROR(IF(AND(G52<>"",H52<>""),IF(G52>$B$13+TIME($C$13,($C$13-INT($C$13))*60,0),0,IF(H52>$B$13+TIME($C$13,($C$13-INT($C$13))*60,0),MIN(TIME($C$13,($C$13-INT($C$13))*60,0),($B$13+TIME($C$13,($C$13-INT($C$13))*60,0)-G52)),MIN(IF((H52-$B$13)<0,0,(H52-$B$13)),(H52-G52))))*24,"")-I52,"") -> 9 | K52: =IF(AND(G52<>"",H52<>""),((IF(G52<$D$49,MIN($D$49-G52,H52-G52),0)+IF(H52>$D$49+TIME($G$49,($G$49-INT($G$49))*60,0),MIN((H52-$D$49-TIME($G$49,($G$49-INT($G$49))*60,0)),(H52-G52)),0))*24),"") -> 0 | M52: =(D49/60)*0 -> 0 | N52: =J52*H49 -> 865.38462
C53: Tue | D53: 23 | G53: 0 | H53: 0 | I53: 0 | J53: =IFERROR(IF(AND(G53<>"",H53<>""),IF(G53>$B$13+TIME($C$13,($C$13-INT($C$13))*60,0),0,IF(H53>$B$13+TIME($C$13,($C$13-INT($C$13))*60,0),MIN(TIME($C$13,($C$13-INT($C$13))*60,0),($B$13+TIME($C$13,($C$13-INT($C$13))*60,0)-G53)),MIN(IF((H53-$B$13)<0,0,(H53-$B$13)),(H53-G53))))*24,"")-I53,"") -> 0 | K53: =IF(AND(G53<>"",H53<>""),((IF(G53<$D$49,MIN($D$49-G53,H53-G53),0)+IF(H53>$D$49+TIME($G$49,($G$49-INT($G$49))*60,0),MIN((H53-$D$49-TIME($G$49,($G$49-INT($G$49))*60,0)),(H53-G53)),0))*24),"") -> 0 | M53: =(D50/60)*0 -> 0 | N53: =J53*H49 -> 0
N54: =SUM(N52:N53) -> 865.38462
N57: =(I49*10%)+I49 -> 137.5
D58: Special (Non-working) Day | N58: =N57*2 -> 275
D60: 44981 | H60: BASIC PAY/DAY
G61: =G60*H61 -> 0 | H61: 0.3
H63: =G61 -> 0
C71: LYN M. BELTRAN
C72: Admin Manager

Sheet MALAZARTE
C7: Employee Name: | G7: MALAZARTE, JAN KAYLE MARI | K7: Period: | M7: =PAALAN!L7 -> September 11-25, 2026
C8: Position: | G8: Project Technical & Survey Staff | K8: Payroll Date: | M8: =PAALAN!L8 -> 9/31/2026
B10: Year | C10: Month | D10: Date | G10: Weekend
B11: 2026 | C11: September | D11: 11 | G11: Sun Only
B13: Start Time | C13: Regular Hours | D13: Regular Pay (hourly) | G13: Overtime Pay (hourly) | H13: Total # of Hours per Cut off | O13: Start Time | P13: Regular Hours | Q13: Regular Pay (hourly) | T13: Overtime Pay (hourly) | U13: Total # of Hours per Cut off
B14: 0.33333333 | C14: 10 | D14: =(19737.18/26)/8 -> 94.890288 | G14: =(D14*25%)+D14 -> 118.61286 | H14: 105 | O14: 0.375 | P14: 3 | Q14: =(16082.56/26)/8 -> 77.32 | T14: =(Q14*25%)+Q14 -> 96.65 | U14: 99
C16: Day | D16: Date | G16: In Time | H16: Out Time | I16: Break Hrs | J16: Regular Hrs | K16: OT Hours | L16: Late | M16: Late Amount | N16: Total Pay
B17: 1 | C17: =DATE($B$11,MATCH($C$11,Data!$B$2:$B$13,0),MALAZARTE!$D$11) -> 46276 | D17: =DATE($B$11,MATCH($C$11,Data!$B$2:$B$13,0),MALAZARTE!$D$11) -> 46276 | E17: 0.33333333 | F17: 0 | G17: =E17-F17 -> 0.33333333 | H17: 0.75 | I17: 1 | J17: =IFERROR(IF(AND(G17<>"",H17<>""),IF(G17>$B$14+TIME($C$14,($C$14-INT($C$14))*60,0),0,IF(H17>$B$14+TIME($C$14,($C$14-INT($C$14))*60,0),MIN(TIME($C$14,($C$14-INT($C$14))*60,0),($B$14+TIME($C$14,($C$14-INT($C$14))*60,0)-G17)),MIN(IF((H17-$B$14)<0,0,(H17-$B$14)),(H17-G17))))*24,"")-I17,"") -> 9 | K17: =IF(AND(G17<>"",H17<>""),((IF(G17<$B$14,MIN($B$14-G17,H17-G17),0)+IF(H17>$B$14+TIME($C$14,($C$14-INT($C$14))*60,0),MIN((H17-$B$14-TIME($C$14,($C$14-INT($C$14))*60,0)),(H17-G17)),0))*24),"") -> 0 | L17: =E17-B14 -> 0 | M17: =(D14/60)*0 -> 0 | N17: =IFERROR(J17*IF(AND(ISNUMBER(SEARCH(TEXT(C17,"ddd"),$G$11)),Data!$F$2),$G$14,$D$14)+K17*$G$14,"") -> 854.0126 | O17: =M17+N17 -> 854.0126
B18: 2 | C18: =C17+1 -> 46277 | D18: =D17+1 -> 46277 | E18: 0.375 | F18: 0 | G18: =E18-F18 -> 0.375 | H18: 0.5 | I18: 0 | J18: =IFERROR(IF(AND(G18<>"",H18<>""),IF(G18>$B$14+TIME($C$14,($C$14-INT($C$14))*60,0),0,IF(H18>$B$14+TIME($C$14,($C$14-INT($C$14))*60,0),MIN(TIME($C$14,($C$14-INT($C$14))*60,0),($B$14+TIME($C$14,($C$14-INT($C$14))*60,0)-G18)),MIN(IF((H18-$B$14)<0,0,(H18-$B$14)),(H18-G18))))*24,"")-I18,"") -> 3 | K18: 4 | L18: 0 | M18: =(D14/60)*0 -> 0 | N18: =IFERROR(J18*IF(AND(ISNUMBER(SEARCH(TEXT(C18,"ddd"),$G$11)),Data!$F$2),$G$14,$D$14)+K18*$G$14,"") -> 759.12231 | O18: =M18+N18 -> 759.12231
C19: =C18+1 -> 46278 | D19: =D18+1 -> 46278 | E19: 0 | F19: 0 | G19: =E19-F19 -> 0 | H19: 0 | I19: 0 | J19: =IFERROR(IF(AND(G19<>"",H19<>""),IF(G19>$B$14+TIME($C$14,($C$14-INT($C$14))*60,0),0,IF(H19>$B$14+TIME($C$14,($C$14-INT($C$14))*60,0),MIN(TIME($C$14,($C$14-INT($C$14))*60,0),($B$14+TIME($C$14,($C$14-INT($C$14))*60,0)-G19)),MIN(IF((H19-$B$14)<0,0,(H19-$B$14)),(H19-G19))))*24,"")-I19,"") -> 0 | K19: =IF(AND(G19<>"",H19<>""),((IF(G19<$B$14,MIN($B$14-G19,H19-G19),0)+IF(H19>$B$14+TIME($C$14,($C$14-INT($C$14))*60,0),MIN((H19-$B$14-TIME($C$14,($C$14-INT($C$14))*60,0)),(H19-G19)),0))*24),"") -> 0 | L19: 0 | M19: 0 | N19: =IFERROR(J19*IF(AND(ISNUMBER(SEARCH(TEXT(C19,"ddd"),$G$11)),Data!$F$2),$G$14,$D$14)+K19*$G$14,"") -> 0 | O19: =M19+N19 -> 0
B20: 3 | C20: =C19+1 -> 46279 | D20: =D19+1 -> 46279 | E20: 0.33333333 | F20: 0 | G20: =E20-F20 -> 0.33333333 | H20: 0.75 | I20: 1 | J20: =IFERROR(IF(AND(G20<>"",H20<>""),IF(G20>$B$14+TIME($C$14,($C$14-INT($C$14))*60,0),0,IF(H20>$B$14+TIME($C$14,($C$14-INT($C$14))*60,0),MIN(TIME($C$14,($C$14-INT($C$14))*60,0),($B$14+TIME($C$14,($C$14-INT($C$14))*60,0)-G20)),MIN(IF((H20-$B$14)<0,0,(H20-$B$14)),(H20-G20))))*24,"")-I20,"") -> 9 | K20: =IF(AND(G20<>"",H20<>""),((IF(G20<$B$14,MIN($B$14-G20,H20-G20),0)+IF(H20>$B$14+TIME($C$14,($C$14-INT($C$14))*60,0),MIN((H20-$B$14-TIME($C$14,($C$14-INT($C$14))*60,0)),(H20-G20)),0))*24),"") -> 0 | L20: =G20-B14 -> 0 | M20: =(D14/60)*0 -> 0 | N20: =IFERROR(J20*IF(AND(ISNUMBER(SEARCH(TEXT(C20,"ddd"),$G$11)),Data!$F$2),$G$14,$D$14)+K20*$G$14,"") -> 854.0126 | O20: =M20+N20 -> 854.0126
B21: 4 | C21: =C20+1 -> 46280 | D21: =D20+1 -> 46280 | E21: 0.33541667 | F21: 0 | G21: =E21-F21 -> 0.33541667 | H21: 0.75 | I21: 1 | J21: =IFERROR(IF(AND(G21<>"",H21<>""),IF(G21>$B$14+TIME($C$14,($C$14-INT($C$14))*60,0),0,IF(H21>$B$14+TIME($C$14,($C$14-INT($C$14))*60,0),MIN(TIME($C$14,($C$14-INT($C$14))*60,0),($B$14+TIME($C$14,($C$14-INT($C$14))*60,0)-G21)),MIN(IF((H21-$B$14)<0,0,(H21-$B$14)),(H21-G21))))*24,"")-I21,"") -> 8.95 | K21: =IF(AND(G21<>"",H21<>""),((IF(G21<$B$14,MIN($B$14-G21,H21-G21),0)+IF(H21>$B$14+TIME($C$14,($C$14-INT($C$14))*60,0),MIN((H21-$B$14-TIME($C$14,($C$14-INT($C$14))*60,0)),(H21-G21)),0))*24),"") -> 0 | L21: =E21-B14 -> 0.0020833333 | M21: =(D14/60)*3 -> 4.7445144 | N21: =IFERROR(J21*IF(AND(ISNUMBER(SEARCH(TEXT(C21,"ddd"),$G$11)),Data!$F$2),$G$14,$D$14)+K21*$G$14,"") -> 849.26808 | O21: =M21+N21 -> 854.0126
B22: 5 | C22: =C21+1 -> 46281 | D22: =D21+1 -> 46281 | E22: 0.33333333 | F22: 0 | G22: =E22-F22 -> 0.33333333 | H22: 0.74305556 | I22: 1 | J22: =IFERROR(IF(AND(G22<>"",H22<>""),IF(G22>$B$14+TIME($C$14,($C$14-INT($C$14))*60,0),0,IF(H22>$B$14+TIME($C$14,($C$14-INT($C$14))*60,0),MIN(TIME($C$14,($C$14-INT($C$14))*60,0),($B$14+TIME($C$14,($C$14-INT($C$14))*60,0)-G22)),MIN(IF((H22-$B$14)<0,0,(H22-$B$14)),(H22-G22))))*24,"")-I22,"") -> 8.8333333 | K22: =IF(AND(G22<>"",H22<>""),((IF(G22<$B$14,MIN($B$14-G22,H22-G22),0)+IF(H22>$B$14+TIME($C$14,($C$14-INT($C$14))*60,0),MIN((H22-$B$14-TIME($C$14,($C$14-INT($C$14))*60,0)),(H22-G22)),0))*24),"") -> 0 | L22: =E22-B14 -> 0 | M22: 0 | N22: =IFERROR(J22*IF(AND(ISNUMBER(SEARCH(TEXT(C22,"ddd"),$G$11)),Data!$F$2),$G$14,$D$14)+K22*$G$14,"") -> 838.19755 | O22: =M22+N22 -> 838.19755 | P22: =O21-O22 -> 15.815048 | R22: 0.40486111
B23: 6 | C23: =C22+1 -> 46282 | D23: =D22+1 -> 46282 | E23: 0.33333333 | F23: 0 | G23: =E23-F23 -> 0.33333333 | H23: 0.75 | I23: 1 | J23: =IFERROR(IF(AND(G23<>"",H23<>""),IF(G23>$B$14+TIME($C$14,($C$14-INT($C$14))*60,0),0,IF(H23>$B$14+TIME($C$14,($C$14-INT($C$14))*60,0),MIN(TIME($C$14,($C$14-INT($C$14))*60,0),($B$14+TIME($C$14,($C$14-INT($C$14))*60,0)-G23)),MIN(IF((H23-$B$14)<0,0,(H23-$B$14)),(H23-G23))))*24,"")-I23,"") -> 9 | K23: 0 | L23: =G23-B14 -> 0 | M23: =(D14/60)*0 -> 0 | N23: =IFERROR(J23*IF(AND(ISNUMBER(SEARCH(TEXT(C23,"ddd"),$G$11)),Data!$F$2),$G$14,$D$14)+K23*$G$14,"") -> 854.0126 | O23: =M23+N23 -> 854.0126 | R23: 0.010416667
B24: 7 | C24: =C23+1 -> 46283 | D24: =D23+1 -> 46283 | E24: 0.33333333 | F24: 0 | G24: =E24-F24 -> 0.33333333 | H24: 0.75 | I24: 1 | J24: =IFERROR(IF(AND(G24<>"",H24<>""),IF(G24>$B$14+TIME($C$14,($C$14-INT($C$14))*60,0),0,IF(H24>$B$14+TIME($C$14,($C$14-INT($C$14))*60,0),MIN(TIME($C$14,($C$14-INT($C$14))*60,0),($B$14+TIME($C$14,($C$14-INT($C$14))*60,0)-G24)),MIN(IF((H24-$B$14)<0,0,(H24-$B$14)),(H24-G24))))*24,"")-I24,"") -> 9 | K24: =IF(AND(G24<>"",H24<>""),((IF(G24<$B$14,MIN($B$14-G24,H24-G24),0)+IF(H24>$B$14+TIME($C$14,($C$14-INT($C$14))*60,0),MIN((H24-$B$14-TIME($C$14,($C$14-INT($C$14))*60,0)),(H24-G24)),0))*24),"") -> 0 | L24: =E24-B14 -> 0 | M24: =(D14/60)*0 -> 0 | N24: =IFERROR(J24*IF(AND(ISNUMBER(SEARCH(TEXT(C24,"ddd"),$G$11)),Data!$F$2),$G$14,$D$14)+K24*$G$14,"") -> 854.0126 | O24: =M24+N24 -> 854.0126 | R24: =R22-R23 -> 0.39444444
B25: 8 | C25: =C24+1 -> 46284 | D25: =D24+1 -> 46284 | E25: 0 | F25: 0 | G25: 0 | H25: 0 | I25: 0 | J25: =IFERROR(IF(AND(G25<>"",H25<>""),IF(G25>$B$14+TIME($C$14,($C$14-INT($C$14))*60,0),0,IF(H25>$B$14+TIME($C$14,($C$14-INT($C$14))*60,0),MIN(TIME($C$14,($C$14-INT($C$14))*60,0),($B$14+TIME($C$14,($C$14-INT($C$14))*60,0)-G25)),MIN(IF((H25-$B$14)<0,0,(H25-$B$14)),(H25-G25))))*24,"")-I25,"") -> 0 | K25: =IF(AND(G25<>"",H25<>""),((IF(G25<$B$14,MIN($B$14-G25,H25-G25),0)+IF(H25>$B$14+TIME($C$14,($C$14-INT($C$14))*60,0),MIN((H25-$B$14-TIME($C$14,($C$14-INT($C$14))*60,0)),(H25-G25)),0))*24),"") -> 0 | L25: 0 | M25: =(D14/60)*540 -> 854.0126 | N25: =IFERROR(J25*IF(AND(ISNUMBER(SEARCH(TEXT(C25,"ddd"),$G$11)),Data!$F$2),$G$14,$D$14)+K25*$G$14,"") -> 0 | O25: =M25+N25 -> 854.0126
C26: =C25+1 -> 46285 | D26: =D25+1 -> 46285 | E26: 0 | F26: 0 | G26: =E26-F26 -> 0 | H26: 0 | I26: 0 | J26: =IFERROR(IF(AND(G26<>"",H26<>""),IF(G26>$B$14+TIME($C$14,($C$14-INT($C$14))*60,0),0,IF(H26>$B$14+TIME($C$14,($C$14-INT($C$14))*60,0),MIN(TIME($C$14,($C$14-INT($C$14))*60,0),($B$14+TIME($C$14,($C$14-INT($C$14))*60,0)-G26)),MIN(IF((H26-$B$14)<0,0,(H26-$B$14)),(H26-G26))))*24,"")-I26,"") -> 0 | K26: =IF(AND(G26<>"",H26<>""),((IF(G26<$B$14,MIN($B$14-G26,H26-G26),0)+IF(H26>$B$14+TIME($C$14,($C$14-INT($C$14))*60,0),MIN((H26-$B$14-TIME($C$14,($C$14-INT($C$14))*60,0)),(H26-G26)),0))*24),"") -> 0 | L26: 0 | M26: =(D14/60)*0 -> 0 | N26: =IFERROR(J26*IF(AND(ISNUMBER(SEARCH(TEXT(C26,"ddd"),$G$11)),Data!$F$2),$G$14,$D$14)+K26*$G$14,"") -> 0 | O26: =M26+N26 -> 0
B27: 9 | C27: =C26+1 -> 46286 | D27: =D26+1 -> 46286 | E27: 0.33333333 | F27: 0 | G27: =E27-F27 -> 0.33333333 | H27: 0.75 | I27: 1 | J27: =IFERROR(IF(AND(G27<>"",H27<>""),IF(G27>$B$14+TIME($C$14,($C$14-INT($C$14))*60,0),0,IF(H27>$B$14+TIME($C$14,($C$14-INT($C$14))*60,0),MIN(TIME($C$14,($C$14-INT($C$14))*60,0),($B$14+TIME($C$14,($C$14-INT($C$14))*60,0)-G27)),MIN(IF((H27-$B$14)<0,0,(H27-$B$14)),(H27-G27))))*24,"")-I27,"") -> 9 | K27: =IF(AND(G27<>"",H27<>""),((IF(G27<$B$14,MIN($B$14-G27,H27-G27),0)+IF(H27>$B$14+TIME($C$14,($C$14-INT($C$14))*60,0),MIN((H27-$B$14-TIME($C$14,($C$14-INT($C$14))*60,0)),(H27-G27)),0))*24),"") -> 0 | L27: 0 | M27: =(D14/60)*0 -> 0 | N27: =IFERROR(J27*IF(AND(ISNUMBER(SEARCH(TEXT(C27,"ddd"),$G$11)),Data!$F$2),$G$14,$D$14)+K27*$G$14,"") -> 854.0126 | O27: =M27+N27 -> 854.0126
B28: 10 | C28: =C27+1 -> 46287 | D28: =D27+1 -> 46287 | E28: 0.33333333 | F28: 0 | G28: =E28-F28 -> 0.33333333 | H28: 0.75 | I28: 1 | J28: =IFERROR(IF(AND(G28<>"",H28<>""),IF(G28>$B$14+TIME($C$14,($C$14-INT($C$14))*60,0),0,IF(H28>$B$14+TIME($C$14,($C$14-INT($C$14))*60,0),MIN(TIME($C$14,($C$14-INT($C$14))*60,0),($B$14+TIME($C$14,($C$14-INT($C$14))*60,0)-G28)),MIN(IF((H28-$B$14)<0,0,(H28-$B$14)),(H28-G28))))*24,"")-I28,"") -> 9 | K28: =IF(AND(G28<>"",H28<>""),((IF(G28<$B$14,MIN($B$14-G28,H28-G28),0)+IF(H28>$B$14+TIME($C$14,($C$14-INT($C$14))*60,0),MIN((H28-$B$14-TIME($C$14,($C$14-INT($C$14))*60,0)),(H28-G28)),0))*24),"") -> 0 | L28: 0 | M28: =(D14/60)*0 -> 0 | N28: =IFERROR(J28*IF(AND(ISNUMBER(SEARCH(TEXT(C28,"ddd"),$G$11)),Data!$F$2),$G$14,$D$14)+K28*$G$14,"") -> 854.0126 | O28: =M28+N28 -> 854.0126
B29: 11 | C29: =C28+1 -> 46288 | D29: =D28+1 -> 46288 | E29: 0.33541667 | F29: 0 | G29: =E29-F29 -> 0.33541667 | H29: 0.75 | I29: 1 | J29: =IFERROR(IF(AND(G29<>"",H29<>""),IF(G29>$B$14+TIME($C$14,($C$14-INT($C$14))*60,0),0,IF(H29>$B$14+TIME($C$14,($C$14-INT($C$14))*60,0),MIN(TIME($C$14,($C$14-INT($C$14))*60,0),($B$14+TIME($C$14,($C$14-INT($C$14))*60,0)-G29)),MIN(IF((H29-$B$14)<0,0,(H29-$B$14)),(H29-G29))))*24,"")-I29,"") -> 8.95 | K29: =IF(AND(G29<>"",H29<>""),((IF(G29<$B$14,MIN($B$14-G29,H29-G29),0)+IF(H29>$B$14+TIME($C$14,($C$14-INT($C$14))*60,0),MIN((H29-$B$14-TIME($C$14,($C$14-INT($C$14))*60,0)),(H29-G29)),0))*24),"") -> 0 | L29: =E29-B14 -> 0.0020833333 | M29: =(D14/60)*3 -> 4.7445144 | N29: =IFERROR(J29*IF(AND(ISNUMBER(SEARCH(TEXT(C29,"ddd"),$G$11)),Data!$F$2),$G$14,$D$14)+K29*$G$14,"") -> 849.26808 | O29: =M29+N29 -> 854.0126 | P29: =O28-O29 -> 0
B30: 12 | C30: =C29+1 -> 46289 | D30: =D29+1 -> 46289 | E30: 0.33333333 | F30: 0 | G30: =E30-F30 -> 0.33333333 | H30: 0.75 | I30: 1 | J30: =IFERROR(IF(AND(G30<>"",H30<>""),IF(G30>$B$14+TIME($C$14,($C$14-INT($C$14))*60,0),0,IF(H30>$B$14+TIME($C$14,($C$14-INT($C$14))*60,0),MIN(TIME($C$14,($C$14-INT($C$14))*60,0),($B$14+TIME($C$14,($C$14-INT($C$14))*60,0)-G30)),MIN(IF((H30-$B$14)<0,0,(H30-$B$14)),(H30-G30))))*24,"")-I30,"") -> 9 | K30: 2 | L30: =G30-B14 -> 0 | M30: =(D14/60)*0 -> 0 | N30: =IFERROR(J30*IF(AND(ISNUMBER(SEARCH(TEXT(C30,"ddd"),$G$11)),Data!$F$2),$G$14,$D$14)+K30*$G$14,"") -> 1091.2383 | O30: =M30+N30 -> 1091.2383
B31: 13 | C31: =C30+1 -> 46290 | D31: =D30+1 -> 46290 | E31: 0.33333333 | F31: 0 | G31: =E31-F31 -> 0.33333333 | H31: 0.75 | I31: 1 | J31: =IFERROR(IF(AND(G31<>"",H31<>""),IF(G31>$B$14+TIME($C$14,($C$14-INT($C$14))*60,0),0,IF(H31>$B$14+TIME($C$14,($C$14-INT($C$14))*60,0),MIN(TIME($C$14,($C$14-INT($C$14))*60,0),($B$14+TIME($C$14,($C$14-INT($C$14))*60,0)-G31)),MIN(IF((H31-$B$14)<0,0,(H31-$B$14)),(H31-G31))))*24,"")-I31,"") -> 9 | K31: 4 | L31: =E31-B14 -> 0 | M31: =(D14/60)*0 -> 0 | N31: =IFERROR(J31*IF(AND(ISNUMBER(SEARCH(TEXT(C31,"ddd"),$G$11)),Data!$F$2),$G$14,$D$14)+K31*$G$14,"") -> 1328.464 | O31: =M31+N31 -> 1328.464 | P31: =O28-O31 -> -474.45144
G32: Total Hours | I32: =SUM(I17:I31) -> 11 | J32: =SUM(J17:J31) -> 101.73333 | K32: =SUM(K17:K31) -> 10 | L32: =SUM(L17:L31) -> 0.0041666667 | M32: =SUM(M17:M31) -> 863.50162 | O32: =SUM(O17:O31) -> 11703.136 | P32: =SUM(P17:P31) -> -458.63639 | Q32: =O32+P32 -> 11244.499
G33: Basic Pay | L33: =(D14/60)*0 -> 0 | N33: =D14*H14 -> 9963.4803
G34: Absences, Late & Undertime | J34: =H14-J32 -> 3.2666667 | L34: =(D15/60)*281 -> 0 | N34: =M32 -> 863.50162 | O34: =O32-O33 -> 11703.136
G35: Total Basic Pay | N35: =N33-N34 -> 9099.9787
G36: Overtime Pay & Premium | N36: =(G14*K32) -> 1186.1286
G37: Holiday Pay/Premium | N37: 0
G38: Gross Pay | N38: =N35+N36+N37 -> 10286.107
B41: HOLIDAY PAY
D43: Regular Holiday
D44: Year | G44: Month | H44: Date | I44: Weekend
D45: 2026 | G45: March | H45: 20 | I45: Sat & Sun
D47: Start Time | G47: Regular Hours | H47: Regular Pay (hourly) | I47: Overtime Pay (hourly)
D48: 0.29166667 | G48: 14 | H48: =D14 -> 94.890288 | I48: =(H48*30%)+H48 -> 123.35737
C50: Day | D50: Date | G50: In Time | H50: Out Time | I50: Break Hrs | J50: Regular Hrs | K50: OT Hours | N50: Total Pay
C51: Fri | D51: 46101 | G51: 0.33333333 | H51: 0.75 | I51: 1 | J51: =IFERROR(IF(AND(G51<>"",H51<>""),IF(G51>$B$14+TIME($C$14,($C$14-INT($C$14))*60,0),0,IF(H51>$B$14+TIME($C$14,($C$14-INT($C$14))*60,0),MIN(TIME($C$14,($C$14-INT($C$14))*60,0),($B$14+TIME($C$14,($C$14-INT($C$14))*60,0)-G51)),MIN(IF((H51-$B$14)<0,0,(H51-$B$14)),(H51-G51))))*24,"")-I51,"") -> 9 | K51: =IF(AND(G51<>"",H51<>""),((IF(G51<$D$48,MIN($D$48-G51,H51-G51),0)+IF(H51>$D$48+TIME($G$48,($G$48-INT($G$48))*60,0),MIN((H51-$D$48-TIME($G$48,($G$48-INT($G$48))*60,0)),(H51-G51)),0))*24),"") -> 0 | N51: =(J51*H48)+854.01*30% -> 1110.2156
C52: Tue | D52: 23 | G52: 0 | H52: 0 | I52: 0 | J52: =IFERROR(IF(AND(G52<>"",H52<>""),IF(G52>$B$14+TIME($C$14,($C$14-INT($C$14))*60,0),0,IF(H52>$B$14+TIME($C$14,($C$14-INT($C$14))*60,0),MIN(TIME($C$14,($C$14-INT($C$14))*60,0),($B$14+TIME($C$14,($C$14-INT($C$14))*60,0)-G52)),MIN(IF((H52-$B$14)<0,0,(H52-$B$14)),(H52-G52))))*24,"")-I52,"") -> 0 | K52: =IF(AND(G52<>"",H52<>""),((IF(G52<$D$48,MIN($D$48-G52,H52-G52),0)+IF(H52>$D$48+TIME($G$48,($G$48-INT($G$48))*60,0),MIN((H52-$D$48-TIME($G$48,($G$48-INT($G$48))*60,0)),(H52-G52)),0))*24),"") -> 0 | N52: 0
N53: =SUM(N51:N52) -> 1110.2156
D56: 46255 | G56: 854.01 | H56: BASIC PAY/DAY
G57: =G56*H57 -> 256.203 | H57: 0.3
H59: =G57 -> 256.203
C67: LYN M. BELTRAN
C68: Admin Manager

Sheet PAREDES
C7: Employee Name: | G7: MATTHEW JOHN CLIFFORD PAREDES | K7: Period: | M7: =PAALAN!L7 -> September 11-25, 2026
C8: Position: | G8: Draftsman | K8: Payroll Date: | M8: =PAALAN!L8 -> 9/31/2026
B10: Year | C10: Month | D10: Date | G10: Weekend
B11: 2026 | C11: September | D11: 11 | G11: Sun Only
B13: Start Time | C13: Regular Hours | D13: Regular Pay (hourly) | G13: Overtime Pay (hourly) | H13: Total # of Hours per Cut off | O13: Start Time | P13: Regular Hours | Q13: Regular Pay (hourly) | T13: Overtime Pay (hourly) | U13: Total # of Hours per Cut off
B14: 0.33333333 | C14: 10 | D14: =(17158.67/26)/8 -> 82.493606 | G14: =(D14*25%)+D14 -> 103.11701 | H14: 105 | O14: 0.375 | P14: 3 | Q14: =(13040/26)/8 -> 62.692308 | T14: =(Q14*25%)+Q14 -> 78.365385 | U14: 105
C16: Day | D16: Date | G16: In Time | H16: Out Time | I16: Break Hrs | J16: Regular Hrs | K16: OT Hours | L16: Late | M16: Late Amount | N16: Total Pay
B17: 1 | C17: =DATE($B$11,MATCH($C$11,Data!$B$2:$B$13,0),PAREDES!$D$11) -> 46276 | D17: =DATE($B$11,MATCH($C$11,Data!$B$2:$B$13,0),PAREDES!$D$11) -> 46276 | E17: 0.34513889 | F17: 0 | G17: =E17-F17 -> 0.34513889 | H17: 0.75 | I17: 1 | J17: =IFERROR(IF(AND(G17<>"",H17<>""),IF(G17>$B$14+TIME($C$14,($C$14-INT($C$14))*60,0),0,IF(H17>$B$14+TIME($C$14,($C$14-INT($C$14))*60,0),MIN(TIME($C$14,($C$14-INT($C$14))*60,0),($B$14+TIME($C$14,($C$14-INT($C$14))*60,0)-G17)),MIN(IF((H17-$B$14)<0,0,(H17-$B$14)),(H17-G17))))*24,"")-I17,"") -> 8.7166667 | K17: 0 | L17: =E17-B14 -> 0.011805556 | M17: =(D14/60)*17 -> 23.373188 | N17: =IFERROR(J17*IF(AND(ISNUMBER(SEARCH(TEXT(C17,"ddd"),$G$11)),Data!$F$2),$G$14,$D$14)+K17*$G$14,"") -> 719.06926 | O17: =M17+N17 -> 742.44245
B18: 2 | C18: =C17+1 -> 46277 | D18: =D17+1 -> 46277 | E18: 0.375 | F18: 0 | G18: =E18-F18 -> 0.375 | H18: 0.5 | I18: 0 | J18: =IFERROR(IF(AND(G18<>"",H18<>""),IF(G18>$B$14+TIME($C$14,($C$14-INT($C$14))*60,0),0,IF(H18>$B$14+TIME($C$14,($C$14-INT($C$14))*60,0),MIN(TIME($C$14,($C$14-INT($C$14))*60,0),($B$14+TIME($C$14,($C$14-INT($C$14))*60,0)-G18)),MIN(IF((H18-$B$14)<0,0,(H18-$B$14)),(H18-G18))))*24,"")-I18,"") -> 3 | K18: 4 | L18: =E18-B14 -> 0.041666667 | M18: =(D14/60)*0 -> 0 | N18: =IFERROR(J18*IF(AND(ISNUMBER(SEARCH(TEXT(C18,"ddd"),$G$11)),Data!$F$2),$G$14,$D$14)+K18*$G$14,"") -> 659.94885
C19: =C18+1 -> 46278 | D19: =D18+1 -> 46278 | E19: 0 | F19: 0 | G19: =E19-F19 -> 0 | H19: 0 | I19: 0 | J19: =IFERROR(IF(AND(G19<>"",H19<>""),IF(G19>$B$14+TIME($C$14,($C$14-INT($C$14))*60,0),0,IF(H19>$B$14+TIME($C$14,($C$14-INT($C$14))*60,0),MIN(TIME($C$14,($C$14-INT($C$14))*60,0),($B$14+TIME($C$14,($C$14-INT($C$14))*60,0)-G19)),MIN(IF((H19-$B$14)<0,0,(H19-$B$14)),(H19-G19))))*24,"")-I19,"") -> 0 | K19: =IF(AND(G19<>"",H19<>""),((IF(G19<$B$14,MIN($B$14-G19,H19-G19),0)+IF(H19>$B$14+TIME($C$14,($C$14-INT($C$14))*60,0),MIN((H19-$B$14-TIME($C$14,($C$14-INT($C$14))*60,0)),(H19-G19)),0))*24),"") -> 0 | L19: 0 | M19: =(D14/60)*0 -> 0 | N19: =IFERROR(J19*IF(AND(ISNUMBER(SEARCH(TEXT(C19,"ddd"),$G$11)),Data!$F$2),$G$14,$D$14)+K19*$G$14,"") -> 0 | O19: =M19+N19 -> 0
B20: 3 | C20: =C19+1 -> 46279 | D20: =D19+1 -> 46279 | E20: 0.33333333 | F20: 0 | G20: =E20-F20 -> 0.33333333 | H20: 0.75 | I20: 1 | J20: =IFERROR(IF(AND(G20<>"",H20<>""),IF(G20>$B$14+TIME($C$14,($C$14-INT($C$14))*60,0),0,IF(H20>$B$14+TIME($C$14,($C$14-INT($C$14))*60,0),MIN(TIME($C$14,($C$14-INT($C$14))*60,0),($B$14+TIME($C$14,($C$14-INT($C$14))*60,0)-G20)),MIN(IF((H20-$B$14)<0,0,(H20-$B$14)),(H20-G20))))*24,"")-I20,"") -> 9 | K20: =IF(AND(G20<>"",H20<>""),((IF(G20<$B$14,MIN($B$14-G20,H20-G20),0)+IF(H20>$B$14+TIME($C$14,($C$14-INT($C$14))*60,0),MIN((H20-$B$14-TIME($C$14,($C$14-INT($C$14))*60,0)),(H20-G20)),0))*24),"") -> 0 | L20: =G20-B14 -> 0 | M20: =(D14/60)*0 -> 0 | N20: =IFERROR(J20*IF(AND(ISNUMBER(SEARCH(TEXT(C20,"ddd"),$G$11)),Data!$F$2),$G$14,$D$14)+K20*$G$14,"") -> 742.44245 | O20: =M20+N20 -> 742.44245
B21: 4 | C21: =C20+1 -> 46280 | D21: =D20+1 -> 46280 | E21: 0.33333333 | F21: 0 | G21: =E21-F21 -> 0.33333333 | H21: 0.75 | I21: 1 | J21: =IFERROR(IF(AND(G21<>"",H21<>""),IF(G21>$B$14+TIME($C$14,($C$14-INT($C$14))*60,0),0,IF(H21>$B$14+TIME($C$14,($C$14-INT($C$14))*60,0),MIN(TIME($C$14,($C$14-INT($C$14))*60,0),($B$14+TIME($C$14,($C$14-INT($C$14))*60,0)-G21)),MIN(IF((H21-$B$14)<0,0,(H21-$B$14)),(H21-G21))))*24,"")-I21,"") -> 9 | K21: =IF(AND(G21<>"",H21<>""),((IF(G21<$B$14,MIN($B$14-G21,H21-G21),0)+IF(H21>$B$14+TIME($C$14,($C$14-INT($C$14))*60,0),MIN((H21-$B$14-TIME($C$14,($C$14-INT($C$14))*60,0)),(H21-G21)),0))*24),"") -> 0 | L21: 0 | M21: =(D14/60)*0 -> 0 | N21: =IFERROR(J21*IF(AND(ISNUMBER(SEARCH(TEXT(C21,"ddd"),$G$11)),Data!$F$2),$G$14,$D$14)+K21*$G$14,"") -> 742.44245 | O21: =M21+N21 -> 742.44245 | P21: =N21-O21 -> 0
B22: 5 | C22: =C21+1 -> 46281 | D22: =D21+1 -> 46281 | E22: 0.33333333 | F22: 0 | G22: =E22-F22 -> 0.33333333 | H22: 0.75 | I22: 1 | J22: 0 | K22: =IF(AND(G22<>"",H22<>""),((IF(G22<$B$14,MIN($B$14-G22,H22-G22),0)+IF(H22>$B$14+TIME($C$14,($C$14-INT($C$14))*60,0),MIN((H22-$B$14-TIME($C$14,($C$14-INT($C$14))*60,0)),(H22-G22)),0))*24),"") -> 0 | L22: 0 | M22: =(D14/60)*0 -> 0 | N22: =IFERROR(J22*IF(AND(ISNUMBER(SEARCH(TEXT(C22,"ddd"),$G$11)),Data!$F$2),$G$14,$D$14)+K22*$G$14,"") -> 0 | O22: =M22+N22 -> 0 | R22: 0.40486111
B23: 6 | C23: =C22+1 -> 46282 | D23: =D22+1 -> 46282 | E23: 0.33333333 | F23: 0 | G23: =E23-F23 -> 0.33333333 | H23: 0.75 | I23: 1 | J23: =IFERROR(IF(AND(G23<>"",H23<>""),IF(G23>$B$14+TIME($C$14,($C$14-INT($C$14))*60,0),0,IF(H23>$B$14+TIME($C$14,($C$14-INT($C$14))*60,0),MIN(TIME($C$14,($C$14-INT($C$14))*60,0),($B$14+TIME($C$14,($C$14-INT($C$14))*60,0)-G23)),MIN(IF((H23-$B$14)<0,0,(H23-$B$14)),(H23-G23))))*24,"")-I23,"") -> 9 | K23: =IF(AND(G23<>"",H23<>""),((IF(G23<$B$14,MIN($B$14-G23,H23-G23),0)+IF(H23>$B$14+TIME($C$14,($C$14-INT($C$14))*60,0),MIN((H23-$B$14-TIME($C$14,($C$14-INT($C$14))*60,0)),(H23-G23)),0))*24),"") -> 0 | L23: =G23-B14 -> 0 | M23: =(D14/60)*0 -> 0 | N23: =IFERROR(J23*IF(AND(ISNUMBER(SEARCH(TEXT(C23,"ddd"),$G$11)),Data!$F$2),$G$14,$D$14)+K23*$G$14,"") -> 742.44245 | O23: =M23+N23 -> 742.44245 | R23: 0.010416667
B24: 7 | C24: =C23+1 -> 46283 | D24: =D23+1 -> 46283 | E24: 0.33333333 | F24: 0 | G24: =E24-F24 -> 0.33333333 | H24: 0.75 | I24: 1 | J24: =IFERROR(IF(AND(G24<>"",H24<>""),IF(G24>$B$14+TIME($C$14,($C$14-INT($C$14))*60,0),0,IF(H24>$B$14+TIME($C$14,($C$14-INT($C$14))*60,0),MIN(TIME($C$14,($C$14-INT($C$14))*60,0),($B$14+TIME($C$14,($C$14-INT($C$14))*60,0)-G24)),MIN(IF((H24-$B$14)<0,0,(H24-$B$14)),(H24-G24))))*24,"")-I24,"") -> 9 | K24: =IF(AND(G24<>"",H24<>""),((IF(G24<$B$14,MIN($B$14-G24,H24-G24),0)+IF(H24>$B$14+TIME($C$14,($C$14-INT($C$14))*60,0),MIN((H24-$B$14-TIME($C$14,($C$14-INT($C$14))*60,0)),(H24-G24)),0))*24),"") -> 0 | L24: =E24-B14 -> 0 | M24: =(D14/60)*0 -> 0 | N24: =IFERROR(J24*IF(AND(ISNUMBER(SEARCH(TEXT(C24,"ddd"),$G$11)),Data!$F$2),$G$14,$D$14)+K24*$G$14,"") -> 742.44245 | O24: =M24+N24 -> 742.44245 | R24: =R22-R23 -> 0.39444444
B25: 8 | C25: =C24+1 -> 46284 | D25: =D24+1 -> 46284 | E25: 0.375 | F25: 0 | G25: =E25-F25 -> 0.375 | H25: 0.5 | I25: 0 | J25: =IFERROR(IF(AND(G25<>"",H25<>""),IF(G25>$B$14+TIME($C$14,($C$14-INT($C$14))*60,0),0,IF(H25>$B$14+TIME($C$14,($C$14-INT($C$14))*60,0),MIN(TIME($C$14,($C$14-INT($C$14))*60,0),($B$14+TIME($C$14,($C$14-INT($C$14))*60,0)-G25)),MIN(IF((H25-$B$14)<0,0,(H25-$B$14)),(H25-G25))))*24,"")-I25,"") -> 3 | K25: =IF(AND(G25<>"",H25<>""),((IF(G25<$B$14,MIN($B$14-G25,H25-G25),0)+IF(H25>$B$14+TIME($C$14,($C$14-INT($C$14))*60,0),MIN((H25-$B$14-TIME($C$14,($C$14-INT($C$14))*60,0)),(H25-G25)),0))*24),"") -> 0 | L25: =E25-B14 -> 0.041666667 | M25: =(D14/60)*0 -> 0 | N25: =IFERROR(J25*IF(AND(ISNUMBER(SEARCH(TEXT(C25,"ddd"),$G$11)),Data!$F$2),$G$14,$D$14)+K25*$G$14,"") -> 247.48082 | O25: =M25+N25 -> 247.48082
C26: =C25+1 -> 46285 | D26: =D25+1 -> 46285 | E26: 0 | F26: 0 | G26: =E26-F26 -> 0 | H26: 0 | I26: 0 | J26: =IFERROR(IF(AND(G26<>"",H26<>""),IF(G26>$B$14+TIME($C$14,($C$14-INT($C$14))*60,0),0,IF(H26>$B$14+TIME($C$14,($C$14-INT($C$14))*60,0),MIN(TIME($C$14,($C$14-INT($C$14))*60,0),($B$14+TIME($C$14,($C$14-INT($C$14))*60,0)-G26)),MIN(IF((H26-$B$14)<0,0,(H26-$B$14)),(H26-G26))))*24,"")-I26,"") -> 0 | K26: =IF(AND(G26<>"",H26<>""),((IF(G26<$B$14,MIN($B$14-G26,H26-G26),0)+IF(H26>$B$14+TIME($C$14,($C$14-INT($C$14))*60,0),MIN((H26-$B$14-TIME($C$14,($C$14-INT($C$14))*60,0)),(H26-G26)),0))*24),"") -> 0 | L26: 0 | M26: =(D14/60)*0 -> 0 | N26: =IFERROR(J26*IF(AND(ISNUMBER(SEARCH(TEXT(C26,"ddd"),$G$11)),Data!$F$2),$G$14,$D$14)+K26*$G$14,"") -> 0 | O26: =M26+N26 -> 0
B27: 9 | C27: =C26+1 -> 46286 | D27: =D26+1 -> 46286 | E27: 0.33333333 | F27: 0 | G27: =E27-F27 -> 0.33333333 | H27: 0.75 | I27: 1 | J27: =IFERROR(IF(AND(G27<>"",H27<>""),IF(G27>$B$14+TIME($C$14,($C$14-INT($C$14))*60,0),0,IF(H27>$B$14+TIME($C$14,($C$14-INT($C$14))*60,0),MIN(TIME($C$14,($C$14-INT($C$14))*60,0),($B$14+TIME($C$14,($C$14-INT($C$14))*60,0)-G27)),MIN(IF((H27-$B$14)<0,0,(H27-$B$14)),(H27-G27))))*24,"")-I27,"") -> 9 | K27: =IF(AND(G27<>"",H27<>""),((IF(G27<$B$14,MIN($B$14-G27,H27-G27),0)+IF(H27>$B$14+TIME($C$14,($C$14-INT($C$14))*60,0),MIN((H27-$B$14-TIME($C$14,($C$14-INT($C$14))*60,0)),(H27-G27)),0))*24),"") -> 0 | L27: 0 | M27: =(D14/60)*0 -> 0 | N27: =IFERROR(J27*IF(AND(ISNUMBER(SEARCH(TEXT(C27,"ddd"),$G$11)),Data!$F$2),$G$14,$D$14)+K27*$G$14,"") -> 742.44245 | O27: =M27+N27 -> 742.44245 | P27: =O27-N27 -> 0
B28: 10 | C28: =C27+1 -> 46287 | D28: =D27+1 -> 46287 | E28: 0.33333333 | F28: 0 | G28: =E28-F28 -> 0.33333333 | H28: 0.75 | I28: 1 | J28: =IFERROR(IF(AND(G28<>"",H28<>""),IF(G28>$B$14+TIME($C$14,($C$14-INT($C$14))*60,0),0,IF(H28>$B$14+TIME($C$14,($C$14-INT($C$14))*60,0),MIN(TIME($C$14,($C$14-INT($C$14))*60,0),($B$14+TIME($C$14,($C$14-INT($C$14))*60,0)-G28)),MIN(IF((H28-$B$14)<0,0,(H28-$B$14)),(H28-G28))))*24,"")-I28,"") -> 9 | K28: =IF(AND(G28<>"",H28<>""),((IF(G28<$B$14,MIN($B$14-G28,H28-G28),0)+IF(H28>$B$14+TIME($C$14,($C$14-INT($C$14))*60,0),MIN((H28-$B$14-TIME($C$14,($C$14-INT($C$14))*60,0)),(H28-G28)),0))*24),"") -> 0 | L28: 0 | M28: =(D14/60)*0 -> 0 | N28: =IFERROR(J28*IF(AND(ISNUMBER(SEARCH(TEXT(C28,"ddd"),$G$11)),Data!$F$2),$G$14,$D$14)+K28*$G$14,"") -> 742.44245 | O28: =M28+N28 -> 742.44245
B29: 11 | C29: =C28+1 -> 46288 | D29: =D28+1 -> 46288 | E29: 0.34513889 | F29: 0 | G29: =E29-F29 -> 0.34513889 | H29: 0.75 | I29: 1 | J29: =IFERROR(IF(AND(G29<>"",H29<>""),IF(G29>$B$14+TIME($C$14,($C$14-INT($C$14))*60,0),0,IF(H29>$B$14+TIME($C$14,($C$14-INT($C$14))*60,0),MIN(TIME($C$14,($C$14-INT($C$14))*60,0),($B$14+TIME($C$14,($C$14-INT($C$14))*60,0)-G29)),MIN(IF((H29-$B$14)<0,0,(H29-$B$14)),(H29-G29))))*24,"")-I29,"") -> 8.7166667 | K29: 2 | L29: =E29-B14 -> 0.011805556 | M29: =(D14/60)*17 -> 23.373188 | N29: =IFERROR(J29*IF(AND(ISNUMBER(SEARCH(TEXT(C29,"ddd"),$G$11)),Data!$F$2),$G$14,$D$14)+K29*$G$14,"") -> 925.30328 | O29: =M29+N29 -> 948.67647
B30: 12 | C30: =C29+1 -> 46289 | D30: =D29+1 -> 46289 | E30: 0.33333333 | F30: 0 | G30: =E30-F30 -> 0.33333333 | H30: 0.75 | I30: 1 | J30: =IFERROR(IF(AND(G30<>"",H30<>""),IF(G30>$B$14+TIME($C$14,($C$14-INT($C$14))*60,0),0,IF(H30>$B$14+TIME($C$14,($C$14-INT($C$14))*60,0),MIN(TIME($C$14,($C$14-INT($C$14))*60,0),($B$14+TIME($C$14,($C$14-INT($C$14))*60,0)-G30)),MIN(IF((H30-$B$14)<0,0,(H30-$B$14)),(H30-G30))))*24,"")-I30,"") -> 9 | K30: 2 | L30: =G30-B14 -> 0 | M30: =(D14/60)*0 -> 0 | N30: =IFERROR(J30*IF(AND(ISNUMBER(SEARCH(TEXT(C30,"ddd"),$G$11)),Data!$F$2),$G$14,$D$14)+K30*$G$14,"") -> 948.67647 | O30: =M30+N30 -> 948.67647
B31: 13 | C31: =C30+1 -> 46290 | D31: =D30+1 -> 46290 | E31: 0.33333333 | F31: 0 | G31: =E31-F31 -> 0.33333333 | H31: 0.75 | I31: 1 | J31: =IFERROR(IF(AND(G31<>"",H31<>""),IF(G31>$B$14+TIME($C$14,($C$14-INT($C$14))*60,0),0,IF(H31>$B$14+TIME($C$14,($C$14-INT($C$14))*60,0),MIN(TIME($C$14,($C$14-INT($C$14))*60,0),($B$14+TIME($C$14,($C$14-INT($C$14))*60,0)-G31)),MIN(IF((H31-$B$14)<0,0,(H31-$B$14)),(H31-G31))))*24,"")-I31,"") -> 9 | K31: 4 | L31: 0 | M31: =(D14/60)*0 -> 0 | N31: =IFERROR(J31*IF(AND(ISNUMBER(SEARCH(TEXT(C31,"ddd"),$G$11)),Data!$F$2),$G$14,$D$14)+K31*$G$14,"") -> 1154.9105 | O31: =M31+N31 -> 1154.9105
G32: Total Hours | I32: =SUM(I17:I31) -> 11 | J32: =SUM(J17:J31) -> 95.433333 | K32: =SUM(K17:K31) -> 12 | L32: =SUM(L17:L31) -> 0.10694444 | M32: =SUM(M17:M31) -> 46.746377 | O32: =SUM(N17:N31) -> 9110.0439
G33: Basic Pay | L33: =(D14/60)*780 -> 1072.4169 | N33: =D14*H14 -> 8661.8286 | O33: =SUM(N17:N31) -> 9110.0439
G34: Absences, Late & Undertime | J34: =H14-J32 -> 9.5666667 | N34: =M32 -> 46.746377 | O34: =O32-O33 -> 0
G35: Total Basic Pay | N35: =N33-N34 -> 8615.0822
G36: Overtime Pay & Premium | N36: =G14*K32 -> 1237.4041
G37: Holiday Pay/Premium | N37: =N53 -> 0
G38: Gross Pay | N38: =N35+N36+N37 -> 9852.4863
B41: HOLIDAY PAY
D43: Regular Holiday
D44: Year | G44: Month | H44: Date | I44: Weekend
D45: 2026 | G45: June | H45: 12 | I45: Sun Only
D47: Start Time | G47: Regular Hours | H47: Regular Pay (hourly) | I47: Overtime Pay (hourly)
D48: 0.33333333 | G48: 10 | H48: =D14 -> 82.493606 | I48: =(H48*30%)+H48 -> 107.24169
C50: Day | D50: Date | G50: In Time | H50: Out Time | I50: Break Hrs | J50: Regular Hrs | K50: OT Hours | N50: Total Pay
C51: Fri | D51: =DATE($B$11,MATCH($G$45,Data!$B$2:$B$13,0),PAREDES!$H$45) -> 46185 | G51: 0 | H51: 0 | I51: 1 | J51: =IFERROR(IF(AND(G51<>"",H51<>""),IF(G51>$B$14+TIME($C$14,($C$14-INT($C$14))*60,0),0,IF(H51>$B$14+TIME($C$14,($C$14-INT($C$14))*60,0),MIN(TIME($C$14,($C$14-INT($C$14))*60,0),($B$14+TIME($C$14,($C$14-INT($C$14))*60,0)-G51)),MIN(IF((H51-$B$14)<0,0,(H51-$B$14)),(H51-G51))))*24,"")-I51,"") -> -1 | K51: 0 | N51: 0
N53: =SUM(N51:N52) -> 0
C55: Special (Non-working) Day
D57: 45581 | G57: 742.44 | H57: BASIC PAY/DAY
G58: =G57*H58 -> 222.732 | H58: 0.3
C70: LYN M. BELTRAN
C71: Admin Manager

Sheet ELEAZAR
C7: Employee Name: | G7: CHIARA NORFIE ELEAZAR | K7: Period: | M7: =PAALAN!L7 -> September 11-25, 2026
C8: Position: | G8: Admin Asst. | K8: Payroll Date: | M8: =PAALAN!L8 -> 9/31/2026
B10: Year | C10: Month | D10: Date | G10: Weekend
B11: 2026 | C11: September | D11: 11 | G11: Sun Only
B13: Start Time | C13: Regular Hours | D13: Regular Pay (hourly) | G13: Overtime Pay (hourly) | H13: Total # of Hours per Cut off | O13: Start Time | P13: Regular Hours | Q13: Regular Pay (hourly) | T13: Overtime Pay (hourly) | U13: Total # of Hours per Cut off
B14: 0.33333333 | C14: 10 | D14: =(13000/26)/8 -> 62.5 | G14: =(D14*25%)+D14 -> 78.125 | H14: 105 | O14: 0.375 | P14: 3 | Q14: =(16082.56/26)/8 -> 77.32 | T14: =(Q14*25%)+Q14 -> 96.65 | U14: 99
C16: Day | D16: Date | G16: In Time | H16: Out Time | I16: Break Hrs | J16: Regular Hrs | K16: OT Hours | L16: Late | M16: Late Amount | N16: Total Pay
B17: 1 | C17: =DATE($B$11,MATCH($C$11,Data!$B$2:$B$13,0),ELEAZAR!$D$11) -> 46276 | D17: =DATE($B$11,MATCH($C$11,Data!$B$2:$B$13,0),ELEAZAR!$D$11) -> 46276 | E17: 0 | F17: 0 | G17: =E17-F17 -> 0 | H17: 0 | I17: 0 | J17: =IFERROR(IF(AND(G17<>"",H17<>""),IF(G17>$B$14+TIME($C$14,($C$14-INT($C$14))*60,0),0,IF(H17>$B$14+TIME($C$14,($C$14-INT($C$14))*60,0),MIN(TIME($C$14,($C$14-INT($C$14))*60,0),($B$14+TIME($C$14,($C$14-INT($C$14))*60,0)-G17)),MIN(IF((H17-$B$14)<0,0,(H17-$B$14)),(H17-G17))))*24,"")-I17,"") -> 0 | K17: 0 | L17: 0 | M17: =(D14/60)*540 -> 562.5 | N17: =IFERROR(J17*IF(AND(ISNUMBER(SEARCH(TEXT(C17,"ddd"),$G$11)),Data!$F$2),$G$14,$D$14)+K17*$G$14,"") -> 0 | O17: =M17+N17 -> 562.5
B18: 2 | C18: =C17+1 -> 46277 | D18: =D17+1 -> 46277 | E18: 0 | F18: 0 | G18: =E18-F18 -> 0 | H18: 0 | I18: 0 | J18: =IFERROR(IF(AND(G18<>"",H18<>""),IF(G18>$B$14+TIME($C$14,($C$14-INT($C$14))*60,0),0,IF(H18>$B$14+TIME($C$14,($C$14-INT($C$14))*60,0),MIN(TIME($C$14,($C$14-INT($C$14))*60,0),($B$14+TIME($C$14,($C$14-INT($C$14))*60,0)-G18)),MIN(IF((H18-$B$14)<0,0,(H18-$B$14)),(H18-G18))))*24,"")-I18,"") -> 0 | K18: 0 | L18: 0 | M18: =(D14/60)*180 -> 187.5 | N18: =IFERROR(J18*IF(AND(ISNUMBER(SEARCH(TEXT(C18,"ddd"),$G$11)),Data!$F$2),$G$14,$D$14)+K18*$G$14,"") -> 0 | O18: =M18+N18 -> 187.5
C19: =C18+1 -> 46278 | D19: =D18+1 -> 46278 | E19: 0 | F19: 0 | G19: =E19-F19 -> 0 | H19: 0 | I19: 0 | J19: =IFERROR(IF(AND(G19<>"",H19<>""),IF(G19>$B$14+TIME($C$14,($C$14-INT($C$14))*60,0),0,IF(H19>$B$14+TIME($C$14,($C$14-INT($C$14))*60,0),MIN(TIME($C$14,($C$14-INT($C$14))*60,0),($B$14+TIME($C$14,($C$14-INT($C$14))*60,0)-G19)),MIN(IF((H19-$B$14)<0,0,(H19-$B$14)),(H19-G19))))*24,"")-I19,"") -> 0 | K19: 0 | L19: 0 | M19: =(D14/60)*0 -> 0 | N19: =IFERROR(J19*IF(AND(ISNUMBER(SEARCH(TEXT(C19,"ddd"),$G$11)),Data!$F$2),$G$14,$D$14)+K19*$G$14,"") -> 0 | O19: =M19+N19 -> 0
B20: 3 | C20: =C19+1 -> 46279 | D20: =D19+1 -> 46279 | E20: 0 | F20: 0 | G20: =E20-F20 -> 0 | H20: 0 | I20: 0 | J20: =IFERROR(IF(AND(G20<>"",H20<>""),IF(G20>$B$14+TIME($C$14,($C$14-INT($C$14))*60,0),0,IF(H20>$B$14+TIME($C$14,($C$14-INT($C$14))*60,0),MIN(TIME($C$14,($C$14-INT($C$14))*60,0),($B$14+TIME($C$14,($C$14-INT($C$14))*60,0)-G20)),MIN(IF((H20-$B$14)<0,0,(H20-$B$14)),(H20-G20))))*24,"")-I20,"") -> 0 | K20: =IF(AND(G20<>"",H20<>""),((IF(G20<$B$14,MIN($B$14-G20,H20-G20),0)+IF(H20>$B$14+TIME($C$14,($C$14-INT($C$14))*60,0),MIN((H20-$B$14-TIME($C$14,($C$14-INT($C$14))*60,0)),(H20-G20)),0))*24),"") -> 0 | L20: 0 | M20: =(D14/60)*540 -> 562.5 | N20: =IFERROR(J20*IF(AND(ISNUMBER(SEARCH(TEXT(C20,"ddd"),$G$11)),Data!$F$2),$G$14,$D$14)+K20*$G$14,"") -> 0 | O20: =M20+N20 -> 562.5
B21: 4 | C21: =C20+1 -> 46280 | D21: =D20+1 -> 46280 | E21: 0 | F21: 0 | G21: =E21-F21 -> 0 | H21: 0 | I21: 0 | J21: =IFERROR(IF(AND(G21<>"",H21<>""),IF(G21>$B$14+TIME($C$14,($C$14-INT($C$14))*60,0),0,IF(H21>$B$14+TIME($C$14,($C$14-INT($C$14))*60,0),MIN(TIME($C$14,($C$14-INT($C$14))*60,0),($B$14+TIME($C$14,($C$14-INT($C$14))*60,0)-G21)),MIN(IF((H21-$B$14)<0,0,(H21-$B$14)),(H21-G21))))*24,"")-I21,"") -> 0 | K21: =IF(AND(G21<>"",H21<>""),((IF(G21<$B$14,MIN($B$14-G21,H21-G21),0)+IF(H21>$B$14+TIME($C$14,($C$14-INT($C$14))*60,0),MIN((H21-$B$14-TIME($C$14,($C$14-INT($C$14))*60,0)),(H21-G21)),0))*24),"") -> 0 | L21: 0 | M21: =(D14/60)*540 -> 562.5 | N21: =IFERROR(J21*IF(AND(ISNUMBER(SEARCH(TEXT(C21,"ddd"),$G$11)),Data!$F$2),$G$14,$D$14)+K21*$G$14,"") -> 0 | O21: =M21+N21 -> 562.5
B22: 5 | C22: =C21+1 -> 46281 | D22: =D21+1 -> 46281 | E22: 0 | F22: 0 | G22: =E22-F22 -> 0 | H22: 0 | I22: 0 | J22: =IFERROR(IF(AND(G22<>"",H22<>""),IF(G22>$B$14+TIME($C$14,($C$14-INT($C$14))*60,0),0,IF(H22>$B$14+TIME($C$14,($C$14-INT($C$14))*60,0),MIN(TIME($C$14,($C$14-INT($C$14))*60,0),($B$14+TIME($C$14,($C$14-INT($C$14))*60,0)-G22)),MIN(IF((H22-$B$14)<0,0,(H22-$B$14)),(H22-G22))))*24,"")-I22,"") -> 0 | K22: =IF(AND(G22<>"",H22<>""),((IF(G22<$B$14,MIN($B$14-G22,H22-G22),0)+IF(H22>$B$14+TIME($C$14,($C$14-INT($C$14))*60,0),MIN((H22-$B$14-TIME($C$14,($C$14-INT($C$14))*60,0)),(H22-G22)),0))*24),"") -> 0 | L22: 0 | M22: =(D14/60)*540 -> 562.5 | N22: =IFERROR(J22*IF(AND(ISNUMBER(SEARCH(TEXT(C22,"ddd"),$G$11)),Data!$F$2),$G$14,$D$14)+K22*$G$14,"") -> 0 | O22: =M22+N22 -> 562.5 | P22: =O21-O22 -> 0 | R22: 0.40486111
B23: 6 | C23: =C22+1 -> 46282 | D23: =D22+1 -> 46282 | E23: 0 | F23: 0 | G23: =E23-F23 -> 0 | H23: 0 | I23: 0 | J23: =IFERROR(IF(AND(G23<>"",H23<>""),IF(G23>$B$14+TIME($C$14,($C$14-INT($C$14))*60,0),0,IF(H23>$B$14+TIME($C$14,($C$14-INT($C$14))*60,0),MIN(TIME($C$14,($C$14-INT($C$14))*60,0),($B$14+TIME($C$14,($C$14-INT($C$14))*60,0)-G23)),MIN(IF((H23-$B$14)<0,0,(H23-$B$14)),(H23-G23))))*24,"")-I23,"") -> 0 | K23: 0 | L23: 0 | M23: =(D14/60)*540 -> 562.5 | N23: =IFERROR(J23*IF(AND(ISNUMBER(SEARCH(TEXT(C23,"ddd"),$G$11)),Data!$F$2),$G$14,$D$14)+K23*$G$14,"") -> 0 | O23: =M23+N23 -> 562.5 | R23: 0.010416667
B24: 7 | C24: =C23+1 -> 46283 | D24: =D23+1 -> 46283 | E24: 0 | F24: 0 | G24: =E24-F24 -> 0 | H24: 0 | I24: 0 | J24: =IFERROR(IF(AND(G24<>"",H24<>""),IF(G24>$B$14+TIME($C$14,($C$14-INT($C$14))*60,0),0,IF(H24>$B$14+TIME($C$14,($C$14-INT($C$14))*60,0),MIN(TIME($C$14,($C$14-INT($C$14))*60,0),($B$14+TIME($C$14,($C$14-INT($C$14))*60,0)-G24)),MIN(IF((H24-$B$14)<0,0,(H24-$B$14)),(H24-G24))))*24,"")-I24,"") -> 0 | K24: 0 | L24: 0 | M24: =(D14/60)*540 -> 562.5 | N24: =IFERROR(J24*IF(AND(ISNUMBER(SEARCH(TEXT(C24,"ddd"),$G$11)),Data!$F$2),$G$14,$D$14)+K24*$G$14,"") -> 0 | O24: =M24+N24 -> 562.5 | R24: =R22-R23 -> 0.39444444
B25: 8 | C25: =C24+1 -> 46284 | D25: =D24+1 -> 46284 | E25: 0 | F25: 0 | G25: =E25-F25 -> 0 | H25: 0 | I25: 0 | J25: =IFERROR(IF(AND(G25<>"",H25<>""),IF(G25>$B$14+TIME($C$14,($C$14-INT($C$14))*60,0),0,IF(H25>$B$14+TIME($C$14,($C$14-INT($C$14))*60,0),MIN(TIME($C$14,($C$14-INT($C$14))*60,0),($B$14+TIME($C$14,($C$14-INT($C$14))*60,0)-G25)),MIN(IF((H25-$B$14)<0,0,(H25-$B$14)),(H25-G25))))*24,"")-I25,"") -> 0 | K25: =IF(AND(G25<>"",H25<>""),((IF(G25<$B$14,MIN($B$14-G25,H25-G25),0)+IF(H25>$B$14+TIME($C$14,($C$14-INT($C$14))*60,0),MIN((H25-$B$14-TIME($C$14,($C$14-INT($C$14))*60,0)),(H25-G25)),0))*24),"") -> 0 | L25: 0 | M25: =(D14/60)*180 -> 187.5 | N25: =IFERROR(J25*IF(AND(ISNUMBER(SEARCH(TEXT(C25,"ddd"),$G$11)),Data!$F$2),$G$14,$D$14)+K25*$G$14,"") -> 0 | O25: =M25+N25 -> 187.5
C26: =C25+1 -> 46285 | D26: =D25+1 -> 46285 | E26: 0 | F26: 0 | G26: =E26-F26 -> 0 | H26: 0 | I26: 0 | J26: =IFERROR(IF(AND(G26<>"",H26<>""),IF(G26>$B$14+TIME($C$14,($C$14-INT($C$14))*60,0),0,IF(H26>$B$14+TIME($C$14,($C$14-INT($C$14))*60,0),MIN(TIME($C$14,($C$14-INT($C$14))*60,0),($B$14+TIME($C$14,($C$14-INT($C$14))*60,0)-G26)),MIN(IF((H26-$B$14)<0,0,(H26-$B$14)),(H26-G26))))*24,"")-I26,"") -> 0 | K26: =IF(AND(G26<>"",H26<>""),((IF(G26<$B$14,MIN($B$14-G26,H26-G26),0)+IF(H26>$B$14+TIME($C$14,($C$14-INT($C$14))*60,0),MIN((H26-$B$14-TIME($C$14,($C$14-INT($C$14))*60,0)),(H26-G26)),0))*24),"") -> 0 | L26: 0 | M26: =(D14/60)*0 -> 0 | N26: =IFERROR(J26*IF(AND(ISNUMBER(SEARCH(TEXT(C26,"ddd"),$G$11)),Data!$F$2),$G$14,$D$14)+K26*$G$14,"") -> 0 | O26: =M26+N26 -> 0
B27: 9 | C27: =C26+1 -> 46286 | D27: =D26+1 -> 46286 | E27: 0.33333333 | F27: 0 | G27: =E27-F27 -> 0.33333333 | H27: 0.75 | I27: 1 | J27: =IFERROR(IF(AND(G27<>"",H27<>""),IF(G27>$B$14+TIME($C$14,($C$14-INT($C$14))*60,0),0,IF(H27>$B$14+TIME($C$14,($C$14-INT($C$14))*60,0),MIN(TIME($C$14,($C$14-INT($C$14))*60,0),($B$14+TIME($C$14,($C$14-INT($C$14))*60,0)-G27)),MIN(IF((H27-$B$14)<0,0,(H27-$B$14)),(H27-G27))))*24,"")-I27,"") -> 9 | K27: =IF(AND(G27<>"",H27<>""),((IF(G27<$B$14,MIN($B$14-G27,H27-G27),0)+IF(H27>$B$14+TIME($C$14,($C$14-INT($C$14))*60,0),MIN((H27-$B$14-TIME($C$14,($C$14-INT($C$14))*60,0)),(H27-G27)),0))*24),"") -> 0 | L27: 0 | M27: =(D14/60)*0 -> 0 | N27: =IFERROR(J27*IF(AND(ISNUMBER(SEARCH(TEXT(C27,"ddd"),$G$11)),Data!$F$2),$G$14,$D$14)+K27*$G$14,"") -> 562.5 | O27: =M27+N27 -> 562.5
B28: 10 | C28: =C27+1 -> 46287 | D28: =D27+1 -> 46287 | E28: 0.33333333 | F28: 0 | G28: =E28-F28 -> 0.33333333 | H28: 0.75 | I28: 1 | J28: =IFERROR(IF(AND(G28<>"",H28<>""),IF(G28>$B$14+TIME($C$14,($C$14-INT($C$14))*60,0),0,IF(H28>$B$14+TIME($C$14,($C$14-INT($C$14))*60,0),MIN(TIME($C$14,($C$14-INT($C$14))*60,0),($B$14+TIME($C$14,($C$14-INT($C$14))*60,0)-G28)),MIN(IF((H28-$B$14)<0,0,(H28-$B$14)),(H28-G28))))*24,"")-I28,"") -> 9 | K28: =IF(AND(G28<>"",H28<>""),((IF(G28<$B$14,MIN($B$14-G28,H28-G28),0)+IF(H28>$B$14+TIME($C$14,($C$14-INT($C$14))*60,0),MIN((H28-$B$14-TIME($C$14,($C$14-INT($C$14))*60,0)),(H28-G28)),0))*24),"") -> 0 | L28: 0 | M28: =(D14/60)*0 -> 0 | N28: =IFERROR(J28*IF(AND(ISNUMBER(SEARCH(TEXT(C28,"ddd"),$G$11)),Data!$F$2),$G$14,$D$14)+K28*$G$14,"") -> 562.5 | O28: =M28+N28 -> 562.5
B29: 11 | C29: =C28+1 -> 46288 | D29: =D28+1 -> 46288 | E29: 0.33333333 | F29: 0 | G29: =E29-F29 -> 0.33333333 | H29: 0.75 | I29: 1 | J29: =IFERROR(IF(AND(G29<>"",H29<>""),IF(G29>$B$14+TIME($C$14,($C$14-INT($C$14))*60,0),0,IF(H29>$B$14+TIME($C$14,($C$14-INT($C$14))*60,0),MIN(TIME($C$14,($C$14-INT($C$14))*60,0),($B$14+TIME($C$14,($C$14-INT($C$14))*60,0)-G29)),MIN(IF((H29-$B$14)<0,0,(H29-$B$14)),(H29-G29))))*24,"")-I29,"") -> 9 | K29: 0 | L29: 0 | M29: =(D14/60)*0 -> 0 | N29: =IFERROR(J29*IF(AND(ISNUMBER(SEARCH(TEXT(C29,"ddd"),$G$11)),Data!$F$2),$G$14,$D$14)+K29*$G$14,"") -> 562.5 | O29: =M29+N29 -> 562.5 | P29: =O28-O29 -> 0
B30: 12 | C30: =C29+1 -> 46289 | D30: =D29+1 -> 46289 | E30: 0.33333333 | F30: 0 | G30: =E30-F30 -> 0.33333333 | H30: 0.75 | I30: 1 | J30: =IFERROR(IF(AND(G30<>"",H30<>""),IF(G30>$B$14+TIME($C$14,($C$14-INT($C$14))*60,0),0,IF(H30>$B$14+TIME($C$14,($C$14-INT($C$14))*60,0),MIN(TIME($C$14,($C$14-INT($C$14))*60,0),($B$14+TIME($C$14,($C$14-INT($C$14))*60,0)-G30)),MIN(IF((H30-$B$14)<0,0,(H30-$B$14)),(H30-G30))))*24,"")-I30,"") -> 9 | K30: 2 | L30: =E30-B14 -> 0 | M30: =(D14/60)*0 -> 0 | N30: =IFERROR(J30*IF(AND(ISNUMBER(SEARCH(TEXT(C30,"ddd"),$G$11)),Data!$F$2),$G$14,$D$14)+K30*$G$14,"") -> 718.75 | O30: =M30+N30 -> 718.75
B31: 13 | C31: =C30+1 -> 46290 | D31: =D30+1 -> 46290 | E31: 0.33333333 | F31: 0 | G31: =E31-F31 -> 0.33333333 | H31: 0.75 | I31: 1 | J31: =IFERROR(IF(AND(G31<>"",H31<>""),IF(G31>$B$14+TIME($C$14,($C$14-INT($C$14))*60,0),0,IF(H31>$B$14+TIME($C$14,($C$14-INT($C$14))*60,0),MIN(TIME($C$14,($C$14-INT($C$14))*60,0),($B$14+TIME($C$14,($C$14-INT($C$14))*60,0)-G31)),MIN(IF((H31-$B$14)<0,0,(H31-$B$14)),(H31-G31))))*24,"")-I31,"") -> 9 | K31: 4 | L31: =E31-B14 -> 0 | M31: =(D14/60)*0 -> 0 | N31: =IFERROR(J31*IF(AND(ISNUMBER(SEARCH(TEXT(C31,"ddd"),$G$11)),Data!$F$2),$G$14,$D$14)+K31*$G$14,"") -> 875 | O31: =M31+N31 -> 875 | P31: =O28-O31 -> -312.5
G32: Total Hours | I32: =SUM(I17:I31) -> 5 | J32: =SUM(J17:J31) -> 45 | K32: =SUM(K17:K31) -> 6 | L32: =SUM(L17:L31) -> 0 | M32: =SUM(M17:M31) -> 3750 | O32: =SUM(O17:O31) -> 7031.25 | P32: =SUM(P17:P31) -> -312.5 | Q32: =O32+P32 -> 6718.75
G33: Basic Pay | L33: =(D14/60)*0 -> 0 | N33: =D14*H14 -> 6562.5
G34: Absences, Late & Undertime | J34: =H14-J32 -> 60 | N34: =M32 -> 3750 | O34: =O32-O33 -> 7031.25
G35: Total Basic Pay | N35: =N33-N34 -> 2812.5
G36: Overtime Pay & Premium | N36: =G14*K32 -> 468.75
G37: Holiday Pay/Premium | N37: =N53 -> 0
G38: Gross Pay | N38: =N35+N36+N37 -> 3281.25
B41: HOLIDAY PAY
D43: Regular Holiday
D44: Year | G44: Month | H44: Date | I44: Weekend
D45: 2026 | G45: March | H45: 20 | I45: Sat & Sun
D47: Start Time | G47: Regular Hours | H47: Regular Pay (hourly) | I47: Overtime Pay (hourly)
D48: 0.33333333 | G48: 10 | H48: =D14 -> 62.5 | I48: =(H48*30%)+H48 -> 81.25
C50: Day | D50: Date | G50: In Time | H50: Out Time | I50: Break Hrs | J50: Regular Hrs | K50: OT Hours | N50: Total Pay
C51: Fri | D51: 46101 | G51: 0.33333333 | H51: 0.75 | I51: 1 | J51: =IFERROR(IF(AND(G51<>"",H51<>""),IF(G51>$B$14+TIME($C$14,($C$14-INT($C$14))*60,0),0,IF(H51>$B$14+TIME($C$14,($C$14-INT($C$14))*60,0),MIN(TIME($C$14,($C$14-INT($C$14))*60,0),($B$14+TIME($C$14,($C$14-INT($C$14))*60,0)-G51)),MIN(IF((H51-$B$14)<0,0,(H51-$B$14)),(H51-G51))))*24,"")-I51,"") -> 9 | K51: =IF(AND(G51<>"",H51<>""),((IF(G51<$D$48,MIN($D$48-G51,H51-G51),0)+IF(H51>$D$48+TIME($G$48,($G$48-INT($G$48))*60,0),MIN((H51-$D$48-TIME($G$48,($G$48-INT($G$48))*60,0)),(H51-G51)),0))*24),"") -> 0 | N51: =(J51*H48)+562.5*30% -> 731.25
C52: Tue | D52: 23 | G52: 0 | H52: 0 | I52: 0 | J52: =IFERROR(IF(AND(G52<>"",H52<>""),IF(G52>$B$14+TIME($C$14,($C$14-INT($C$14))*60,0),0,IF(H52>$B$14+TIME($C$14,($C$14-INT($C$14))*60,0),MIN(TIME($C$14,($C$14-INT($C$14))*60,0),($B$14+TIME($C$14,($C$14-INT($C$14))*60,0)-G52)),MIN(IF((H52-$B$14)<0,0,(H52-$B$14)),(H52-G52))))*24,"")-I52,"") -> 0 | K52: =IF(AND(G52<>"",H52<>""),((IF(G52<$D$48,MIN($D$48-G52,H52-G52),0)+IF(H52>$D$48+TIME($G$48,($G$48-INT($G$48))*60,0),MIN((H52-$D$48-TIME($G$48,($G$48-INT($G$48))*60,0)),(H52-G52)),0))*24),"") -> 0 | N52: 0
D56: 46255 | G56: 562.5 | H56: BASIC PAY/DAY
G57: =G56*H57 -> 168.75 | H57: 0.3
H59: =G57 -> 168.75
C67: LYN M. BELTRAN
C68: Admin Manager

Sheet BUNGAY
C7: Employee Name: | G7: JANELLE BUNGAY | K7: Period: | M7: =PAALAN!L7 -> September 11-25, 2026
C8: Position: | G8: Project Technical Staff | K8: Payroll Date: | M8: =PAALAN!L8 -> 9/31/2026
B10: Year | C10: Month | D10: Date | G10: Weekend
B11: 2026 | C11: September | D11: 11 | G11: Sun Only
B13: Start Time | C13: Regular Hours | D13: Regular Pay (hourly) | G13: Overtime Pay (hourly) | H13: Total # of Hours per Cut off | O13: Start Time | P13: Regular Hours | Q13: Regular Pay (hourly) | T13: Overtime Pay (hourly) | U13: Total # of Hours per Cut off
B14: 0.33333333 | C14: 10 | D14: =(13000/26)/8 -> 62.5 | G14: =(D14*25%)+D14 -> 78.125 | H14: 105 | O14: 0.375 | P14: 3 | Q14: =(16082.56/26)/8 -> 77.32 | T14: =(Q14*25%)+Q14 -> 96.65 | U14: 99
C16: Day | D16: Date | G16: In Time | H16: Out Time | I16: Break Hrs | J16: Regular Hrs | K16: OT Hours | L16: Late | M16: Late Amount | N16: Total Pay
B17: 1 | C17: =DATE($B$11,MATCH($C$11,Data!$B$2:$B$13,0),BUNGAY!$D$11) -> 46276 | D17: =DATE($B$11,MATCH($C$11,Data!$B$2:$B$13,0),BUNGAY!$D$11) -> 46276 | E17: 0.33333333 | F17: 0 | G17: =E17-F17 -> 0.33333333 | H17: 0.75 | I17: 1 | J17: =IFERROR(IF(AND(G17<>"",H17<>""),IF(G17>$B$14+TIME($C$14,($C$14-INT($C$14))*60,0),0,IF(H17>$B$14+TIME($C$14,($C$14-INT($C$14))*60,0),MIN(TIME($C$14,($C$14-INT($C$14))*60,0),($B$14+TIME($C$14,($C$14-INT($C$14))*60,0)-G17)),MIN(IF((H17-$B$14)<0,0,(H17-$B$14)),(H17-G17))))*24,"")-I17,"") -> 9 | K17: 0 | L17: =E17-B14 -> 0 | M17: =(D14/60)*0 -> 0 | N17: =IFERROR(J17*IF(AND(ISNUMBER(SEARCH(TEXT(C17,"ddd"),$G$11)),Data!$F$2),$G$14,$D$14)+K17*$G$14,"") -> 562.5 | O17: =M17+N17 -> 562.5
